Workbook

Sheet Deckblatt
C9: Reifegradmodell für die Technische Dokumentation
C26: Erstellt durch: | E26: Christian Koch
C27: Version: | E27: 2.0
C28: Letzte Änderung: | E28: 45994
C29: Credit: | E29: Victor Wolf

Sheet Einführung
B6: Willkommen zum Reifegradmodell für die Technische Dokumentation
B9: Das Reifegradmodell ist ein fragenbasiertes Tool zur Erhebung der Reifegrade der technischen Dokumentation. Es wurde entwickelt, um Unternehmen eine Hilfestellung bei der nachhaltigen Weiterentwicklung der technischen Dokumentation zu geben.
B10: Das Reifegradmodell basiert auf Ergebnissen einer Recherche zu bestehenden Reifegradmodellen sowie der Auswertung von Interviews. Das RGM besteht aus 33 Subdimmensionen, aufgeteilt auf 8 Dimensionen und ist modellhaft zu verstehen. Dies bedeutet, dass die Aspekte der Dimensionen je nach Organisation unterschiedlich interpretiert werden können. Die Nutzenden sind herzlich dazu eingeladen, eigene, unternehmensspezifische Punkte zu ergänzen.
B11: Kontaktdaten für Feedback und Fragen: christian4.koch@tu-dortmund.de
B12: Das Tool deckt die folgenden Bereiche ab. Die jeweiligen Betrachtungsobjekte sind farblich hervorgehoben.
B13: Technische Dokumentation (TD):
B14: Relevante Themenbereiche der technischen Dokumentation.
B16: Organisation (OG):
B17: Relevante Themenbereiche der Organisation, die mit der technischen Dokumentation in Verbindung stehen bzw. diese beeinflussen.

Sheet Dashboard
B6: Dashboard
C10: Name der Organisation: | G10: Datum der Durchführung:
C12: Beispiel GmbH | G12: TT.MM.JJJJ
C14: Bereich:
C16: Bereich A
C18: Erhebung durchgeführt von: | G18: Angestrebtes Ziel:
C20: Herr/Frau Beispiel | G20: Quantitativ gemanagt
B23: Visualisiertes Ergebnis der Reifegraderhebung: | L23: Ergebnis in Tabellenform:
M27: Kürzel | N27: Themenbereich | O27: Reifegrad | P27: Link
M28: {=Data!B3:C35} -> TD1.1 | N28: Prozessinitierung | O28: =Data!D3 -> 0 | P28: Hier klicken
M29: TD1.2 | N29: Informationsbeschaffung | O29: =Data!D4 -> 0 | P29: Hier klicken
M30: TD1.3 | N30: Interne Zusammenarbeit | O30: =Data!D5 -> 0 | P30: Hier klicken
M31: TD1.4 | N31: Externe Zusammenarbeit | O31: =Data!D6 -> 0 | P31: Hier klicken
M32: TD1.5 | N32: Rechtskonformität | O32: =Data!D7 -> 0 | P32: Hier klicken
M33: TD1.6 | N33: Qualitätssicherung | O33: =Data!D8 -> 0 | P33: Hier klicken
M34: TD2.1 | N34: Dokumentationsstrukturierung | O34: =Data!D9 -> 0 | P34: Hier klicken
M35: TD2.2 | N35: Variantenmanagement | O35: =Data!D10 -> 0 | P35: Hier klicken
M36: TD2.3 | N36: Metadatenmanagement | O36: =Data!D11 -> 0 | P36: Hier klicken
M37: TD2.4 | N37: Terminologiemanagement | O37: =Data!D12 -> 0 | P37: Hier klicken
M38: TD2.5 | N38: Übersetzungsmanagement | O38: =Data!D13 -> 0 | P38: Hier klicken
M39: TD2.6 | N39: Aktualität | O39: =Data!D14 -> 0 | P39: Hier klicken
M40: TD2.7 | N40: Versionierung | O40: =Data!D15 -> 0 | P40: Hier klicken
... M60: OG4.4 | N60: Produktions-IT-Infrastruktur | O60: =Data!D35 -> 0 | P60: Hier klicken
M63: Legende:
M64: 1 - initial
M65: 2 - Gemanagt
M66: 3 - Definiert
M67: 4 - Quantitativ gemanagt
M68: 5 - Optimiert

Sheet Ausfüllhinweise
B6: Ausfüllhinweise zum Reifegradmodell
B9: Anhand des Reifegradmodells ist eine rasche und einheitliche Bestimmung von Reifegraden der technischen Dokumentation möglich. Hierzu werden je Subdimension spezifische Fragestellungen beantwortet. Das Reifegradmodell orientiert sich an den Reifegradstufen der Capability Maturity Model Integration (CMMI).
B11: Beschreibung der Reifegradstufen:
C13: Reifegradstufe | D13: Beschreibung
C14: 1 - initial | D14: Prozesse bleiben unvorhersehbar und reaktiv. Der Erfolg auf dieser Ebene hängt hauptsächlich von den individuellen Anstrengungen und nicht von etablierten organisatorischen Prozessen ab.
C15: 2 - gemanagt | D15: Organisationen auf dieser Ebene etablieren grundlegende Projektmanagementpraktiken. Projekte folgen grundlegenden Planungs- und Kontrollmechanismen und führen so zu vorhersehbareren Ergebnissen.
C16: 3 - definiert | D16: Diese Ebene markiert einen deutlichen Wandel hin zu einer unternehmensweiten Prozessstandardisierung. Auf dieser Ebene werden einheitliche Vorgehensweisen in der gesamten Organisation etabliert und die Variabilität bei der Projektausführung verringert.
C17: 4 - quantitativ gemanagt | D17: Organisationen erreichen eine präzise Prozesskontrolle. Projekte arbeiten mit einem hohen Maß an Vorhersehbarkeit und nutzen Kennzahlen zur Verwaltung der Prozess- und Produktqualität.
C18: 5 - optimiert | D18: Organisationen auf dieser Ebene verbessern ihre Prozesse systematisch durch inkrementelle und innovative Änderungen.
B20: Um eine inhaltliche Abgrenzung zwischen den jeweiligen Reifegradstufen zu ermöglichen, werden Schlüsselwörter verwendet. Diese werden nachfolgend erläutert.
B22: Beschreibung der Schlüsselwörter:
C24: Schlüsselwort | D24: Interpretation/Bedeutung
C25: Situativ/Ad-Hoc | D25: Der Prozess wird anlassbezogen durchgeführt und beispielsweise durch externe Trigger angestoßen.
C26: Gelegentlich | D26: Der Prozess wird zwar wiederholt durchgeführt, jedoch ohne fest definiertes Intervall.
C27: Regelmäßig | D27: Der Prozess wird in einem fest definierten Intervall durchgeführt.
C28: Regelmäßig überprüft | D28: Die Einhaltung der fest definierten Intervalle wird mit Hilfe von Kennzahlen gesteuert.
C29: Kontinuierlich verbessert | D29: Der Prozess wird durch die durchführenden Mitarbeiter kontinuierlich verbessert.
B31: Zur Identifikation der Reifegrade werden spezifische Fragestellungen definiert. Die Antwortmöglichkeiten spiegeln den Umsetzungsgrad des jeweiligen Prüfkriterium wieder. Basierend auf der Konsolidierung der Antworten wird der Reifegrad des betrachteten Prozessbereich identifiziert. Das methodische Basismodell zur Identifikation der Reifegrade ist die Normreihe ISO/IEC 330xx.
B33: Beschreibung der Antwortmöglichkeiten
C35: Antwort | D35: Umsetzungsgrad | E35: Beschreibung
C36: Nicht anwendbar | D36: / | E36: Das Prüfkriterium ist nicht auf die Organisation anwendbar. Sollten alle Fragen einer Stufe nicht anwendbar sein, verbleibt der Reifegradauf der darunter liegenden Stufe bzw. als #NV.
C37: Gar nicht | D37: 0% - 15% | E37: Es gibt keinen Nachweis für die Erreichung des Prüfkriteriums.
C38: In ein Paar Fällen | D38: >15% - 50% | E38: Es bestehen teilweise Anzeichen für die Erreichung des Prüfkriteriums.
C39: In den meisten Fällen | D39: >50% - 85% | E39: Es gibt signifikante Anzeichen für die Erreichung des Prüfkriteriums.
C40: Vollständig | D40: >85% - 100% | E40: Es gibt einen vollständigen Nachweis für die Erreichung des Prüfkriteriums.
C42: WICHTIG!
C43: Bitte beachten Sie:
C44: Die Fragen des Reifegradmodells sind so formuliert, dass jede Reifegradstufe auf den vorhergehenden Stufen aufbaut. Das bedeutet: Wenn Ihre Organisation eine höhere Stufe bereits erreicht hat und der beschriebene Zustand einer niedrigeren Stufe dadurch überwunden wurde (z. B. Varianten werden nicht mehr manuell gepflegt), ist die Frage dennoch mit „Vollständig“ zu beantworten. „Vollständig“ bedeutet in diesem Zusammenhang: Der beschriebene Zustand dieser Stufe wurde vollständig erreicht oder übertroffen. Antworten wie „Gar nicht“, „In ein paar Fällen“ oder „In den meisten Fällen“ würden fälschlicherweise anzeigen, dass diese Stufe noch nicht erfüllt ist.

Sheet Erläuterung
B6: Erläuterung der Erhebungsblätter
C10: Überblick der Tabellenblätter:
C12: Jeder Untersuchungsgegenstand hat ein eigenes Erhebungsblatt. Die Erhebungsblätter sind nicht voneinander abhängig und können auch einzeln bearbeitet werden. Die Erhebungsblätter sind je nach Art kategorisiert: Blau: Technische Dokumentation (TD) Orange: Organisation (OG)
C15: Wichtig: Diese Reifegraderhebung zielt auf die Inhalte technischer Dokumentation ab. Sowohl das Referenzmodell als auch die einzelnen Prozesse sind schematisch zu verstehen und dienen als inhaltliche Stütze. Sie müssen weder nach diesem Schema etabliert, noch nach dieser Vorgehensweise umgesetzt werden!
C16: Ablauf der Erhebung:
C18: Zur Identifikation der Reifegrade werden spezifische Fragestellungen je Reifegrad gestellt. [1] Diese Fragen sind mit den vordefinierten Antwortmöglichkeiten zu beantworten. [2] Für jede Stufe wird der konkrete Nutzen für die Organisation dargestellt. [3] Zusätzlich besteht die Möglichkeit, einen Kommentar im Freitextfeld zu hinterlassen. [4]
C37: Weitere Informationen anzeigen lassen:
C39: [5] Durch Klicken des [+] Symbols können Sie sich zusätzliche Informationen zu den Prüffragen anzeigen lassen.
C40: [6] Durch Klicken des [+] Symbols können Sie sich den jeweiligen schematischen Prozess-Steckbrief anzeigen lassen.
C42: Wie die Reifegrade berechnet werden:
C44: Der Reifegrad für jeden Prozess wird auf der Grundlage der gegebenen Antwort berechnet und in der Bewertungs-Zelle angezeigt. [7] Die Reifegrad-Skala ist kumulativ. Die Reifegradbewertung beginnt für jeden Prozess bei 0 und arbeitet aufwärts. Jede Reifegradstufe baut auf den vorherigen Stufen auf. Damit die nächsthöhere Reifegradstufe erreicht werden kann, wird die vollständige Umsetzung der vorherigen Stufen benötigt. Das bedeutet auch, dass die Umsetzung teilweise kontra-intuitiv ausgewählt werden muss. Die Festlegung der Reifegradstufen erfolgt anhand von Abnahmekriterien. Diese sind jeder Reifegradstufe zugeordnet und beschreiben die benötigten Fähigkeiten je Reifegradstufe. Die Abnahmekriterien können unter [5] angezeigt werden.

Sheet Glossar
B6: Glossar
C10: Begriffe, die unterstrichen und in grüner Farbe dargestellt sind, sind in diesem Glossar zu finden. Mit einem Klick auf die Zelle, in der der Begriff steht, gelangt man zum Glossar.
C13: A
C14: API (Application Programmable Interface) | E14: Programmteil, der von einem Softwaresystem anderen Programmen zur Anbindung an das System zur Verfügung gestellt wird (https://de.wikipedia.org/wiki/Programmierschnittstelle)
C15: C
C16: CCMS (Component Content Management System) | E16: spezialisierte Form eines Content Management Systems (CMS), die speziell für die Verwaltung, Speicherung und Wiederverwendung von Inhalten in einer granularen Form, bekannt als Komponenten, entwickelt wurde (https://carstens-techdok.de/ccms/)
C17: CMS (Content Management System) | E17: Software oder Service zur gemeinschaftlichen Erstellung, Bearbeitung, Organisation, Darstellung und Auslieferung digitaler Inhalte (Content) zur Verwendung in Webseiten, Apps, Digital Signage und anderen Medienformen (https://de.wikipedia.org/wiki/Content-Management-System)
C18: Corporate Design | E18: Teil des Corporate Branding. Es umfasst die visuelle und sprachliche Inszenierung der Marke und dient dazu, die Identität und Werte eines Unternehmens sichtbar zu machen (https://www.syndicate.de/was-ist-corporate-design/#:~:text=Das%20Corporate%20Design%20ist%20neben,eines%20Unternehmens%20sichtbar%20zu%20machen.)
C19: Corporate Identity | E19: Gesamtheit der Merkmale, die ein Unternehmen kennzeichnet und es von anderen Unternehmen unterscheidet. Die Corporate Identity ist damit das Selbstbild des Unternehmens (https://de.wikipedia.org/wiki/Corporate_Identity)
C20: CSR (Corporate Social Responsibility) | E20: Integration von ökologischen, sozialen und wirtschaftlichen Faktoren in die Unternehmenstätigkeit auf freiwilliger und manchmal auch rechtlicher Basis. Die Aktivitäten der Unternehmen werden hier im weitesten Sinne verstanden: wirtschaftliche Aktivitäten, interne Interaktionen (Arbeitnehmer, Manager, Aktionäre) und externe Interaktionen (Lieferanten, Kunden) (https://de.wikipedia.org/wiki/Corporate_Social_Responsibility)
C21: D
C22: DMS (Document Management System) | E22: datenbankgestützte Verwaltung elektronischer Dokumente (https://de.wikipedia.org/wiki/Dokumentenmanagement)
C23: DITA (Darwin Information Typing Architecture) | E23: Dokumentenformat, ähnlich dem bekannten DocBook. DITA wird vom OASIS DITA Technical Committee als freie Architektur entwickelt und steht als Dokumenttypdefinition (DTD) kostenlos zur Verfügung. Das Format basiert auf XML: Im Gegensatz zu DocBook gibt es für DITA keine SGML-basierte Dokumenttypdefinition (DTD) (https://de.wikipedia.org/wiki/Darwin_Information_Typing_Architecture)
C24: E
C25: ECLASS | E25: Datenstandard für die Klassifizierung von Produkten und Dienstleistungen mit Hilfe von standardisierten ISO-konformen Merkmalen. Der ECLASS-Standard ermöglicht den digitalen Austausch von Produktstammdaten über Branchen, Länder, Sprachen oder Organisationen hinweg (https://de.wikipedia.org/wiki/ECLASS)
C26: ERP (Enterprise Resource Planning) | E26: unternehmerische Aufgabe, Personal, Ressourcen, Kapital, Betriebsmittel, Material sowie Informations- und Kommunikationstechnik im Sinne des Unternehmenszwecks rechtzeitig und bedarfsgerecht zu planen, zu steuern und zu verwalten. Gewährleistet werden soll ein effizienter betrieblicher Wertschöpfungsprozess und eine stetig optimierte Steuerung der unternehmerischen und betrieblichen Abläufe (https://de.wikipedia.org/wiki/Enterprise-Resource-Planning)
C27: Ethernet | E27: Technik, die Software (Protokolle usw.) und Hardware (Kabel, Verteiler, Netzwerkkarten usw.) für kabelgebundene Datennetze spezifiziert, welche ursprünglich für lokale Datennetze (LANs) gedacht war und daher auch als LAN-Technik bezeichnet wird. Sie ermöglicht den Datenaustausch in Form von Datenframes zwischen den in einem lokalen Netz (LAN) angeschlossenen Geräten (https://de.wikipedia.org/wiki/Ethernet)
C28: F
C29: Feldbus | E29: Bussystem, das in einer Anlage Feldgeräte wie Messfühler (Sensoren) und Stellglieder (Aktoren) zur Kommunikation mit einem Automatisierungsgerät verbindet. Wenn mehrere Kommunikationsteilnehmer ihre Nachrichten über dieselbe Leitung senden, dann muss festgelegt sein, wer (Kennung) was (Messwert, Befehl) wann (Initiative) sagt. Hierfür gibt es normierte Protokolle (https://de.wikipedia.org/wiki/Feldbus)
C30: H
C31: Headless Delivery | E31: bezieht sich auf eine Architektur, die das Content-Backend von der Frontend-Anzeige entkoppelt, sodass Inhalte über eine API an beliebige Kanäle und Endgeräte verteilt werden können. Im Gegensatz zu herkömmlichen Systemen wird bei Headless Delivery nur der reine Inhalt (oft als Daten wie JSON) an die Benutzeroberfläche ausgeliefert, was eine größere Flexibilität und Skalierbarkeit bei der Personalisierung von Inhalten über verschiedene Kanäle hinweg ermöglicht (https://documentation.coremedia.com/discover/api/headless-server-api/)
C32: I
C33: iiRDS (intelligent information Request and Delivery Standard) | E33: technischer Standard für die Auslieferung von digitalen Anwenderinformationen, z. B. elektronischen Betriebsanleitungen und Gebrauchsanleitungen (https://de.wikipedia.org/wiki/IiRDS)
C34: M
C35: Middleware | E35: anwendungsneutrale Programme, die so zwischen Anwendungen vermitteln, dass die Komplexität dieser Applikationen und ihre Infrastruktur verborgen werden (https://de.wikipedia.org/wiki/Middleware)
C36: Modell, semantisches | E36: im Rahmen der Datenmodellierung eine abstrakte, formale Beschreibung und Darstellung eines Ausschnittes der in einem bestimmten Zusammenhang (z. B. eines Projekts) „wahrgenommenen Welt“. Zur Formulierung semantischer Datenmodelle existieren verschiedene Modellierungssprachen, von denen das Entity-Relationship-Modell das bekannteste ist (https://de.wikipedia.org/wiki/Semantisches_Datenmodell)
C37: O
C38: Omnichannel | E38: kanalübergreifendes Geschäftsmodell für Unternehmen zum Verbessern des Kundenerfahrungsmanagements. Der Ansatz wird in den Bereichen Gesundheitswesen, Regierungsbehörden und Finanzdienstleistungen sowie in der Einzelhandels[1]- und Telekommunikationsbranche genutzt, wobei als Kanäle z. B. physische Standorte, FAQ-Webseiten, soziale Medien, Live-Webchats, mobile Anwendungen und Telefonkommunikation zum Einsatz kommen.[2][3] Unternehmen, die das Omnichannel-Konzept umsetzen, argumentieren, dass Kunden über mehrere Kanäle gleichzeitig in ständigem Kontakt mit einem Unternehmen sein möchten (https://de.wikipedia.org/wiki/Omnichannel)
C39: Ontologie | E39: sprachlich gefasste und formal geordnete Darstellungen einer Menge von Begriffen und der zwischen ihnen bestehenden Beziehungen in einem bestimmten Gegenstandsbereich (in Anlehnung an den klassischen Begriff der Ontologie). Sie werden dazu genutzt, „Wissen“ in digitalisierter und formaler Form zwischen Prozessen (oft Anwendungsprogrammen) und Diensten auszutauschen. Wissen umfasst dabei sowohl Allgemeinwissen als auch Wissen über sehr spezielle Themengebiete und Vorgänge (https://de.wikipedia.org/wiki/Ontologie_(Informatik))
C40: OPC UA | E40: Standard für den Datenaustausch als plattformunabhängige, service-orientierte Architektur (SOA)[1]. Sie führt die Fähigkeit ein, Maschinendaten (Regelgrößen, Messwerte, Parameter usw.) nicht nur zu transportieren, sondern auch maschinenlesbar semantisch zu beschreiben (https://de.wikipedia.org/wiki/OPC_Unified_Architecture)
C41: P
C42: PDM (Product Data Management) | E42: speichert und verwaltet produktdefinierende, repräsentierende und präsentierende Daten als Ergebnis der Produktentwicklung und stellt sie in nachgelagerten Phasen des Produktlebenszyklus zur Verfügung (https://de.wikipedia.org/wiki/Produktdatenmanagement)
C43: PIM (Product Information Management) | E43: Bereitstellung von Produktinformationen für den Einsatz in verschiedenen Ausgabemedien beziehungsweise Vertriebskanälen sowie für unterschiedliche Standorte (https://de.wikipedia.org/wiki/Produktinformationsmanagement)
C44: PLM (Product Lifecycle Management) | E44: Konzept zur nahtlosen Integration sämtlicher Informationen, die im Verlauf des Lebenszyklus eines Produktes anfallen (https://de.wikipedia.org/wiki/Product-Lifecycle-Management)
C45: T
C46: Team, crossfunktionales | E46: Gruppen von Menschen mit einer Vielzahl von Fähigkeiten und Erfahrungen, die alle auf ein gemeinsames Ziel hinarbeiten. Statt also ein Projekt von Team zu Team bis zum Markteinführungstermin weiterzugeben, kann ein einziges Team jeden Aspekt des Projekts bearbeiten (https://www.dropbox.com/de/resources/cross-functional-teams)
C47: Terminologiemapping | E47: Zuordnung von Begriffen aus unterschiedlichen Terminologien, um deren Bedeutungen abzugleichen oder zu harmonisieren.
C48: Translation Memory | E48: Datenbank mit strukturierten Übersetzungen, die die Hauptkomponente von Anwendungen zur rechnerunterstützten Übersetzung (Computer-aided translation, abgekürzt CAT) darstellt (https://de.wikipedia.org/wiki/%C3%9Cbersetzungsspeicher)
C49: U
C50: URI (Uniform Resource Identifier) | E50: Identifikator bestehend aus einer Zeichenfolge, die zur Identifizierung einer abstrakten oder physischen Ressource dient. URIs werden zur Bezeichnung von Ressourcen (wie Webseiten, sonstigen Dateien, Aufruf von Webservices, aber auch E-Mail-Empfängern) im Internet und dort vor allem im WWW eingesetzt (https://de.wikipedia.org/wiki/Uniform_Resource_Identifier)

Sheet Offene Punkte
B4: {=INDEX(_xlfn._xlws.FILTER('TD1.1'!B16:H32,'TD1.1'!H16:H32<>"Vollständig"),,1)} -> 1 | C4: =IF(B4=0,C3,B4) -> 1 | D4: {=INDEX(_xlfn._xlws.FILTER('TD1.1'!B16:H32,'TD1.1'!H16:H32<>"Vollständig"),,2)} -> Ist sichergestellt, dass die Mitarbeitenden wissen – basierend auf ihrer Erfahrung oder etablierten Kenntnissen –, wann sie im Entwicklungsprozess mit dem Redaktionsprozess beginnen müssen?
B5: 2 | C5: =IF(B5=0,C4,B5) -> 2 | D5: Sind in Entwicklungsprozessen allgemeine erforderliche Ressourcen für den Redaktionsprozess vorab bekannt? Sind ausreichend Ressourcen vorhanden?
B6: 0 | C6: =IF(B6=0,C5,B6) -> 2 | D6: Sind in Entwicklungsprozessen Deadlines für die Fertigstellung der Dokumentation definiert? Lässt sich ein Einstiegspunkt für den redaktionellen Prozess bestimmen?
B7: 0 | C7: =IF(B7=0,C6,B7) -> 2 | D7: Ist die Vorgehensweise zur Etablierung eines auf den Entwicklungsprozess angeglichenen Redaktionsprozess geplant (Beispielsweise in einer Roadmap)?
B8: 0 | C8: =IF(B8=0,C7,B8) -> 2 | D8: Existiert eine Leitlinie für durchzuführende Aufgaben im Redaktionsprozess und wird diese gelegentlich aktualisiert?
B9: 3 | C9: =IF(B9=0,C8,B9) -> 3 | D9: Wurde der Redaktionsprozess in Arbeitspakete zerlegt und sind diese an einzelne Entwicklungsaufgaben gekoppelt?
B10: 0 | C10: =IF(B10=0,C9,B10) -> 3 | D10: Finden regelmäßige Abstimmungen mit allen relevanten Stakeholdern statt?
B11: 0 | C11: =IF(B11=0,C10,B11) -> 3 | D11: Wurde eine Ressourcenplanung für einzelne Aufgaben im Redaktionsprozess durchgeführt?
B12: 0 | C12: =IF(B12=0,C11,B12) -> 3 | D12: Wird der reale Ressourcenbedarf dokumentiert und regelmäßig mit den Planungsdaten verglichen?
B13: 0 | C13: =IF(B13=0,C12,B13) -> 3 | D13: Sind zeitkritische Redaktionsaufgaben bekannt und werden mit entsprechendem Puffer berücksichtigt?
B14: 0 | C14: =IF(B14=0,C13,B14) -> 3 | D14: Werden Verbesserungspotentiale zur Vorgehensweise im Redaktionsprozess identifiziert?
B15: 4 | C15: =IF(B15=0,C14,B15) -> 4 | D15: Ist die Ressourcenplanung systemgestützt an den Entwicklungsprozess gekoppelt?
B16: 0 | C16: =IF(B16=0,C15,B16) -> 4 | D16: Werden die Performance-Daten aus dem Redaktionsprozess weiter verwendet (z.B. zur verbesserten Prognose des Ressourcenbedarfs)?
... B20: 0 | C20: =IF(B20=0,C19,B20) -> 5 | D20: Werden basierend auf aktuellen Entwicklungen Verbesserungspotentiale für den Redaktionsprozess identifiziert, bewertet und umgesetzt?

Sheet TD1.1
B4: Die Reifegrade werden anhand der jeweiligen Antwort ermittelt. Eine Erläuterung des Aufbaus der Reifegrade und der Antwortmöglichkeiten finden Sie in den Ausfüllhinweisen.
B6: TD1.1 | C6: Redaktionsprozess - Prozessinitiierung | K6: Reifegrad: | L6: =ROUNDDOWN(Z16/0.25,0)*0.25 -> 0 | M6: =IF(L6<1,"Unvollständig",IF(L6<2,"Initial",IF(L6<3,"Gemanagt",IF(L6<4,"Definiert",IF(L6<5,"Quantitativ gemanagt",IF(L6<6,"Optimiert","Ausstehend")))))) -> Unvollständig
B7: Zweck | C7: Startpunkt der redaktionellen Tätigkeiten eindeutig definieren, die erforderlichen Aktivitäten anstoßen und die notwendigen Rahmenbedingungen (z. B. Zuständigkeiten, Ressourcen, Zeitplan) festzulegen, um einen reibungslosen Ablauf der Dokumentationserstellung sicherzustellen.
B8: Ergebnisse | C8: • Ressourcenplanung und Prozessinitiierung sind festgelegt • Zeitplan und Meilensteinplan liegen vor • Redaktionsprozess ist an den Entwicklungsprozess gekoppelt
B9: Basispraktiken | C9: • Erkennen und dokumentieren des Auslösers für den Redaktionsprozess • Sicherstellen, dass alle erforderlichen Ressourcen vorliegen • Verknüpfen der Aktivitäten des Redaktionsprozesses mit Aktivitäten des Entwicklungsprozesses
B10: Arbeitsprodukte | C10: • Startdokumentation • Projektzeitplan • Ressourcenplanung
B12: Erhebung der Reifegrade:
B14: Zu Reifegrad | C14: Kontrollfrage | F14: Abnahmekriterien | H14: Umsetzung | J14: Nutzen bei Erreichen der Stufe | N14: Kommentar/Hinweis | T14: Listenindex | Y14: Zw. Ergebnis | Z14: Ergebnis
B16: 1 | C16: Ist sichergestellt, dass die Mitarbeitenden wissen – basierend auf ihrer Erfahrung oder etablierten Kenntnissen –, wann sie im Entwicklungsprozess mit dem Redaktionsprozess beginnen müssen? | F16: • Mitarbeiter besitzen das Erfahrungswissen zur selbstständigen Initiierung des Redaktionsprozesses | H16: Bitte auswählen | J16: / | S16: =IF(H16="Nicht anwendbar","n.a.",0) -> 0 | T16: =IF(H16="Vollständig",1,0) -> 0 | U16: =IF(H16="In den meisten Fällen",0.75,0) -> 0 | V16: =IF(H16="In ein Paar Fällen",0.5,0) -> 0 | W16: =IF(H16="Gar nicht",0,0) -> 0 | X16: =IF(S16>0,"n.a.",SUM(S16:W16)) -> 0 | Y16: =X16 -> 0 | Z16: =IF(Y16<>"n.a.",SUM(Y16,Y17,Y21,Y27,Y30),NA()) -> 0 | AG16: =IF(X16>0.5,"Umgesetzt","Nicht umgesetzt") -> Nicht umgesetzt
B17: 2 | C17: Sind in Entwicklungsprozessen allgemeine erforderliche Ressourcen für den Redaktionsprozess vorab bekannt? Sind ausreichend Ressourcen vorhanden? | F17: • Die erforderlichen Ressourcen für den Redaktionsprozess sind insgesamt grob bekannt (z.B. Anzahl Personenmonate) • Die Mitarbeitenden verfügen über ausreichend Ressourcen zur Durchführung der Redaktionsarbeit • Deadlines für die Fertigstellung der Dokumentation sind festgelegt und werden größtenteils eingehalten • Die Angleichung des Redaktionsprozesses an den Entwicklungsprozess ist geplant • Es existieren Leitlinien für die Aufgaben im Redaktionsprozess | H17: Bitte auswählen | J17: • Frühere Planbarkeit, da erste Kriterien für den Start vorhanden sind • Vermeidung von kritischen Verzögerungen durch die Redaktion in Einzelfällen • gesteigerte Effizienz durch initale Klärung der Zuständigkeiten --> erste Stabilität | S17: =IF(H17="Nicht anwendbar","n.a.",0) -> 0 | T17: =IF(H17="Vollständig",1,0) -> 0 | U17: =IF(H17="In den meisten Fällen",0.75,0) -> 0 | V17: =IF(H17="In ein Paar Fällen",0.5,0) -> 0 | W17: =IF(H17="Gar nicht",0,0) -> 0 | X17: =IFERROR(SUM(T17:W20)/COUNTIF(H17:H20,"<>Nicht anwendbar"),"n.a.") -> 0 | Y17: =IF(X16=1,X17,0) -> 0 | AG17: =IF(X17>0.5,"Umgesetzt","Nicht umgesetzt") -> Nicht umgesetzt
C18: Sind in Entwicklungsprozessen Deadlines für die Fertigstellung der Dokumentation definiert? Lässt sich ein Einstiegspunkt für den redaktionellen Prozess bestimmen? | H18: Bitte auswählen | S18: =IF(H18="Nicht anwendbar","n.a.",0) -> 0 | T18: =IF(H18="Vollständig",1,0) -> 0 | U18: =IF(H18="In den meisten Fällen",0.75,0) -> 0 | V18: =IF(H18="In ein Paar Fällen",0.5,0) -> 0 | W18: =IF(H18="Gar nicht",0,0) -> 0 | AG18: =IF(X18>0.5,"Umgesetzt","Nicht umgesetzt") -> Nicht umgesetzt
C19: Ist die Vorgehensweise zur Etablierung eines auf den Entwicklungsprozess angeglichenen Redaktionsprozess geplant (Beispielsweise in einer Roadmap)? | H19: Bitte auswählen | S19: =IF(H19="Nicht anwendbar","n.a.",0) -> 0 | T19: =IF(H19="Vollständig",1,0) -> 0 | U19: =IF(H19="In den meisten Fällen",0.75,0) -> 0 | V19: =IF(H19="In ein Paar Fällen",0.5,0) -> 0 | W19: =IF(H19="Gar nicht",0,0) -> 0 | AG19: =IF(X19>0.5,"Umgesetzt","Nicht umgesetzt") -> Nicht umgesetzt
C20: Existiert eine Leitlinie für durchzuführende Aufgaben im Redaktionsprozess und wird diese gelegentlich aktualisiert? | H20: Bitte auswählen | S20: =IF(H20="Nicht anwendbar","n.a.",0) -> 0 | T20: =IF(H20="Vollständig",1,0) -> 0 | U20: =IF(H20="In den meisten Fällen",0.75,0) -> 0 | V20: =IF(H20="In ein Paar Fällen",0.5,0) -> 0 | W20: =IF(H20="Gar nicht",0,0) -> 0 | AG20: =IF(X20>0.5,"Umgesetzt","Nicht umgesetzt") -> Nicht umgesetzt
B21: 3 | C21: Wurde der Redaktionsprozess in Arbeitspakete zerlegt und sind diese an einzelne Entwicklungsaufgaben gekoppelt? | F21: • Der Redaktionsprozess wurde in Einzelarbeitspakete zerlegt • Die Arbeitspakete sind mit Arbeitspaketen im Entwicklungsprozess verknüpft • Die Einzelarbeitspakete unterliegen einer konkreten Ressourcenplanung • Der tatsächliche Ressourcenbedarf wird dokumentiert • Ist- und Plan-Ressourcenbedarf werden regelmäßig miteinander verglichen • Zeitkritische Redaktionsaufgaben sind bekannt und dementsprechende Puffer werden berücksichtigt • Verbesserungspotenziale hinsichtlich des Redaktionsprozesses werden identifiziert | H21: Bitte auswählen | J21: • Klare Startpunkte erhöhen die Verlässlichkeit der Prozesse • Bessere Planbarkeit von Ressourcen und Terminen • Das Herunterbrechen in Einzelarbeitspakete erhöht die Transparenz im Redaktionsprozess und erleichtert die Identifikation von Verbesserungspotenzialen --> Verlässlichkeit und Effizienz | S21: =IF(H21="Nicht anwendbar","n.a.",0) -> 0 | T21: =IF(H21="Vollständig",1,0) -> 0 | U21: =IF(H21="In den meisten Fällen",0.75,0) -> 0 | V21: =IF(H21="In ein Paar Fällen",0.5,0) -> 0 | W21: =IF(H21="Gar nicht",0,0) -> 0 | X21: =IFERROR(SUM(T21:W26)/COUNTIF(H21:H26,"<>Nicht anwendbar"),"n.a.") -> 0 | Y21: =IF(Y17=1,X21,0) -> 0
C22: Finden regelmäßige Abstimmungen mit allen relevanten Stakeholdern statt? | H22: Bitte auswählen | S22: =IF(H22="Nicht anwendbar","n.a.",0) -> 0 | T22: =IF(H22="Vollständig",1,0) -> 0 | U22: =IF(H22="In den meisten Fällen",0.75,0) -> 0 | V22: =IF(H22="In ein Paar Fällen",0.5,0) -> 0 | W22: =IF(H22="Gar nicht",0,0) -> 0
C23: Wurde eine Ressourcenplanung für einzelne Aufgaben im Redaktionsprozess durchgeführt? | H23: Bitte auswählen | S23: =IF(H23="Nicht anwendbar","n.a.",0) -> 0 | T23: =IF(H23="Vollständig",1,0) -> 0 | U23: =IF(H23="In den meisten Fällen",0.75,0) -> 0 | V23: =IF(H23="In ein Paar Fällen",0.5,0) -> 0 | W23: =IF(H23="Gar nicht",0,0) -> 0
C24: Wird der reale Ressourcenbedarf dokumentiert und regelmäßig mit den Planungsdaten verglichen? | H24: Bitte auswählen | S24: =IF(H24="Nicht anwendbar","n.a.",0) -> 0 | T24: =IF(H24="Vollständig",1,0) -> 0 | U24: =IF(H24="In den meisten Fällen",0.75,0) -> 0 | V24: =IF(H24="In ein Paar Fällen",0.5,0) -> 0 | W24: =IF(H24="Gar nicht",0,0) -> 0
C25: Sind zeitkritische Redaktionsaufgaben bekannt und werden mit entsprechendem Puffer berücksichtigt? | H25: Bitte auswählen | S25: =IF(H25="Nicht anwendbar","n.a.",0) -> 0 | T25: =IF(H25="Vollständig",1,0) -> 0 | U25: =IF(H25="In den meisten Fällen",0.75,0) -> 0 | V25: =IF(H25="In ein Paar Fällen",0.5,0) -> 0 | W25: =IF(H25="Gar nicht",0,0) -> 0
C26: Werden Verbesserungspotentiale zur Vorgehensweise im Redaktionsprozess identifiziert? | H26: Bitte auswählen | S26: =IF(H26="Nicht anwendbar","n.a.",0) -> 0 | T26: =IF(H26="Vollständig",1,0) -> 0 | U26: =IF(H26="In den meisten Fällen",0.75,0) -> 0 | V26: =IF(H26="In ein Paar Fällen",0.5,0) -> 0 | W26: =IF(H26="Gar nicht",0,0) -> 0
B27: 4 | C27: Ist die Ressourcenplanung systemgestützt an den Entwicklungsprozess gekoppelt? | F27: • Die Ressourcenplanung ist systemgestützt an den Entwicklungsprozess gekoppelt • Die Performance-Daten aus dem Redaktionsprozess werden für Analysen weiter verwendet • Workflows wurden definiert • Aufgaben werden automatisiert mit Deadlines an die Verantwortlichen gesendet | H27: Bitte auswählen | J27: • Keine Verzögerung (durch die Redaktion) der Markteinführung • Verbesserte Zusammenarbeit zwischen Redaktion und Entwicklung • Transparenter Informationsfluss reduziert Medienbrüche und Fehler --> Zeit- und Qualitätsvorteile | S27: =IF(H27="Nicht anwendbar","n.a.",0) -> 0 | T27: =IF(H27="Vollständig",1,0) -> 0 | U27: =IF(H27="In den meisten Fällen",0.75,0) -> 0 | V27: =IF(H27="In ein Paar Fällen",0.5,0) -> 0 | W27: =IF(H27="Gar nicht",0,0) -> 0 | X27: =IFERROR(SUM(T27:W29)/COUNTIF(H27:H29,"<>Nicht anwendbar"),"n.a.") -> 0 | Y27: =IF(Y21=1,X27,0) -> 0
C28: Werden die Performance-Daten aus dem Redaktionsprozess weiter verwendet (z.B. zur verbesserten Prognose des Ressourcenbedarfs)? | H28: Bitte auswählen | S28: =IF(H28="Nicht anwendbar","n.a.",0) -> 0 | T28: =IF(H28="Vollständig",1,0) -> 0 | U28: =IF(H28="In den meisten Fällen",0.75,0) -> 0 | V28: =IF(H28="In ein Paar Fällen",0.5,0) -> 0 | W28: =IF(H28="Gar nicht",0,0) -> 0
C29: Wurden Workflows definiert? Werden die Aufgaben mit Deadlines an die Verantwortlichen gesendet (z.B. Ticketsystem)? | H29: Bitte auswählen | S29: =IF(H29="Nicht anwendbar","n.a.",0) -> 0 | T29: =IF(H29="Vollständig",1,0) -> 0 | U29: =IF(H29="In den meisten Fällen",0.75,0) -> 0 | V29: =IF(H29="In ein Paar Fällen",0.5,0) -> 0 | W29: =IF(H29="Gar nicht",0,0) -> 0
B30: 5 | C30: Wird bei Änderungen im Entwicklungsprozess (z.B. Produktänderungen) der Redaktionsprozess angestoßen? Werden die Ressourcen dynamisch angepasst? | F30: • Bei Änderungen im Entwicklungsprozess werden die tangierten Aufgaben im Redaktionsprozess angestoßen • Bei Änderungen im Entwicklungsprozess werden die Ressourcen dynamisch angepasst • Ressourcen werden automatisiert geplant und priorisiert • Basierend auf den aktuellen Entwicklungen werden Verbesserungspotenziale identifiziert, bewertet und umgesetzt | H30: Bitte auswählen | J30: • Dokumentation wird zu einem strategischen Enabler und unterstützt agile Entwicklungsprozesse und kann frühzeitig Wissen sichern • Automatische Initiierung senkt den manuellen Aufwand • Entlastung der Organisation durch vorausschauende Ressourcenplanung --> strategische Nutzung und Wettbewerbsvorteil | S30: =IF(H30="Nicht anwendbar","n.a.",0) -> 0 | T30: =IF(H30="Vollständig",1,0) -> 0 | U30: =IF(H30="In den meisten Fällen",0.75,0) -> 0 | V30: =IF(H30="In ein Paar Fällen",0.5,0) -> 0 | W30: =IF(H30="Gar nicht",0,0) -> 0 | X30: =IFERROR(SUM(T30:W32)/COUNTIF(H30:H32,"<>Nicht anwendbar"),"n.a.") -> 0 | Y30: =IF(Y27=1,X30,0) -> 0
C31: Werden benötigte Ressourcen für den Redaktionsprozess automatisiert geplant und priorisiert (z.B. auf Grundlage des Projektfortschritts)? | H31: Bitte auswählen | S31: =IF(H31="Nicht anwendbar","n.a.",0) -> 0 | T31: =IF(H31="Vollständig",1,0) -> 0 | U31: =IF(H31="In den meisten Fällen",0.75,0) -> 0 | V31: =IF(H31="In ein Paar Fällen",0.5,0) -> 0 | W31: =IF(H31="Gar nicht",0,0) -> 0
C32: Werden basierend auf aktuellen Entwicklungen Verbesserungspotentiale für den Redaktionsprozess identifiziert, bewertet und umgesetzt? | H32: Bitte auswählen | S32: =IF(H32="Nicht anwendbar","n.a.",0) -> 0 | T32: =IF(H32="Vollständig",1,0) -> 0 | U32: =IF(H32="In den meisten Fällen",0.75,0) -> 0 | V32: =IF(H32="In ein Paar Fällen",0.5,0) -> 0 | W32: =IF(H32="Gar nicht",0,0) -> 0

Sheet TD1.2
B4: Die Reifegrade werden anhand der jeweiligen Antwort ermittelt. Eine Erläuterung des Aufbaus der Reifegrade und der Antwortmöglichkeiten finden Sie in den Ausfüllhinweisen.
B6: TD1.2 | C6: Redaktionsprozess - Informationsbeschaffung | K6: Reifegrad: | L6: =ROUNDDOWN(Z16/0.25,0)*0.25 -> 0 | M6: =IF(L6<1,"Unvollständig",IF(L6<2,"Initial",IF(L6<3,"Gemanagt",IF(L6<4,"Definiert",IF(L6<5,"Quantitativ gemanagt",IF(L6<6,"Optimiert","Ausstehend")))))) -> Unvollständig
B7: Zweck | C7: Prozess zur Beschaffung der Informationen, die für den Redaktionsprozess erforderlich sind
B8: Ergebnisse | C8: • sämtliche Informationsquellen und Ansprechpartner sind bekannt und dokumentiert • Informationen erreichen die Redaktion automatisch im Push-Prinzip • Informationslücken sind erkannt, dokumentiert und mit Maßnahmen zur Schließung versehen
B9: Basispraktiken | C9: • Informationsbedarf definieren und dokumentieren • Geeignete Quellen identifizieren und dokumentieren • Informationsbeschaffung durchführen und dokumentieren
B10: Arbeitsprodukte | C10: • Quellenverzeichnis • Informationsanforderungsliste
B12: Erhebung der Reifegrade
B14: Zu Reifegrad | C14: Kontrollfrage | F14: Abnahmekriterien | H14: Umsetzung | J14: Nutzen bei Erreichen der Stufe | N14: Kommentar/Hinweis | T14: Listenindex | Y14: Zw. Ergebnis | Z14: Ergebnis
B16: 1 | C16: Wissen die Mitarbeiter, die mit der Technischen Dokumentation vertraut sind, aus der Erfahrung ungefähr, woher sie die erforderlichen Informationen bekommen bzw. sind die Informationsquellen zumindest grob definiert? | F16: • Mitarbeiter besitzen das Erfahrungswissen zur selbstständigen Beschaffung von Informationen | H16: Bitte auswählen | J16: / | S16: =IF(H16="Nicht anwendbar","n.a.",0) -> 0 | T16: =IF(H16="Vollständig",1,0) -> 0 | U16: =IF(H16="In den meisten Fällen",0.75,0) -> 0 | V16: =IF(H16="In ein Paar Fällen",0.5,0) -> 0 | W16: =IF(H16="Gar nicht",0,0) -> 0 | X16: =IF(S16>0,"n.a.",SUM(S16:W16)) -> 0 | Y16: =X16 -> 0 | Z16: =IF(Y16<>"n.a.",SUM(Y16,Y17,Y21,Y23,Y26),NA()) -> 0 | AG16: =IF(X16>0.5,"Umgesetzt","Nicht umgesetzt") -> Nicht umgesetzt
B17: 2 | C17: Ist identifiziert worden, welche Informationen im Redaktionsprozess für die technische Dokumentation erforderlich sind? | F17: • Die erforderlichen Informationen sind bekannt • Die Ansprechpartner für die erforderlichen Informationen bzw. die Informationsquellen sind bekannt • Die Ansprechpartner werden frühzeitig eingebunden • Es existiert eine Leitlinie für erforderliche Information und die zugehörigen Informationsquellen • Es sind Ziele und Vorgehensweisen für die Durchführung der Informationsbeschaffung festgelegt und dokumentiert | H17: Bitte auswählen | J17: • Reduzierte Abhängigkeit von Einzelpersonen • geringerer Zeitaufwand für wiederkehrende Informationsrecherchen • Verbesserung der Nachvollziehbarkeit durch vereinzelte Dokumentation von Quellen --> erste Stabilität und Entlastung | S17: =IF(H17="Nicht anwendbar","n.a.",0) -> 0 | T17: =IF(H17="Vollständig",1,0) -> 0 | U17: =IF(H17="In den meisten Fällen",0.75,0) -> 0 | V17: =IF(H17="In ein Paar Fällen",0.5,0) -> 0 | W17: =IF(H17="Gar nicht",0,0) -> 0 | X17: =IFERROR(SUM(T17:W20)/COUNTIF(H17:H20,"<>Nicht anwendbar"),"n.a.") -> 0 | Y17: =IF(X16=1,X17,0) -> 0 | AG17: =IF(X17>0.5,"Umgesetzt","Nicht umgesetzt") -> Nicht umgesetzt
C18: Sind die Ansprechpartner für die erforderlichen Informationen bzw. Informationsquellen bekannt und werden diese frühzeitig eingebunden? | H18: Bitte auswählen | S18: =IF(H18="Nicht anwendbar","n.a.",0) -> 0 | T18: =IF(H18="Vollständig",1,0) -> 0 | U18: =IF(H18="In den meisten Fällen",0.75,0) -> 0 | V18: =IF(H18="In ein Paar Fällen",0.5,0) -> 0 | W18: =IF(H18="Gar nicht",0,0) -> 0 | AG18: =IF(X18>0.5,"Umgesetzt","Nicht umgesetzt") -> Nicht umgesetzt
C19: Existiert eine Leitlinie für erforderliche Information und die zugehörigen Informationsquellen und wird diese gelegentlich aktualisiert? | H19: Bitte auswählen | S19: =IF(H19="Nicht anwendbar","n.a.",0) -> 0 | T19: =IF(H19="Vollständig",1,0) -> 0 | U19: =IF(H19="In den meisten Fällen",0.75,0) -> 0 | V19: =IF(H19="In ein Paar Fällen",0.5,0) -> 0 | W19: =IF(H19="Gar nicht",0,0) -> 0 | AG19: =IF(X19>0.5,"Umgesetzt","Nicht umgesetzt") -> Nicht umgesetzt
C20: Sind Ziele und Vorgehensweisen für die Durchführung der Informationsbeschaffung festgelegt und dokumentiert? | H20: Bitte auswählen | S20: =IF(H20="Nicht anwendbar","n.a.",0) -> 0 | T20: =IF(H20="Vollständig",1,0) -> 0 | U20: =IF(H20="In den meisten Fällen",0.75,0) -> 0 | V20: =IF(H20="In ein Paar Fällen",0.5,0) -> 0 | W20: =IF(H20="Gar nicht",0,0) -> 0 | AG20: =IF(X20>0.5,"Umgesetzt","Nicht umgesetzt") -> Nicht umgesetzt
B21: 3 | C21: Erfolgt die Informationsbeschaffung regelmäßig im Push-Prinzip von den Abteilungen zur Redaktion (z.B. von einzelnen Abteilungen / für einzelne Informationen)? | F21: • Der Informationsfluss erfolgt regelmäßig im Push-Prinzip • Es ist ein systematischer Informationsbeschaffungsprozess mit Rollen und Verantwortlichkeiten definiert | H21: Bitte auswählen | J21: • Die Etablierung des Push-Prinzips sorgt für erhöhte Transaprenz und Nachvollziehbarkeit über Informationsflüsse • verlässliche Infpormationsqualität und -vollständigkeit • effizientere Redaktionsarbeit durch weniger Doppelarbeit und Korrekturschleifen --> verlässliche Prozesse und Qualität | S21: =IF(H21="Nicht anwendbar","n.a.",0) -> 0 | T21: =IF(H21="Vollständig",1,0) -> 0 | U21: =IF(H21="In den meisten Fällen",0.75,0) -> 0 | V21: =IF(H21="In ein Paar Fällen",0.5,0) -> 0 | W21: =IF(H21="Gar nicht",0,0) -> 0 | X21: =IFERROR(SUM(T21:W22)/COUNTIF(H21:H22,"<>Nicht anwendbar"),"n.a.") -> 0 | Y21: =IF(Y17=1,X21,0) -> 0
C22: Ist ein systematischer Informationsbeschaffungsprozess mit Rollen und Verantwortlichkeiten definiert? | H22: Bitte auswählen | S22: =IF(H22="Nicht anwendbar","n.a.",0) -> 0 | T22: =IF(H22="Vollständig",1,0) -> 0 | U22: =IF(H22="In den meisten Fällen",0.75,0) -> 0 | V22: =IF(H22="In ein Paar Fällen",0.5,0) -> 0 | W22: =IF(H22="Gar nicht",0,0) -> 0
B23: 4 | C23: Gelangen alle erforderliche Informationen im Push-Prinzip zur Redaktion? | F23: • Die Informationen erreichen die Redaktion im Push-Prinzip • Redundanzen in den Informationen werden vermieden • Der Informationsfluss ist ganzheitlich modelliert und definiert • Der Informationsfluss wird regelmäßig überprüft • Die Redaktion stützt sich bei der Informationsbeschaffung auf eine Single Source of Truth | H23: Bitte auswählen | J23: • reduzierte Fehleranfälligkeit durch Wegfall von manuellen Übergaben • Bessere Abstimmung mit anderen Abteilungen - redundante Arbeiten werden abteilungsübergreifend reduziert • erhöhte Termintreue, da benötigte Informationen planbar verfügbar sind --> Integration bringt Effizienz und Konsistenz | S23: =IF(H23="Nicht anwendbar","n.a.",0) -> 0 | T23: =IF(H23="Vollständig",1,0) -> 0 | U23: =IF(H23="In den meisten Fällen",0.75,0) -> 0 | V23: =IF(H23="In ein Paar Fällen",0.5,0) -> 0 | W23: =IF(H23="Gar nicht",0,0) -> 0 | X23: =IFERROR(SUM(T23:W25)/COUNTIF(H23:H25,"<>Nicht anwendbar"),"n.a.") -> 0 | Y23: =IF(Y21=1,X23,0) -> 0
C24: Ist ein ganzheitlicher Informationsfluss modelliert und definiert? Wird dieser regelmäßig überprüft? | H24: Bitte auswählen | S24: =IF(H24="Nicht anwendbar","n.a.",0) -> 0 | T24: =IF(H24="Vollständig",1,0) -> 0 | U24: =IF(H24="In den meisten Fällen",0.75,0) -> 0 | V24: =IF(H24="In ein Paar Fällen",0.5,0) -> 0 | W24: =IF(H24="Gar nicht",0,0) -> 0
C25: Werden Redundanzen vermieden und kann sich die Redaktion auf eine Single Source of Truth verlassen? | H25: Bitte auswählen | S25: =IF(H25="Nicht anwendbar","n.a.",0) -> 0 | T25: =IF(H25="Vollständig",1,0) -> 0 | U25: =IF(H25="In den meisten Fällen",0.75,0) -> 0 | V25: =IF(H25="In ein Paar Fällen",0.5,0) -> 0 | W25: =IF(H25="Gar nicht",0,0) -> 0
B26: 5 | C26: Gelangen die Informationen automatisiert und normalisiert zur Redaktion? | F26: • Die Informationen gelangen automatisiert und normalisiert zur Redaktion • Der Informationsbeschaffungsprozess wird kontinuierlich verbessert • Es werden basierend auf den aktuellen Entwicklungen Verbesserungspotenziale für die Informationsbeschaffung identifiziert, bewertet und umgesetzt | H26: Bitte auswählen | J26: • Effizienzgewinne durch Wegfall von Such- und Abstimmungsaufwänden • kontiunierliche Aktualität der Informationen Wettbewerbsvorteil durch höhere Geschwindigkeiten bei Markteinführungen und Änderungsumsetzungen --> Proaktivität und Automatisierung sichern strategische Vorteile | S26: =IF(H26="Nicht anwendbar","n.a.",0) -> 0 | T26: =IF(H26="Vollständig",1,0) -> 0 | U26: =IF(H26="In den meisten Fällen",0.75,0) -> 0 | V26: =IF(H26="In ein Paar Fällen",0.5,0) -> 0 | W26: =IF(H26="Gar nicht",0,0) -> 0 | X26: =IFERROR(SUM(T26:W28)/COUNTIF(H26:H28,"<>Nicht anwendbar"),"n.a.") -> 0 | Y26: =IF(Y23=1,X26,0) -> 0
C27: Wird der Prozess der Informationsbeschaffung kontinuierlich verbessert? | H27: Bitte auswählen | S27: =IF(H27="Nicht anwendbar","n.a.",0) -> 0 | T27: =IF(H27="Vollständig",1,0) -> 0 | U27: =IF(H27="In den meisten Fällen",0.75,0) -> 0 | V27: =IF(H27="In ein Paar Fällen",0.5,0) -> 0 | W27: =IF(H27="Gar nicht",0,0) -> 0
C28: Werden basierend auf aktuellen Entwicklungen Verbesserungspotentiale für die Informationsbeschaffung identifiziert, bewertet und umgesetzt? | H28: Bitte auswählen | S28: =IF(H28="Nicht anwendbar","n.a.",0) -> 0 | T28: =IF(H28="Vollständig",1,0) -> 0 | U28: =IF(H28="In den meisten Fällen",0.75,0) -> 0 | V28: =IF(H28="In ein Paar Fällen",0.5,0) -> 0 | W28: =IF(H28="Gar nicht",0,0) -> 0

Sheet TD1.3
B4: Die Reifegrade werden anhand der jeweiligen Antwort ermittelt. Eine Erläuterung des Aufbaus der Reifegrade und der Antwortmöglichkeiten finden Sie in den Ausfüllhinweisen.
B6: TD1.3 | C6: Redaktionsprozess - Interne Zusammenarbeit | K6: Reifegrad: | L6: =ROUNDDOWN(Z16/0.25,0)*0.25 -> 0 | M6: =IF(L6<1,"Unvollständig",IF(L6<2,"Initial",IF(L6<3,"Gemanagt",IF(L6<4,"Definiert",IF(L6<5,"Quantitativ gemanagt",IF(L6<6,"Optimiert","Ausstehend")))))) -> Unvollständig
B7: Zweck | C7: Zusammenarbeit zwischen den Mitarbeitern, die an der technischen Dokumentation arbeiten bzw. dafür verantwortlich sind untereinander sowie mit anderen, tangierten Abteilungen
B8: Ergebnisse | C8: • Kollaborative Zusammenarbeit abteilungsintern • Kollaborative Zusammenarbeit abteilungsübergreifend • Abteilungsübergreifende Teamkultur • Ganzheitliche Sicht auf Redaktionsprozesse und Entwicklungsprozesse
B9: Basispraktiken | C9: • regelmäßige Abstimmungen innerhalb der Redaktion und abteilungsübergreifend • Förderung einer kollaborativen Unternehmenskultur durch Schulungen oder Guidelines • Nutzung gemeinsamer Tools und Plattformen zur Koordination und Dokumentation
B10: Arbeitsprodukte | C10: • Regeln und Praktiken zur Zusammenarbeit • Rollen- und Verantwortlichkeitsmatrix • gemeinsame Informationsplattformen oder Tools
B12: Erhebung der Reifegrade
B14: Zu Reifegrad | C14: Kontrollfrage | F14: Abnahmekriterien | H14: Umsetzung | J14: Nutzen bei Erreichen der Stufe | N14: Kommentar/Hinweis | T14: Listenindex | Y14: Zw. Ergebnis | Z14: Ergebnis
B16: 1 | C16: Wird bei Bedarf projektbezogenen mit anderen Redakteuren bzw. für die Dokumentation verantwortlichen Personen zusammengearbeitet? | F16: • Bei Bedarf wird projektbezogen mit anderen Redakteuren bzw. für die Dokumentation verantwortlichen Personen zusammengearbeitet | H16: Bitte auswählen | J16: / | S16: =IF(H16="Nicht anwendbar","n.a.",0) -> 0 | T16: =IF(H16="Vollständig",1,0) -> 0 | U16: =IF(H16="In den meisten Fällen",0.75,0) -> 0 | V16: =IF(H16="In ein Paar Fällen",0.5,0) -> 0 | W16: =IF(H16="Gar nicht",0,0) -> 0 | X16: =IF(S16>0,"n.a.",SUM(S16:W16)) -> 0 | Y16: =X16 -> 0 | Z16: =IF(Y16<>"n.a.",SUM(Y16,Y17,Y21,Y25,Y29),NA()) -> 0 | AG16: =IF(X16>0.5,"Umgesetzt","Nicht umgesetzt") -> Nicht umgesetzt
B17: 2 | C17: Wird gelegentlich mit anderen Redakteuren zum Zweck des Informations- und Erfahrungsaustausch zusammengearbeitet? | F17: • Es wird gelegentlich mit anderen Redakteuren zum Zweck des Informations- und Erfahrungsaustausch zusammengearbeitet • Durch eine Zusammenarbeit wird doppelte Arbeit durch mehrere Personen innerhalb der Redaktion vermieden • Verantwortlichkeiten in der Redaktion sind projektbezogen definiert und dokumentiert • Informationen bzw. Inhalte werden gelegentlich mit anderen Mitarbeitern innerhalb der Redaktion geteilt | H17: Bitte auswählen | J17: • Verbesserung der Transparenz durch vereinzelte Kommunikationsroutinen • Reduzierte Abhängigkeit von Einzelpersonen • Erste Entlastung durch definierte Ansprechpersonen oder Absprachen --> erste Transparenz und Entlastung | S17: =IF(H17="Nicht anwendbar","n.a.",0) -> 0 | T17: =IF(H17="Vollständig",1,0) -> 0 | U17: =IF(H17="In den meisten Fällen",0.75,0) -> 0 | V17: =IF(H17="In ein Paar Fällen",0.5,0) -> 0 | W17: =IF(H17="Gar nicht",0,0) -> 0 | X17: =IFERROR(SUM(T17:W20)/COUNTIF(H17:H20,"<>Nicht anwendbar"),"n.a.") -> 0 | Y17: =IF(X16=1,X17,0) -> 0 | AG17: =IF(X17>0.5,"Umgesetzt","Nicht umgesetzt") -> Nicht umgesetzt
C18: Wird durch eine Zusammenarbeit doppelte Arbeit durch mehrere Personen innerhalb der Redaktion gelegentlich vermieden? | H18: Bitte auswählen | S18: =IF(H18="Nicht anwendbar","n.a.",0) -> 0 | T18: =IF(H18="Vollständig",1,0) -> 0 | U18: =IF(H18="In den meisten Fällen",0.75,0) -> 0 | V18: =IF(H18="In ein Paar Fällen",0.5,0) -> 0 | W18: =IF(H18="Gar nicht",0,0) -> 0 | AG18: =IF(X18>0.5,"Umgesetzt","Nicht umgesetzt") -> Nicht umgesetzt
C19: Sind Verantwortlichkeiten in der Redaktion projektbezogen definiert und dokumentiert? | H19: Bitte auswählen | S19: =IF(H19="Nicht anwendbar","n.a.",0) -> 0 | T19: =IF(H19="Vollständig",1,0) -> 0 | U19: =IF(H19="In den meisten Fällen",0.75,0) -> 0 | V19: =IF(H19="In ein Paar Fällen",0.5,0) -> 0 | W19: =IF(H19="Gar nicht",0,0) -> 0 | AG19: =IF(X19>0.5,"Umgesetzt","Nicht umgesetzt") -> Nicht umgesetzt
C20: Werden Informationen bzw. Inhalte gelegentlich mit anderen Mitarbeitern innerhalb der Redaktion geteilt? | H20: Bitte auswählen | S20: =IF(H20="Nicht anwendbar","n.a.",0) -> 0 | T20: =IF(H20="Vollständig",1,0) -> 0 | U20: =IF(H20="In den meisten Fällen",0.75,0) -> 0 | V20: =IF(H20="In ein Paar Fällen",0.5,0) -> 0 | W20: =IF(H20="Gar nicht",0,0) -> 0 | AG20: =IF(X20>0.5,"Umgesetzt","Nicht umgesetzt") -> Nicht umgesetzt
B21: 3 | C21: Existiert ein definierter Prozess zur projektbegleitenden, abteilungsübergreifenden Zusammenarbeit? | F21: • Es existiert ein definierter Prozess zur projektbegleitenden, abteilungsübergreifenden Zusammenarbeit • Es werden regelmäßig abteilungsübergreifend Teams zur Zusammenarbeit gebildet • Die Mitarbeiter sind sensibilisiert für die Informationsergebnisse anderer Abteilungen, wodurch doppelte Arbeit abteilungsübergreifend vermieden werden kann • Innerhalb der Teams werden Entscheidungen für den Entwicklungs- und den Redaktionsprozess getroffen | H21: Bitte auswählen | J21: • verbesserte Planbarkeit von Arbeitsaufwänden über Abteilungsgrenzen hinweg • Fehlerreduktion durch nachvollziehbare Zuständigkeiten • Redundanzreduktion durch abteilungsübergreifenden Austausch --> Effizienz und Verlässlichkeit | S21: =IF(H21="Nicht anwendbar","n.a.",0) -> 0 | T21: =IF(H21="Vollständig",1,0) -> 0 | U21: =IF(H21="In den meisten Fällen",0.75,0) -> 0 | V21: =IF(H21="In ein Paar Fällen",0.5,0) -> 0 | W21: =IF(H21="Gar nicht",0,0) -> 0 | X21: =IFERROR(SUM(T21:W24)/COUNTIF(H21:H24,"<>Nicht anwendbar"),"n.a.") -> 0 | Y21: =IF(Y17=1,X21,0) -> 0
C22: Werden regelmäßig abteilungsübergreifend Teams zur Zusammenarbeit gebildet? | H22: Bitte auswählen | S22: =IF(H22="Nicht anwendbar","n.a.",0) -> 0 | T22: =IF(H22="Vollständig",1,0) -> 0 | U22: =IF(H22="In den meisten Fällen",0.75,0) -> 0 | V22: =IF(H22="In ein Paar Fällen",0.5,0) -> 0 | W22: =IF(H22="Gar nicht",0,0) -> 0
C23: Sind die Mitarbeiter sensibilisiert für die Informationsergebnisse anderer Abteilungen, wodurch doppelte Arbeit abteilungsübergreifend vermieden werden kann? | H23: Bitte auswählen | S23: =IF(H23="Nicht anwendbar","n.a.",0) -> 0 | T23: =IF(H23="Vollständig",1,0) -> 0 | U23: =IF(H23="In den meisten Fällen",0.75,0) -> 0 | V23: =IF(H23="In ein Paar Fällen",0.5,0) -> 0 | W23: =IF(H23="Gar nicht",0,0) -> 0
C24: Werden innerhalb der Teams Entscheidungen für den Entwicklungs- und den Redaktionsprozess getroffen? | H24: Bitte auswählen | S24: =IF(H24="Nicht anwendbar","n.a.",0) -> 0 | T24: =IF(H24="Vollständig",1,0) -> 0 | U24: =IF(H24="In den meisten Fällen",0.75,0) -> 0 | V24: =IF(H24="In ein Paar Fällen",0.5,0) -> 0 | W24: =IF(H24="Gar nicht",0,0) -> 0
B25: 4 | C25: Sind innerhalb der Teams Rollen definiert und werden diese regelmäßig überprüft? | F25: • Innerhalb der Teams sind Rollen definiert und werden diese regelmäßig überprüft • Die crossfunktionale Teamarbeit wird mit Hilfe von Kennzahlen gesteuert • Innerhalb der Teams herrscht die Überzeugung, dass gemeinsam bessere Ergebnisse erreicht werden als allein • Die Teamarbeit wird mithilfe von Tools unterstützt | H25: Bitte auswählen | J25: • deutllich verbesserter Wissensaustausch • stärkere Einbindung verschiedener Abteilungen führt zu weniger Medienbrüchen • gesteigerte Mitarbeiterzufriedenheit durch klare Kommunikationswege --> Integration bringt Geschwindigkeit, bessere Qualität und höherre Zufriedenheit | S25: =IF(H25="Nicht anwendbar","n.a.",0) -> 0 | T25: =IF(H25="Vollständig",1,0) -> 0 | U25: =IF(H25="In den meisten Fällen",0.75,0) -> 0 | V25: =IF(H25="In ein Paar Fällen",0.5,0) -> 0 | W25: =IF(H25="Gar nicht",0,0) -> 0 | X25: =IFERROR(SUM(T25:W28)/COUNTIF(H25:H28,"<>Nicht anwendbar"),"n.a.") -> 0 | Y25: =IF(Y21=1,X25,0) -> 0
C26: Wird die crossfunktionale Teamarbeit mit Hilfe von Kennzahlen gesteuert? | H26: Bitte auswählen | S26: =IF(H26="Nicht anwendbar","n.a.",0) -> 0 | T26: =IF(H26="Vollständig",1,0) -> 0 | U26: =IF(H26="In den meisten Fällen",0.75,0) -> 0 | V26: =IF(H26="In ein Paar Fällen",0.5,0) -> 0 | W26: =IF(H26="Gar nicht",0,0) -> 0
C27: Herrscht innerhalb der Teams die Überzeugung, dass gemeinsam bessere Ergebnisse erreicht werden als allein? | H27: Bitte auswählen | S27: =IF(H27="Nicht anwendbar","n.a.",0) -> 0 | T27: =IF(H27="Vollständig",1,0) -> 0 | U27: =IF(H27="In den meisten Fällen",0.75,0) -> 0 | V27: =IF(H27="In ein Paar Fällen",0.5,0) -> 0 | W27: =IF(H27="Gar nicht",0,0) -> 0
C28: Wird die Teamarbeit mithilfe von Tools unterstützt? | H28: Bitte auswählen | S28: =IF(H28="Nicht anwendbar","n.a.",0) -> 0 | T28: =IF(H28="Vollständig",1,0) -> 0 | U28: =IF(H28="In den meisten Fällen",0.75,0) -> 0 | V28: =IF(H28="In ein Paar Fällen",0.5,0) -> 0 | W28: =IF(H28="Gar nicht",0,0) -> 0
B29: 5 | C29: Wird die Zusammenarbeit und Kommunikation im Team kontinuierlich verbessert? | F29: • Die Zusammenarbeit und Kommunikation im Team wird kontinuierlich verbessert • Es werden kontinuierlich neue Möglichkeiten der Zusammenarbeit identifiziert, bewertet und umgesetzt | H29: Bitte auswählen | J29: • nachhaltige Effizienzsteigerung durch kontinuierliche Verbesserung • Organisation entwickelt eine Kultur des Wissensaustauschs und der Transparenz • hohe Innovationsfähigkeit durch crossfunktionale, nahtlose Zusammenarbeit --> Optimierung sichert Innovationskraft und eine kollaborative Unternehmenskultur | S29: =IF(H29="Nicht anwendbar","n.a.",0) -> 0 | T29: =IF(H29="Vollständig",1,0) -> 0 | U29: =IF(H29="In den meisten Fällen",0.75,0) -> 0 | V29: =IF(H29="In ein Paar Fällen",0.5,0) -> 0 | W29: =IF(H29="Gar nicht",0,0) -> 0 | X29: =IFERROR(SUM(T3:W29)/COUNTIF(H29:H30,"<>Nicht anwendbar"),"n.a.") -> 0 | Y29: =IF(Y25=1,X29,0) -> 0
C30: Werden kontinuierlich neue Möglichkeiten der Zusammenarbeit identifiziert, bewertet und umgesetzt? | H30: Bitte auswählen | S30: =IF(H30="Nicht anwendbar","n.a.",0) -> 0 | T30: =IF(H30="Vollständig",1,0) -> 0 | U30: =IF(H30="In den meisten Fällen",0.75,0) -> 0 | V30: =IF(H30="In ein Paar Fällen",0.5,0) -> 0 | W30: =IF(H30="Gar nicht",0,0) -> 0

Sheet TD1.4
B4: Die Reifegrade werden anhand der jeweiligen Antwort ermittelt. Eine Erläuterung des Aufbaus der Reifegrade und der Antwortmöglichkeiten finden Sie in den Ausfüllhinweisen.
B6: TD1.4 | C6: Redaktionsprozess - Externe Zusammenarbeit | K6: Reifegrad: | L6: =ROUNDDOWN(Z16/0.25,0)*0.25 -> 0 | M6: =IF(L6<1,"Unvollständig",IF(L6<2,"Initial",IF(L6<3,"Gemanagt",IF(L6<4,"Definiert",IF(L6<5,"Quantitativ gemanagt",IF(L6<6,"Optimiert","Ausstehend")))))) -> Unvollständig
B7: Zweck | C7: Die Zusammenarbeit der Redaktion mit externen Partnern außerhalb der Organisation. Dies können etwa Dienstleister für die technische Dokumentation sein (z.B. Übersetzungsdienstleister) oder Partner innerhalb des Entwicklungsprozesses (z.B. Lieferanten)
B8: Ergebnisse | C8: • Relevante externe Partner sind identifiziert, eingebunden und ihre Rollen definiert • Kommunikations- und Abstimmungswege mit externen Akteuren sind definiert • Vereinbarungen sind dokumentiert • Externe Beiträge sind integriert und konsistent mit der Gesamtdokumentation
B9: Basispraktiken | C9: • Klare Definition von Schnittstellen, Verantwortlichkeiten und Qualitätskriterien • Regelmäßige Abstimmungsrunden oder Statusmeetings mit externen Partnern • Nutzung von Tools und Plattformen
B10: Arbeitsprodukte | C10: • Verträge, Vereinbarungen oder Service Level Agreements (SLA) mit externen Partnern • Dokumentierte Kommunikations- und Schnittstellenregeln für externe Zusammenarbeit • Gemeinsame Arbeitsplattformen oder Austauschformate
B12: Erhebung der Reifegrade
B14: Zu Reifegrad | C14: Kontrollfrage | F14: Abnahmekriterien | H14: Umsetzung | J14: Nutzen bei Erreichen der Stufe | N14: Kommentar/Hinweis | T14: Listenindex | Y14: Zw. Ergebnis | Z14: Ergebnis
B16: 1 | C16: Kann die externe Kommunikation situativ über Dritte (z. B. Projektleitung) erfolgen, wenn dies erforderlich ist? | F16: • Die Kommunikation erfolgt über Dritte (z.B. Projektleiter) | H16: Bitte auswählen | J16: / | S16: =IF(H16="Nicht anwendbar","n.a.",0) -> 0 | T16: =IF(H16="Vollständig",1,0) -> 0 | U16: =IF(H16="In den meisten Fällen",0.75,0) -> 0 | V16: =IF(H16="In ein Paar Fällen",0.5,0) -> 0 | W16: =IF(H16="Gar nicht",0,0) -> 0 | X16: =IF(S16>0,"n.a.",SUM(S16:W16)) -> 0 | Y16: =X16 -> 0 | Z16: =IF(Y16<>"n.a.",SUM(Y16,Y17,Y20,Y23,Y27),NA()) -> 0
B17: 2 | C17: Gibt es definierte Ansprechpartner bei externen Partnern für die Redaktion und sind diese dokumentiert? | F17: • Es gibt definierte Ansprechpartner bei externen Partnern für die Redaktion • Die externe Zusammenarbeit erfolgt gelegentlich projektbezogen • Absprachen mit externen Partnern werden gelegentlich dokumentiert | H17: Bitte auswählen | J17: • Aufbau von Verlässlichkeit in bestimmten Kooperationen • Verringerte Such- und Abstimmungsaufwände durch bekannte Ansprechpartner --> erste Stabilität durch feste Partner | S17: =IF(H17="Nicht anwendbar","n.a.",0) -> 0 | T17: =IF(H17="Vollständig",1,0) -> 0 | U17: =IF(H17="In den meisten Fällen",0.75,0) -> 0 | V17: =IF(H17="In ein Paar Fällen",0.5,0) -> 0 | W17: =IF(H17="Gar nicht",0,0) -> 0 | X17: =IFERROR(SUM(T17:W19)/COUNTIF(H17:H19,"<>Nicht anwendbar"),"n.a.") -> 0 | Y17: =IF(X16=1,X17,0) -> 0 | AG17: =IF(X18>0.5,"Umgesetzt","Nicht umgesetzt") -> Nicht umgesetzt
C18: Erfolgt die externe Zusammenarbeit projektbezogen gelegentlich zwischen externen Partnern und der Redaktion? | H18: Bitte auswählen | S18: =IF(H18="Nicht anwendbar","n.a.",0) -> 0 | T18: =IF(H18="Vollständig",1,0) -> 0 | U18: =IF(H18="In den meisten Fällen",0.75,0) -> 0 | V18: =IF(H18="In ein Paar Fällen",0.5,0) -> 0 | W18: =IF(H18="Gar nicht",0,0) -> 0 | AG18: =IF(X19>0.5,"Umgesetzt","Nicht umgesetzt") -> Nicht umgesetzt
C19: Werden Absprachen mit externen Partnern gelegentlich dokumentiert? | H19: Bitte auswählen | S19: =IF(H19="Nicht anwendbar","n.a.",0) -> 0 | T19: =IF(H19="Vollständig",1,0) -> 0 | U19: =IF(H19="In den meisten Fällen",0.75,0) -> 0 | V19: =IF(H19="In ein Paar Fällen",0.5,0) -> 0 | W19: =IF(H19="Gar nicht",0,0) -> 0 | AG19: =IF(#REF!>0.5,"Umgesetzt","Nicht umgesetzt") -> #REF!
B20: 3 | C20: Ist die Zusammenarbeit der Redaktion mit externen Partnern vertraglich geregelt? | F20: • Die Zusammenarbeit mit externen Partnern ist vertraglich geregelt • Es gibt standardisierte Schnittstellen und Übergabeformate zu den Partnern für den Informationsaustausch und für die Integration externer Inhalte in die technische Dokumentation • Rollen, Verantwortlichkeiten und Kommunikationswege mit externen Partnern sind klar festgelegt und dokumentiert | H20: Bitte auswählen | J20: • höhere Qualität und Konsistenz externer Leistungen • geringeres Risiko durch klar geregelte Abläufe und Verträge • verbesserte Nachvollziehbarkeit und Dokumentation der Zusammenarbeit --> Qualität und Planbarkeit steigen | S20: =IF(H20="Nicht anwendbar","n.a.",0) -> 0 | T20: =IF(H20="Vollständig",1,0) -> 0 | U20: =IF(H20="In den meisten Fällen",0.75,0) -> 0 | V20: =IF(H20="In ein Paar Fällen",0.5,0) -> 0 | W20: =IF(H20="Gar nicht",0,0) -> 0 | X20: =IFERROR(SUM(T20:W22)/COUNTIF(H20:H22,"<>Nicht anwendbar"),"n.a.") -> 0 | Y20: =IF(Y17=1,X20,0) -> 0
C21: Gibt es standardisierte Schnittstellen und Übergabeformate zu den Partnern für den Informationsaustausch und für die Integration externer Inhalte in die technische Dokumentation? | H21: Bitte auswählen | S21: =IF(H21="Nicht anwendbar","n.a.",0) -> 0 | T21: =IF(H21="Vollständig",1,0) -> 0 | U21: =IF(H21="In den meisten Fällen",0.75,0) -> 0 | V21: =IF(H21="In ein Paar Fällen",0.5,0) -> 0 | W21: =IF(H21="Gar nicht",0,0) -> 0
C22: Sind Rollen, Verantwortlichkeiten und Kommunikationswege mit externen Partnern definiert und dokumentiert? | H22: Bitte auswählen | S22: =IF(H22="Nicht anwendbar","n.a.",0) -> 0 | T22: =IF(H22="Vollständig",1,0) -> 0 | U22: =IF(H22="In den meisten Fällen",0.75,0) -> 0 | V22: =IF(H22="In ein Paar Fällen",0.5,0) -> 0 | W22: =IF(H22="Gar nicht",0,0) -> 0
B23: 4 | C23: Werden in der externen Zusammenarbeit der Redaktion gemeinsame Tools verwendet? | F23: • In der externen Zusammenarbeit werden gemeinsame Tools verwendet • In der externen Zusammenarbeit werden gemeinsame (Qualitäts-) Ziele verfolgt • Die Leistungen werden anhand gemeinsam definierter KPIs regelmäßig überprüft und gesteuert • Die externe Zusammenarbeit wird auf der Grundlage gemeinsamer Workflows durchgeführt | H23: Bitte auswählen | J23: • beschleunigte Prozesse durch digitale Integration externer Partner • weniger Medienbrüche • nahtlose Abstimmung und Qualitätskontrolle engere Bindung und langfristige Partnerschaften mit externen Akteuren --> Integration bringt Effizienz und Geschwindigkeit | S23: =IF(H23="Nicht anwendbar","n.a.",0) -> 0 | T23: =IF(H23="Vollständig",1,0) -> 0 | U23: =IF(H23="In den meisten Fällen",0.75,0) -> 0 | V23: =IF(H23="In ein Paar Fällen",0.5,0) -> 0 | W23: =IF(H23="Gar nicht",0,0) -> 0 | X23: =IFERROR(SUM(T23:W26)/COUNTIF(H23:H26,"<>Nicht anwendbar"),"n.a.") -> 0 | Y23: =IF(Y20=1,X23,0) -> 0
C24: Werden in der externen Zusammenarbeit gemeinsame (Qualitäts-) Ziele verfolgt? | H24: Bitte auswählen | S24: =IF(H24="Nicht anwendbar","n.a.",0) -> 0 | T24: =IF(H24="Vollständig",1,0) -> 0 | U24: =IF(H24="In den meisten Fällen",0.75,0) -> 0 | V24: =IF(H24="In ein Paar Fällen",0.5,0) -> 0 | W24: =IF(H24="Gar nicht",0,0) -> 0
C25: Werden die Leistungen anhand gemeinsam definierter KPIs regelmäßig überprüft und gesteuert? | H25: Bitte auswählen | S25: =IF(H25="Nicht anwendbar","n.a.",0) -> 0 | T25: =IF(H25="Vollständig",1,0) -> 0 | U25: =IF(H25="In den meisten Fällen",0.75,0) -> 0 | V25: =IF(H25="In ein Paar Fällen",0.5,0) -> 0 | W25: =IF(H25="Gar nicht",0,0) -> 0
C26: Wird die externe Zusammenarbeit auf der Grundlage gemeinsamer Workflows durchgeführt? | H26: Bitte auswählen | S26: =IF(H26="Nicht anwendbar","n.a.",0) -> 0 | T26: =IF(H26="Vollständig",1,0) -> 0 | U26: =IF(H26="In den meisten Fällen",0.75,0) -> 0 | V26: =IF(H26="In ein Paar Fällen",0.5,0) -> 0 | W26: =IF(H26="Gar nicht",0,0) -> 0
B27: 5 | C27: Wird die externe Zusammenarbeit gemeinsam mit den Partnern kontinuierlich verbessert? Werden neue Möglichkeiten zur Zusammenarbeit identifiziert, bewertet und umgesetzt? | F27: • Die externe Zusammenarbeit wird gemeinsam mit den Partnern kontinuierlich verbessert • Neue Möglichkeiten zur Zusammenarbeit werden identifiziert, bewertet und umgesetzt • Es wird gemeinsam an der kontinuierlichen Verbesserung der Dokumentation gearbeitet (z.B. in Form von Innovationspartnerschaften) | H27: Bitte auswählen | J27: • Wettbewerbsvorteil durch stabile, leistungsstarke Partnernetzwerke • hohe Innovationsfähigkeit durch gemeinsame Entwicklung und Wissenstransfer • geteiltes Risiko und gemeinsame Verantwortung zwischen Organsiationen und Partnern --> Strategische Partnerschaften sichern Innovationskraft und Wettbewerbsvorteile | S27: =IF(H27="Nicht anwendbar","n.a.",0) -> 0 | T27: =IF(H27="Vollständig",1,0) -> 0 | U27: =IF(H27="In den meisten Fällen",0.75,0) -> 0 | V27: =IF(H27="In ein Paar Fällen",0.5,0) -> 0 | W27: =IF(H27="Gar nicht",0,0) -> 0 | X27: =IFERROR(SUM(T27:W28)/COUNTIF(H27:H28,"<>Nicht anwendbar"),"n.a.") -> 0 | Y27: =IF(Y23=1,X27,0) -> 0
C28: Wird gemeinsam an der kontinuierlichen Verbesserung der Dokumentation gearbeitet (z.B. in Form von Innovationspartnerschaften)? | H28: Bitte auswählen | S28: =IF(H28="Nicht anwendbar","n.a.",0) -> 0 | T28: =IF(H28="Vollständig",1,0) -> 0 | U28: =IF(H28="In den meisten Fällen",0.75,0) -> 0 | V28: =IF(H28="In ein Paar Fällen",0.5,0) -> 0 | W28: =IF(H28="Gar nicht",0,0) -> 0

Sheet TD1.5
B4: Die Reifegrade werden anhand der jeweiligen Antwort ermittelt. Eine Erläuterung des Aufbaus der Reifegrade und der Antwortmöglichkeiten finden Sie in den Ausfüllhinweisen.
B6: TD1.5 | C6: Redaktionsprozess - Rechtskonformität | K6: Reifegrad: | L6: =ROUNDDOWN(Z17/0.25,0)*0.25 -> 0 | M6: =IF(L6<1,"Unvollständig",IF(L6<2,"Initial",IF(L6<3,"Gemanagt",IF(L6<4,"Definiert",IF(L6<5,"Quantitativ gemanagt",IF(L6<6,"Optimiert","Ausstehend")))))) -> Unvollständig
B7: Zweck | C7: Sicherstellung, dass die technische Dokumentation alle relevanten gesetzlichen, normativen und regulatorischen Anforderungen erfüllt. Ziel ist es, rechtliche Risiken zu vermeiden, Produkthaftung zu reduzieren und die Markt- und Zulassungsfähigkeit von Produkten sicherzustellen.
B8: Ergebnisse | C8: • Anwendbare Gesetze, Normen und Richtlinien für die technische Dokumentation sind identifiziert und bekannt • Die Dokumentation erfüllt die relevanten rechtlichen und normativen Anforderungen • Nachweise über die Einhaltung der Rechtskonformität liegen vor • Änderungen in regulatorischen Rahmenbedingungen werden zeitnah in den Redaktionsprozess integriert
B9: Basispraktiken | C9: • Systematische Recherche relevanter Normen, Gesetze und Richtlinien für die Dokumentation. • Übersetzung rechtlicher Anforderungen in konkrete Redaktionsleitlinien und -prozesse. • Regelmäßige Aktualisierung der Rechts- und Normenlage im Redaktionsprozess. • Durchführung von Konformitätsprüfungen während und nach der Dokumentationserstellung
B10: Arbeitsprodukte | C10: • Dokumentierte Rechts- und Normenrecherchen (z. B. Anforderungslisten, Normenregister). • Checklisten oder Prüfdokumente zur Sicherstellung der Konformität. • Nachweise der Rechtskonformität (z. B. Prüfberichte, Freigabeprotokolle, Zertifikate). • Versionierte Dokumentationsstände, die den Zeitpunkt der Rechtsprüfung nachvollziehbar machen
B12: Erhebung der Reifegrade
B14: Zu Reifegrad | C14: Kontrollfrage | F14: Abnahmekriterien | H14: Umsetzung | J14: Nutzen bei Erreichen der Stufe | N14: Kommentar/Hinweis | T14: Listenindex | Y14: Zw. Ergebnis | Z14: Ergebnis
B16: 1 | C16: Kann die Recherche zu den rechtlichen Anforderungen projekt- bzw. anlassbezogen erfolgen, wenn dies erforderlich ist? | F16: • Die Recherche zu den rechtlichen Anforderungen ist projektbezogen • Die Mitarbeitenden besitzen individuell Kenntnisse über die relevanten Normen • Die Mitarbeitenden besitzen individuelle Normenbibliotheken | H16: Bitte auswählen | J16: / | S16: =IF(H16="Nicht anwendbar","n.a.",0) -> 0 | T16: =IF(H16="Vollständig",1,0) -> 0 | U16: =IF(H16="In den meisten Fällen",0.75,0) -> 0 | V16: =IF(H16="In ein Paar Fällen",0.5,0) -> 0 | W16: =IF(H16="Gar nicht",0,0) -> 0
C17: Besitzen die Mitarbeitenden individuell Kenntnisse über die relevanten Normen? Besitzen sie individuelle Normenbibliotheken? | H17: Bitte auswählen | S17: =IF(H17="Nicht anwendbar","n.a.",0) -> 0 | T17: =IF(H17="Vollständig",1,0) -> 0 | U17: =IF(H17="In den meisten Fällen",0.75,0) -> 0 | V17: =IF(H17="In ein Paar Fällen",0.5,0) -> 0 | W17: =IF(H17="Gar nicht",0,0) -> 0 | X17: =IFERROR(SUM(T16:W17)/COUNTIF(H16:H17,"<>Nicht anwendbar"),"n.a.") -> 0 | Y17: =X17 -> 0 | Z17: =IF(Y17<>"n.a.",SUM(Y17,Y18,Y22,Y25,Y28),NA()) -> 0 | AG17: =IF(X17>0.5,"Umgesetzt","Nicht umgesetzt") -> Nicht umgesetzt
B18: 2 | C18: Werden den Mitarbeitenden relevante Richtlinien und Normen allgemein zugänglich gemacht? | F18: • Den Mitarbeitenden relevante Richtlinien und Normen allgemein zugänglich gemacht • Die Recherche nach einem definierten Prozess durchgeführt • Die Durchführung der Recherche wird dokumentiert • Gelegentlich wird die Aktualität der Richtlinien und Normen überprüft | H18: Bitte auswählen | J18: • erhöhte Rechtssicherheit durch erste Vorgaben --> erste Sicherheit durch vereinzelte Anwendung | S18: =IF(H18="Nicht anwendbar","n.a.",0) -> 0 | T18: =IF(H18="Vollständig",1,0) -> 0 | U18: =IF(H18="In den meisten Fällen",0.75,0) -> 0 | V18: =IF(H18="In ein Paar Fällen",0.5,0) -> 0 | W18: =IF(H18="Gar nicht",0,0) -> 0 | X18: =IFERROR(SUM(T18:W21)/COUNTIF(H18:H21,"<>Nicht anwendbar"),"n.a.") -> 0 | Y18: =IF(X17=1,X18,0) -> 0 | AG18: =IF(X18>0.5,"Umgesetzt","Nicht umgesetzt") -> Nicht umgesetzt
C19: Wird die Recherche nach einem definierten Prozess durchgeführt? | H19: Bitte auswählen | S19: =IF(H19="Nicht anwendbar","n.a.",0) -> 0 | T19: =IF(H19="Vollständig",1,0) -> 0 | U19: =IF(H19="In den meisten Fällen",0.75,0) -> 0 | V19: =IF(H19="In ein Paar Fällen",0.5,0) -> 0 | W19: =IF(H19="Gar nicht",0,0) -> 0 | AG19: =IF(X19>0.5,"Umgesetzt","Nicht umgesetzt") -> Nicht umgesetzt
C20: Wird die Durchführung der Recherche dokumentiert? | H20: Bitte auswählen | S20: =IF(H20="Nicht anwendbar","n.a.",0) -> 0 | T20: =IF(H20="Vollständig",1,0) -> 0 | U20: =IF(H20="In den meisten Fällen",0.75,0) -> 0 | V20: =IF(H20="In ein Paar Fällen",0.5,0) -> 0 | W20: =IF(H20="Gar nicht",0,0) -> 0 | AG20: =IF(X20>0.5,"Umgesetzt","Nicht umgesetzt") -> Nicht umgesetzt
C21: Wird gelegentlich die Aktualität der Richtlinien und Normen überprüft? | H21: Bitte auswählen | S21: =IF(H21="Nicht anwendbar","n.a.",0) -> 0 | T21: =IF(H21="Vollständig",1,0) -> 0 | U21: =IF(H21="In den meisten Fällen",0.75,0) -> 0 | V21: =IF(H21="In ein Paar Fällen",0.5,0) -> 0 | W21: =IF(H21="Gar nicht",0,0) -> 0 | AG21: =IF(X21>0.5,"Umgesetzt","Nicht umgesetzt") -> Nicht umgesetzt
B22: 3 | C22: Liegen dokumentierte Prozesse oder Leitlinien zur Sicherstellung der Rechtskonformität in der Dokumentation vor? Sind die Prozesse fester Bestandteil des Redaktionsprozesses? | F22: • dokumentierte Prozesse oder Leitlinien zur Sicherstellung der Rechtskonformität in der Dokumentation liegen vor • Die Prozesse sind fester Bestandteil des Redaktionsprozesses • Verantwortlichkeiten für die Identifikation und Umsetzung rechtlicher Anforderungen sind zugewiesen • Es existieren systematische Prüfverfahren zur Einhaltung der Rechtsvorgaben | H22: Bitte auswählen | J22: • deutlich geringeres Haftungsrisiko durch systematische Absicherung • Verlässlichkeit und Konsistenz bei der Umsetzung von Vorgaben • verbesserte Nachvollziehbarkeit im Audit- oder Prüfungsfall --> verlässliche und effiziente Standardisierung | S22: =IF(H22="Nicht anwendbar","n.a.",0) -> 0 | T22: =IF(H22="Vollständig",1,0) -> 0 | U22: =IF(H22="In den meisten Fällen",0.75,0) -> 0 | V22: =IF(H22="In ein Paar Fällen",0.5,0) -> 0 | W22: =IF(H22="Gar nicht",0,0) -> 0 | X22: =IFERROR(SUM(T22:W25)/COUNTIF(H22:H25,"<>Nicht anwendbar"),"n.a.") -> 0 | Y22: =IF(Y18=1,X22,0) -> 0
C23: Werden Verantwortlichkeiten für die Identifikation und Umsetzung rechtlicher Anforderungen zugewiesen? | H23: Bitte auswählen | S23: =IF(H23="Nicht anwendbar","n.a.",0) -> 0 | T23: =IF(H23="Vollständig",1,0) -> 0 | U23: =IF(H23="In den meisten Fällen",0.75,0) -> 0 | V23: =IF(H23="In ein Paar Fällen",0.5,0) -> 0 | W23: =IF(H23="Gar nicht",0,0) -> 0
C24: Existieren systematische Prüfverfahren zur Einhaltung der Rechtsvorgaben? | H24: Bitte auswählen | S24: =IF(H24="Nicht anwendbar","n.a.",0) -> 0 | T24: =IF(H24="Vollständig",1,0) -> 0 | U24: =IF(H24="In den meisten Fällen",0.75,0) -> 0 | V24: =IF(H24="In ein Paar Fällen",0.5,0) -> 0 | W24: =IF(H24="Gar nicht",0,0) -> 0
B25: 4 | C25: Werden rechtliche Anforderungen regelmäßig überprüft und deren Einhaltung aktiv überwacht? | F25: • rechtliche Anforderungen werden regelmäßig überprüft und deren Einhaltung aktiv überwacht • Aussagekräftige Kennzahlen für die Steuerung von Prozessen im Kontext der Rechtskonformität sind definiert worden und werden regelmäßig kontrolliert • Änderungen in Gesetzen, Normen oder Richtlinien werden systematisch verfolgt und in die Redaktionsprozesse integriert | H25: Bitte auswählen | J25: • frühzeitige Identifikation rechtlicher Anforderungen im Produktlebenszyklus • höheres Vertrauen bei Kunden und Partnern • positive Effekte durch Unternehmensimage und Compliance-Struktur --> Integration bringt Prozesssicherheit und Vertrauen | S25: =IF(H25="Nicht anwendbar","n.a.",0) -> 0 | T25: =IF(H25="Vollständig",1,0) -> 0 | U25: =IF(H25="In den meisten Fällen",0.75,0) -> 0 | V25: =IF(H25="In ein Paar Fällen",0.5,0) -> 0 | W25: =IF(H25="Gar nicht",0,0) -> 0 | X25: =IFERROR(SUM(T25:W28)/COUNTIF(H25:H28,"<>Nicht anwendbar"),"n.a.") -> 0 | Y25: =IF(Y22=1,X25,0) -> 0
C26: Sind aussagekräftige Kennzahlen für die Steuerung von Prozessen im Kontext der Rechtskonformität definiert worden und werden diese regelmäßig kontrolliert? | H26: Bitte auswählen | S26: =IF(H26="Nicht anwendbar","n.a.",0) -> 0 | T26: =IF(H26="Vollständig",1,0) -> 0 | U26: =IF(H26="In den meisten Fällen",0.75,0) -> 0 | V26: =IF(H26="In ein Paar Fällen",0.5,0) -> 0 | W26: =IF(H26="Gar nicht",0,0) -> 0
C27: Werden Änderungen in Gesetzen, Normen oder Richtlinien systematisch verfolgt und in die Redaktionsprozesse integriert? | H27: Bitte auswählen | S27: =IF(H27="Nicht anwendbar","n.a.",0) -> 0 | T27: =IF(H27="Vollständig",1,0) -> 0 | U27: =IF(H27="In den meisten Fällen",0.75,0) -> 0 | V27: =IF(H27="In ein Paar Fällen",0.5,0) -> 0 | W27: =IF(H27="Gar nicht",0,0) -> 0
B28: 5 | C28: Wird die Aktualität relevanter Rechtsdokumente automatisiert sichergestellt? | F28: • Die Aktualität relevanter Rechtsdokumente wird automatisiert sichergestellt • Die Rechts- und Normenrecherche wird KI-gestützt durchgeführt • KI unterstützt beim Ableiten von anwendungsspezifischen Maßnahmen zur Sicherstellung der Rechtskonformität • Verbesserungspotenziale für die Rechtskonformität der Dokumentation werden kontinuierlich identifiziert, bewertet und umgesetzt | H28: Bitte auswählen | J28: • minimiertes Haftungsrisiko • Wettbewerbsvorteil durch schnelle Anpassung an neue rechtliche Rahmenbedingungen • strategischer Beitrag zur Unternehmenssicherheit und Nachhaltigkeit --> proaktive Steuerung wird zum strategischen Wettbewerbsvorteil | S28: =IF(H28="Nicht anwendbar","n.a.",0) -> 0 | T28: =IF(H28="Vollständig",1,0) -> 0 | U28: =IF(H28="In den meisten Fällen",0.75,0) -> 0 | V28: =IF(H28="In ein Paar Fällen",0.5,0) -> 0 | W28: =IF(H28="Gar nicht",0,0) -> 0 | X28: =IFERROR(SUM(T28:W31)/COUNTIF(H28:H31,"<>Nicht anwendbar"),"n.a.") -> 0 | Y28: =IF(Y25=1,X28,0) -> 0
C29: Wird die Rechts- und Normenrecherche KI-gestützt durchgeführt? Unterstützt KI beim Ableiten von anwendungsspezifischen Maßnahmen zur Sicherstellung der Rechtskonformität? | H29: Bitte auswählen | S29: =IF(H29="Nicht anwendbar","n.a.",0) -> 0 | T29: =IF(H29="Vollständig",1,0) -> 0 | U29: =IF(H29="In den meisten Fällen",0.75,0) -> 0 | V29: =IF(H29="In ein Paar Fällen",0.5,0) -> 0 | W29: =IF(H29="Gar nicht",0,0) -> 0
C30: Werden Verbesserungspotenziale für die Rechtskonformität der Dokumentation kontinuierlich identifiziert, bewertet und umgesetzt? | H30: Bitte auswählen | S30: =IF(H30="Nicht anwendbar","n.a.",0) -> 0 | T30: =IF(H30="Vollständig",1,0) -> 0 | U30: =IF(H30="In den meisten Fällen",0.75,0) -> 0 | V30: =IF(H30="In ein Paar Fällen",0.5,0) -> 0 | W30: =IF(H30="Gar nicht",0,0) -> 0

Sheet TD1.6
B4: Die Reifegrade werden anhand der jeweiligen Antwort ermittelt. Eine Erläuterung des Aufbaus der Reifegrade und der Antwortmöglichkeiten finden Sie in den Ausfüllhinweisen.
B6: TD1.6 | C6: Redaktionsprozess - Qualitätssicherung | K6: Reifegrad: | L6: =ROUNDDOWN(Z17/0.25,0)*0.25 -> 0 | M6: =IF(L6<1,"Unvollständig",IF(L6<2,"Initial",IF(L6<3,"Gemanagt",IF(L6<4,"Definiert",IF(L6<5,"Quantitativ gemanagt",IF(L6<6,"Optimiert","Ausstehend")))))) -> Unvollständig
B7: Zweck | C7: Die Qualitätssicherung im Redaktionsprozess dient dazu, die Richtigkeit, Vollständigkeit, Verständlichkeit und Konsistenz der technischen Dokumentation sicherzustellen. Ziel ist es, Fehler zu vermeiden, Nutzerfreundlichkeit zu gewährleisten und die Einhaltung interner sowie externer Standards abzusichern.
B8: Ergebnisse | C8: • Inhalte der Dokumentation werden regelmäßig überprüft und freigegeben. • Konsistenz, Terminologie und formale Standards sind eingehalten. • Fehler, Inkonsistenzen oder fehlende Informationen werden identifiziert und korrigiert. • Nachweise für durchgeführte Prüfungen und Freigaben liegen vor.
B9: Basispraktiken | C9: • Durchführung formaler und inhaltlicher Prüfungen (Fachprüfung, Sprachprüfung, Normprüfung). • Einsatz standardisierter Methoden und Tools (z. B. Stylechecker). • Definierte Abläufe für Freigaben und Korrekturschleifen. • Systematische Erfassung und Bearbeitung von Fehlern oder Änderungsbedarfen. • Einbindung relevanter Fachbereiche in Prüf- und Freigabeprozesse.
B10: Arbeitsprodukte | C10: • Prüf- und Freigabedokumente (Checklisten, Prüfprotokolle, Freigabeformulare). • Richtlinien und Standards für Dokumentationsqualität (z. B. Styleguides). • Versionierte Dokumentationsstände mit nachvollziehbarer Historie. • Dokumentierte Korrekturmaßnahmen und Lessons Learned.
B12: Erhebung der Reifegrade
B14: Zu Reifegrad | C14: Kontrollfrage | F14: Abnahmekriterien | H14: Umsetzung | J14: Nutzen bei Erreichen der Stufe | N14: Kommentar/Hinweis | T14: Listenindex | Y14: Zw. Ergebnis | Z14: Ergebnis
B16: 1 | C16: Werden zumindest situativ im Fall eines Defizits / Schadensfall qualitätssichernde Maßnahmen durchgeführt? | F16: • Im Fall eines Defizits / Schadensfall werden qualitätssichernde Maßnahmen durchgeführt • Es existieren erste Qualitätsmerkmale zur Beurteilung des Redaktionsprozesses | H16: Bitte auswählen | J16: / | S16: =IF(H16="Nicht anwendbar","n.a.",0) -> 0 | T16: =IF(H16="Vollständig",1,0) -> 0 | U16: =IF(H16="In den meisten Fällen",0.75,0) -> 0 | V16: =IF(H16="In ein Paar Fällen",0.5,0) -> 0 | W16: =IF(H16="Gar nicht",0,0) -> 0
C17: Existieren erste Qualitätsmerkmale (z.B. die Einhaltung von Fristen) zur Beurteilung des Redaktionsprozesses? | H17: Bitte auswählen | S17: =IF(H17="Nicht anwendbar","n.a.",0) -> 0 | T17: =IF(H17="Vollständig",1,0) -> 0 | U17: =IF(H17="In den meisten Fällen",0.75,0) -> 0 | V17: =IF(H17="In ein Paar Fällen",0.5,0) -> 0 | W17: =IF(H17="Gar nicht",0,0) -> 0 | X17: =IFERROR(SUM(T16:W17)/COUNTIF(H16:H17,"<>Nicht anwendbar"),"n.a.") -> 0 | Y17: =X17 -> 0 | Z17: =IF(Y17<>"n.a.",SUM(Y17,Y18,Y20,Y24,Y28),NA()) -> 0 | AG17: =IF(X17>0.5,"Umgesetzt","Nicht umgesetzt") -> Nicht umgesetzt
B18: 2 | C18: Werden einfache Methoden zur Qualitätssicherung (z.B. Vier-Augen-Prinzip, Checklisten) durchgeführt? | F18: • Es werden einfache Methoden zur Qualitätssicherung durchgeführt • Durchgeführte qualitätssichernde Maßnahmen werden gelegentlich dokumentiert | H18: Bitte auswählen | J18: • höhere Verlässlichkeit bei wiederkehrenden Aufgaben | S18: =IF(H18="Nicht anwendbar","n.a.",0) -> 0 | T18: =IF(H18="Vollständig",1,0) -> 0 | U18: =IF(H18="In den meisten Fällen",0.75,0) -> 0 | V18: =IF(H18="In ein Paar Fällen",0.5,0) -> 0 | W18: =IF(H18="Gar nicht",0,0) -> 0 | X18: =IFERROR(SUM(T18:W19)/COUNTIF(H18:H19,"<>Nicht anwendbar"),"n.a.") -> 0 | Y18: =IF(X17=1,X18,0) -> 0 | AG18: =IF(X18>0.5,"Umgesetzt","Nicht umgesetzt") -> Nicht umgesetzt
C19: Werden durchgeführte qualitätssichernde Maßnahmen gelegentlich dokumentiert? | H19: Bitte auswählen | S19: =IF(H19="Nicht anwendbar","n.a.",0) -> 0 | T19: =IF(H19="Vollständig",1,0) -> 0 | U19: =IF(H19="In den meisten Fällen",0.75,0) -> 0 | V19: =IF(H19="In ein Paar Fällen",0.5,0) -> 0 | W19: =IF(H19="Gar nicht",0,0) -> 0 | AG19: =IF(X19>0.5,"Umgesetzt","Nicht umgesetzt") -> Nicht umgesetzt
B20: 3 | C20: Gibt es dokumentierte Prozesse und Verantwortlichkeiten für die Qualitätssicherung der Dokumentation? Sind diese Prozesse in der Redaktion verankert? | F20: • Es gibt dokumentierte Prozesse und Verantwortlichkeiten für die Qualitätssicherung der Dokumentation • Diese Prozesse sind in der Redaktion verankert • Standardisierte Prüfverfahren werden eingesetzt, um die Dokumentationsqualität sicherzustellen • Die Freigabe der Dokumentation ist an definierte Qualitätskriterien gebunden • Es existieren prozessbezogene Leitfäden für den redaktionellen Prozess (Redaktionsleitfaden) • Diese sind verbindlich anzuwenden | H20: Bitte auswählen | J20: • messbare Qualität der Dokumentation • Vertrauen in Ergebnisse steigt bei internen und externen Stakeholdern | S20: =IF(H20="Nicht anwendbar","n.a.",0) -> 0 | T20: =IF(H20="Vollständig",1,0) -> 0 | U20: =IF(H20="In den meisten Fällen",0.75,0) -> 0 | V20: =IF(H20="In ein Paar Fällen",0.5,0) -> 0 | W20: =IF(H20="Gar nicht",0,0) -> 0 | X20: =IFERROR(SUM(T20:W23)/COUNTIF(H20:H23,"<>Nicht anwendbar"),"n.a.") -> 0 | Y20: =IF(Y18=1,X20,0) -> 0
C21: Werden standardisierte Prüfverfahren eingesetzt, um die Dokumentationsqualität sicherzustellen? | H21: Bitte auswählen | S21: =IF(H21="Nicht anwendbar","n.a.",0) -> 0 | T21: =IF(H21="Vollständig",1,0) -> 0 | U21: =IF(H21="In den meisten Fällen",0.75,0) -> 0 | V21: =IF(H21="In ein Paar Fällen",0.5,0) -> 0 | W21: =IF(H21="Gar nicht",0,0) -> 0
C22: Ist die Freigabe der Dokumentation an definierte Qualitätskriterien gebunden? | H22: Bitte auswählen | S22: =IF(H22="Nicht anwendbar","n.a.",0) -> 0 | T22: =IF(H22="Vollständig",1,0) -> 0 | U22: =IF(H22="In den meisten Fällen",0.75,0) -> 0 | V22: =IF(H22="In ein Paar Fällen",0.5,0) -> 0 | W22: =IF(H22="Gar nicht",0,0) -> 0
C23: Existieren prozessbezogene Leitfäden für den redaktionellen Prozess (Redaktionsleitfaden)? Sind diese verbindlich anzuwenden? | H23: Bitte auswählen | S23: =IF(H23="Nicht anwendbar","n.a.",0) -> 0 | T23: =IF(H23="Vollständig",1,0) -> 0 | U23: =IF(H23="In den meisten Fällen",0.75,0) -> 0 | V23: =IF(H23="In ein Paar Fällen",0.5,0) -> 0 | W23: =IF(H23="Gar nicht",0,0) -> 0
B24: 4 | C24: Wird die Qualitätssicherung regelmäßig überwacht und anhand von Kennzahlen bewertet (z. B. Fehlerquote, Nacharbeitsaufwand)? | F24: • Die Qualitätssicherung wird regelmäßig überwacht und anhand von Kennzahlen bewertet • Die Qualitätssicherung wird als Teil der Unternehmenskultur gesehen • Der Redaktionsleitfaden ist verknüpft mit der Corporate Identity/ dem Corporate Design • Es werden systematische Fehleranalysen bei Qualitätsmängeln durchgeführt | H24: Bitte auswählen | J24: • frühzeitige Fehlerekennung reduziert Korrekturschleifen • höhere Termintreue durch stabile QS-Prozesse • Qualität wird Teil des Gesmatprozesses und geschieht nicht mehr nachgelagert | S24: =IF(H24="Nicht anwendbar","n.a.",0) -> 0 | T24: =IF(H24="Vollständig",1,0) -> 0 | U24: =IF(H24="In den meisten Fällen",0.75,0) -> 0 | V24: =IF(H24="In ein Paar Fällen",0.5,0) -> 0 | W24: =IF(H24="Gar nicht",0,0) -> 0 | X24: =IFERROR(SUM(T24:W27)/COUNTIF(H24:H27,"<>Nicht anwendbar"),"n.a.") -> 0 | Y24: =IF(Y20=1,X24,0) -> 0
C25: Wird die Qualitätssicherung als Teil der Unternehmenskultur gesehen? | H25: Bitte auswählen | S25: =IF(H25="Nicht anwendbar","n.a.",0) -> 0 | T25: =IF(H25="Vollständig",1,0) -> 0 | U25: =IF(H25="In den meisten Fällen",0.75,0) -> 0 | V25: =IF(H25="In ein Paar Fällen",0.5,0) -> 0 | W25: =IF(H25="Gar nicht",0,0) -> 0
C26: Ist der Redaktionsleitfaden verknüpft mit der Corporate Identity/ dem Corporate Design? | H26: Bitte auswählen | S26: =IF(H26="Nicht anwendbar","n.a.",0) -> 0 | T26: =IF(H26="Vollständig",1,0) -> 0 | U26: =IF(H26="In den meisten Fällen",0.75,0) -> 0 | V26: =IF(H26="In ein Paar Fällen",0.5,0) -> 0 | W26: =IF(H26="Gar nicht",0,0) -> 0
C27: Werden systematische Fehleranalysen bei Qualitätsmängeln durchgeführt? | H27: Bitte auswählen | S27: =IF(H27="Nicht anwendbar","n.a.",0) -> 0 | T27: =IF(H27="Vollständig",1,0) -> 0 | U27: =IF(H27="In den meisten Fällen",0.75,0) -> 0 | V27: =IF(H27="In ein Paar Fällen",0.5,0) -> 0 | W27: =IF(H27="Gar nicht",0,0) -> 0
B28: 5 | C28: Werden Verfahren und Tools der Qualitätssicherung regelmäßig überprüft und weiterentwickelt? | F28: • Verfahren und Tools der Qualitätssicherung werden regelmäßig überprüft und weiterentwickelt • Erfahrungen werden systematisch genutzt, um Prüfverfahren zu optimieren • Ein proaktiver Einsatz innovativer Methoden erfolgt | H28: Bitte auswählen | J28: • Qualitätsdaten unterstützen die Weiterentwicklung von Prozessen und Produkten • Wettbewerbsvorteil durch nachweislich verlässliche Dokumentation • höhere Kundenzufriedenheit und geringeres Risiko von Reklamation | S28: =IF(H28="Nicht anwendbar","n.a.",0) -> 0 | T28: =IF(H28="Vollständig",1,0) -> 0 | U28: =IF(H28="In den meisten Fällen",0.75,0) -> 0 | V28: =IF(H28="In ein Paar Fällen",0.5,0) -> 0 | W28: =IF(H28="Gar nicht",0,0) -> 0 | X28: =IFERROR(SUM(T28:W30)/COUNTIF(H28:H30,"<>Nicht anwendbar"),"n.a.") -> 0 | Y28: =IF(Y24=1,X28,0) -> 0
C29: Werden Erfahrungen (z. B. Lessons Learned) systematisch genutzt, um Prüfverfahren zu optimieren? | H29: Bitte auswählen | S29: =IF(H29="Nicht anwendbar","n.a.",0) -> 0 | T29: =IF(H29="Vollständig",1,0) -> 0 | U29: =IF(H29="In den meisten Fällen",0.75,0) -> 0 | V29: =IF(H29="In ein Paar Fällen",0.5,0) -> 0 | W29: =IF(H29="Gar nicht",0,0) -> 0
C30: Erfolgt ein proaktiver Einsatz innovativer Methoden (z. B. KI-gestützte Qualitätssicherung, automatisierte Prüfungen)? | H30: Bitte auswählen | S30: =IF(H30="Nicht anwendbar","n.a.",0) -> 0 | T30: =IF(H30="Vollständig",1,0) -> 0 | U30: =IF(H30="In den meisten Fällen",0.75,0) -> 0 | V30: =IF(H30="In ein Paar Fällen",0.5,0) -> 0 | W30: =IF(H30="Gar nicht",0,0) -> 0

Sheet TD2.1
B4: Die Reifegrade werden anhand der jeweiligen Antwort ermittelt. Eine Erläuterung des Aufbaus der Reifegrade und der Antwortmöglichkeiten finden Sie in den Ausfüllhinweisen.
B6: TD2.1 | C6: Content Management - Dokumentationsstrukturierung | K6: Reifegrad: | L6: =ROUNDDOWN(Z16/0.25,0)*0.25 -> 0 | M6: =IF(L6<1,"Unvollständig",IF(L6<2,"Initial",IF(L6<3,"Gemanagt",IF(L6<4,"Definiert",IF(L6<5,"Quantitativ gemanagt",IF(L6<6,"Optimiert","Ausstehend")))))) -> Unvollständig
B7: Zweck | C7: Die Dokumentationsstrukturierung hat den Zweck, Inhalte der technischen Dokumentation systematisch in logische, konsistente und wiederverwendbare Einheiten zu gliedern. Es wird darauf abgezielt, die Verständlichkeit für die Zielgruppen zu erhöhen, die Pflege zu vereinfachen und die Grundlage für Mehrfachnutzung, Modularisierung und effiziente Publikation zu schaffen
B8: Ergebnisse | C8: • Inhalte sind nachvollziehbar in Kapitel, Module oder Informationseinheiten gegliedert. • Strukturierungsprinzipien (z. B. modulare Inhalte, hierarchische Gliederung) sind definiert und werden eingehalten. • Dokumentationen sind konsistent aufgebaut und unterstützen verschiedene Zielgruppen. • Wiederverwendbarkeit und effiziente Verwaltung von Inhalten sind gewährleistet.
B9: Basispraktiken | C9: • Definition und Umsetzung von Gliederungsprinzipien (z. B. Kapitelstruktur, Topic-orientiertes Schreiben). • Einsatz von Modulen, wiederverwendbaren Bausteinen oder standardisierten Content-Patterns. • Verwendung von Metadaten zur Kategorisierung und Verwaltung der Inhalte. • Regelmäßige Prüfung der Dokumentationsstruktur auf Konsistenz und Zielgruppenorientierung. • Abstimmung der Struktur mit den Anforderungen von Redaktionssystemen oder Publikationskanälen.
B10: Arbeitsprodukte | C10: • Strukturpläne, Inhaltsmodelle oder Dokumentationskonzepte. • Modularisierte Inhalte (Topics, Bausteine, Module). • Metadaten, Klassifikationen oder Tags zur inhaltlichen Strukturierung. • Versionierte Dokumentationsstände mit nachvollziehbarer Struktur.
B12: Erhebung der Reifegrade
B14: Zu Reifegrad | C14: Kontrollfrage | F14: Abnahmekriterien | H14: Umsetzung | J14: Nutzen bei Erreichen der Stufe | N14: Kommentar/Hinweis | T14: Listenindex | Y14: Zw. Ergebnis | Z14: Ergebnis
B16: 1 | C16: Wird die Dokumentation von den Mitarbeitenden mindestens situativ strukturiert, sodass sie unabhängig von festen Vorgaben dennoch konsistent auf Seiten‑ bzw. Kapitelebene aufgebaut ist? | F16: • Die Mitarbeitenden strukturieren die Dokumentation individuell, aber konsistent • Die Strukturierung ist auf Seiten-/ Kapitelebene | H16: Bitte auswählen | J16: / | S16: =IF(H16="Nicht anwendbar","n.a.",0) -> 0 | T16: =IF(H16="Vollständig",1,0) -> 0 | U16: =IF(H16="In den meisten Fällen",0.75,0) -> 0 | V16: =IF(H16="In ein Paar Fällen",0.5,0) -> 0 | W16: =IF(H16="Gar nicht",0,0) -> 0 | X16: =IF(S16>0,"n.a.",SUM(S16:W16)) -> 0 | Y16: =X16 -> 0 | Z16: =IF(Y16<>"n.a.",SUM(Y16,Y17,Y19,Y22,Y25),NA()) -> 0 | AG16: =IF(X16>0.5,"Umgesetzt","Nicht umgesetzt") -> Nicht umgesetzt
B17: 2 | C17: Existieren Vorlagen oder Musterdokumente zur Strukturierung der Dokumentation? | F17: • Es existieren Vorlagen oder Musterdokumente zur Strukturierung der Dokumentation • Die Vorlagen werden von den Mitarbeitenden verwendet | H17: Bitte auswählen | J17: • verbesserte Orientierung für Redakteur:innen • weniger Nacharbeit durch wiederkehrende Layouts und Strukturen | S17: =IF(H17="Nicht anwendbar","n.a.",0) -> 0 | T17: =IF(H17="Vollständig",1,0) -> 0 | U17: =IF(H17="In den meisten Fällen",0.75,0) -> 0 | V17: =IF(H17="In ein Paar Fällen",0.5,0) -> 0 | W17: =IF(H17="Gar nicht",0,0) -> 0 | X17: =IFERROR(SUM(T17:W18)/COUNTIF(H17:H18,"<>Nicht anwendbar"),"n.a.") -> 0 | Y17: =IF(Y16=1,X17,0) -> 0 | AG17: =IF(X17>0.5,"Umgesetzt","Nicht umgesetzt") -> Nicht umgesetzt
C18: Werden die Vorlagen von den Mitarbeitenden verwendet? | H18: Bitte auswählen | S18: =IF(H18="Nicht anwendbar","n.a.",0) -> 0 | T18: =IF(H18="Vollständig",1,0) -> 0 | U18: =IF(H18="In den meisten Fällen",0.75,0) -> 0 | V18: =IF(H18="In ein Paar Fällen",0.5,0) -> 0 | W18: =IF(H18="Gar nicht",0,0) -> 0 | AG18: =IF(X18>0.5,"Umgesetzt","Nicht umgesetzt") -> Nicht umgesetzt
B19: 3 | C19: Sind verbindliche Strukturkonventionen bzw. Informationsarchitekturen zur Strukturierung der Dokumentation vorhanden (z.B. DITA)? | F19: • Es sind verbindliche Strukturkonventionen bzw. Informationsarchitekturen zur Strukturierung der Dokumentation vorhanden • Inhalte werden systematisch in Module oder Topics gegliedert • Die Strukturierung wird konsistent über alle Projekte und durch alle Mitarbeitende umgesetzt | H19: Bitte auswählen | J19: • hohe Konsistenz über alle Dokumente hinweg • bessere Wiederverwendbarkeit von Inhalten • Effizientere Erstellung durch klare Vorgaben • erleichterte Einarbeitung neuer Mitarbeiter | S19: =IF(H19="Nicht anwendbar","n.a.",0) -> 0 | T19: =IF(H19="Vollständig",1,0) -> 0 | U19: =IF(H19="In den meisten Fällen",0.75,0) -> 0 | V19: =IF(H19="In ein Paar Fällen",0.5,0) -> 0 | W19: =IF(H19="Gar nicht",0,0) -> 0 | X19: =IFERROR(SUM(T19:W21)/COUNTIF(H19:H21,"<>Nicht anwendbar"),"n.a.") -> 0 | Y19: =IF(Y17=1,X19,0) -> 0
C20: Werden Inhalte systematisch in Module oder Topics gegliedert? | H20: Bitte auswählen | S20: =IF(H20="Nicht anwendbar","n.a.",0) -> 0 | T20: =IF(H20="Vollständig",1,0) -> 0 | U20: =IF(H20="In den meisten Fällen",0.75,0) -> 0 | V20: =IF(H20="In ein Paar Fällen",0.5,0) -> 0 | W20: =IF(H20="Gar nicht",0,0) -> 0
C21: Wird die Strukturierung konsistent über alle Projekte und durch alle Mitarbeitende umgesetzt? | H21: Bitte auswählen | S21: =IF(H21="Nicht anwendbar","n.a.",0) -> 0 | T21: =IF(H21="Vollständig",1,0) -> 0 | U21: =IF(H21="In den meisten Fällen",0.75,0) -> 0 | V21: =IF(H21="In ein Paar Fällen",0.5,0) -> 0 | W21: =IF(H21="Gar nicht",0,0) -> 0
B22: 4 | C22: Wird die Einhaltung der Strukturierungsvorgaben regelmäßig überprüft (z. B. durch Reviews, automatisierte Checks)? | F22: • Die Einhaltung der Strukturierungsvorgaben wird regelmäßig überprüft • Metadaten oder Klassifikationen werden systematisch eingesetzt, um die Strukturierung zu unterstützen • Die Struktur folgt einem semantischen Modell • Die Dokumentationsstruktur wird regelmäßig bewertet und weiterentwickelt | H22: Bitte auswählen | J22: • Flexibilität für verschiedene Publikationsformate • Effizienzsteigerung durch verbesserte Auffindbarkeit und Wiederverwendung von Modulen • Qualitätssicherung durch einheitliche Module • deutliche Zeitersparnis bei Aktualisierungen | S22: =IF(H22="Nicht anwendbar","n.a.",0) -> 0 | T22: =IF(H22="Vollständig",1,0) -> 0 | U22: =IF(H22="In den meisten Fällen",0.75,0) -> 0 | V22: =IF(H22="In ein Paar Fällen",0.5,0) -> 0 | W22: =IF(H22="Gar nicht",0,0) -> 0 | X22: =IFERROR(SUM(T22:W24)/COUNTIF(H22:H24,"<>Nicht anwendbar"),"n.a.") -> 0 | Y22: =IF(Y19=1,X22,0) -> 0
C23: Werden Metadaten oder Klassifikationen systematisch eingesetzt, um die Strukturierung zu unterstützen? Folgt die Struktur einem semantischen Modell (z.B. iiRDS)? | H23: Bitte auswählen | S23: =IF(H23="Nicht anwendbar","n.a.",0) -> 0 | T23: =IF(H23="Vollständig",1,0) -> 0 | U23: =IF(H23="In den meisten Fällen",0.75,0) -> 0 | V23: =IF(H23="In ein Paar Fällen",0.5,0) -> 0 | W23: =IF(H23="Gar nicht",0,0) -> 0
C24: Wird die Dokumentationsstruktur regelmäßig bewertet und weiterentwickelt? | H24: Bitte auswählen | S24: =IF(H24="Nicht anwendbar","n.a.",0) -> 0 | T24: =IF(H24="Vollständig",1,0) -> 0 | U24: =IF(H24="In den meisten Fällen",0.75,0) -> 0 | V24: =IF(H24="In ein Paar Fällen",0.5,0) -> 0 | W24: =IF(H24="Gar nicht",0,0) -> 0
B25: 5 | C25: Erfolgt eine kontinuierliche Optimierung der Dokumentationsstruktur anhand von Nutzerfeedback und Best Practices? | F25: • Es erfolgt eine kontinuierliche Optimierung der Dokumentationsstruktur anhand von Nutzerfeedback und Best Practices • Die Dokumentationsstruktur flexibel an neue Publikationskanäle, Zielgruppen und Technologien angepasst • innovative Ansätze werden aktiv evaluiert und eingesetzt | H25: Bitte auswählen | J25: • verbesserte Nutzerfreundlichkeit durch passgenaue Inhalte • Wettbewerbsvorteil durch innovative Informationsbereitstellung • erhöhte Aktualität, da Inhalte automatisiert zusammengestellt werden können • strategische Verankerung der Dokumentation als Teil digitaler Services | S25: =IF(H25="Nicht anwendbar","n.a.",0) -> 0 | T25: =IF(H25="Vollständig",1,0) -> 0 | U25: =IF(H25="In den meisten Fällen",0.75,0) -> 0 | V25: =IF(H25="In ein Paar Fällen",0.5,0) -> 0 | W25: =IF(H25="Gar nicht",0,0) -> 0 | X25: =IFERROR(SUM(T25:W27)/COUNTIF(H25:H27,"<>Nicht anwendbar"),"n.a.") -> 0 | Y25: =IF(Y22=1,X25,0) -> 0
C26: Wird die Dokumentationsstruktur flexibel an neue Publikationskanäle, Zielgruppen und Technologien angepasst? | H26: Bitte auswählen | S26: =IF(H26="Nicht anwendbar","n.a.",0) -> 0 | T26: =IF(H26="Vollständig",1,0) -> 0 | U26: =IF(H26="In den meisten Fällen",0.75,0) -> 0 | V26: =IF(H26="In ein Paar Fällen",0.5,0) -> 0 | W26: =IF(H26="Gar nicht",0,0) -> 0
C27: Werden innovative Ansätze (z. B. semantische Modelle, KI-gestützte Strukturierung) aktiv evaluiert und eingesetzt? | H27: Bitte auswählen | S27: =IF(H27="Nicht anwendbar","n.a.",0) -> 0 | T27: =IF(H27="Vollständig",1,0) -> 0 | U27: =IF(H27="In den meisten Fällen",0.75,0) -> 0 | V27: =IF(H27="In ein Paar Fällen",0.5,0) -> 0 | W27: =IF(H27="Gar nicht",0,0) -> 0

Sheet TD2.2
B4: Die Reifegrade werden anhand der jeweiligen Antwort ermittelt. Eine Erläuterung des Aufbaus der Reifegrade und der Antwortmöglichkeiten finden Sie in den Ausfüllhinweisen.
B6: TD2.2 | C6: Content Management - Variantenmanagement | K6: Reifegrad: | L6: =ROUNDDOWN(Z16/0.25,0)*0.25 -> 0 | M6: =IF(L6<1,"Unvollständig",IF(L6<2,"Initial",IF(L6<3,"Gemanagt",IF(L6<4,"Definiert",IF(L6<5,"Quantitativ gemanagt",IF(L6<6,"Optimiert","Ausstehend")))))) -> Unvollständig
B7: Zweck | C7: Produkt- und Dokumentationsvarianten effizient verwalten, sodass unterschiedliche Ausprägungen (z. B. Produktlinien, Konfigurationen, Märkte, Sprachen) konsistent und ressourcenschonend abgebildet werden können. Ziel ist die Vermeidung redundanter Inhalte, die Sicherstellung von Konsistenz und die effiziente Wiederverwendung von Dokumentationsbausteinen bezogen auf unterschiedliche Varianten
B8: Ergebnisse | C8: • Varianten in der Dokumentation sind identifiziert, dokumentiert und konsistent abgebildet. • Unterschiede und Gemeinsamkeiten zwischen Varianten sind transparent dargestellt. • Inhalte werden gezielt wiederverwendet, um Redundanzen zu minimieren. • Varianten sind nachvollziehbar mit Produktdaten, Metadaten oder Strukturen verknüpft.
B9: Basispraktiken | C9: • Identifikation und Dokumentation relevanter Varianten (Produkte, Märkte, Sprachen). • Nutzung von modularen Inhalten und Wiederverwendungsmechanismen. • Einsatz von Metadaten, Variablen oder Filtermechanismen zur Steuerung von Varianten. • Regelmäßige Abstimmung zwischen Redaktion, Produktentwicklung und Vertrieb zu Variantenanforderungen. • Systematische Prüfung auf Konsistenz zwischen Varianten.
B10: Arbeitsprodukte | C10: • Variantenlisten oder Konfigurationsdokumentationen. • Modularisierte Inhalte mit Variantenkennzeichnung (z. B. über Metadaten, Attribute, Filter). • Strukturpläne oder Regelwerke zur Steuerung von Varianten. • Publikationsausgaben für spezifische Produkt- oder Zielgruppenvarianten.
B12: Erhebung der Reifegrade
B14: Zu Reifegrad | C14: Kontrollfrage | F14: Abnahmekriterien | H14: Umsetzung | J14: Nutzen bei Erreichen der Stufe | N14: Kommentar/Hinweis | T14: Listenindex | Y14: Zw. Ergebnis | Z14: Ergebnis
B16: 1 | C16: Werden Varianten mindestens manuell Ad-Hoc gepflegt, etwa durch das Kopieren und Anpassen kompletter Dokumente? | F16: • Varianten werden manuell gepflegt, etwa durch das Kopieren und Anpassen kompletter Dokumente | H16: Bitte auswählen | J16: / | S16: =IF(H16="Nicht anwendbar","n.a.",0) -> 0 | T16: =IF(H16="Vollständig",1,0) -> 0 | U16: =IF(H16="In den meisten Fällen",0.75,0) -> 0 | V16: =IF(H16="In ein Paar Fällen",0.5,0) -> 0 | W16: =IF(H16="Gar nicht",0,0) -> 0 | X16: =IF(S16>0,"n.a.",SUM(S16:W16)) -> 0 | Y16: =X16 -> 0 | Z16: =IF(Y16<>"n.a.",SUM(Y16,Y17,Y19,Y22,Y26),NA()) -> 0 | AG16: =IF(X16>0.5,"Umgesetzt","Nicht umgesetzt") -> Nicht umgesetzt
B17: 2 | C17: Werden Varianten manuell in Listen verwaltet (z.B. Excel)? | F17: • Varianten werden manuell in Listen verwaltet • Das Anlegen neuer Varianten und Arbeiten mit Varianten wird dokumentiert | H17: Bitte auswählen | J17: • vereinfachte Wiederverwendung bestimmter Inhalte • bessere Orientierung bei häufig genutzten Varianten • weniger Redundanzen | S17: =IF(H17="Nicht anwendbar","n.a.",0) -> 0 | T17: =IF(H17="Vollständig",1,0) -> 0 | U17: =IF(H17="In den meisten Fällen",0.75,0) -> 0 | V17: =IF(H17="In ein Paar Fällen",0.5,0) -> 0 | W17: =IF(H17="Gar nicht",0,0) -> 0 | X17: =IFERROR(SUM(T17:W18)/COUNTIF(H17:H18,"<>Nicht anwendbar"),"n.a.") -> 0 | Y17: =IF(X16=1,X17,0) -> 0 | AG17: =IF(X17>0.5,"Umgesetzt","Nicht umgesetzt") -> Nicht umgesetzt
C18: Wird das Anlegen neuer Varianten und Arbeiten mit Varianten dokumentiert? Wird dadurch redundante Arbeit reduziert? | H18: Bitte auswählen | S18: =IF(H18="Nicht anwendbar","n.a.",0) -> 0 | T18: =IF(H18="Vollständig",1,0) -> 0 | U18: =IF(H18="In den meisten Fällen",0.75,0) -> 0 | V18: =IF(H18="In ein Paar Fällen",0.5,0) -> 0 | W18: =IF(H18="Gar nicht",0,0) -> 0 | AG18: =IF(X18>0.5,"Umgesetzt","Nicht umgesetzt") -> Nicht umgesetzt
B19: 3 | C19: Sind Varianten systematisch identifiziert und dokumentiert? | F19: • Varianten sind systematisch identifiziert und dokumentiert • Varianten werden konsistent über modulare Bausteine oder definierte Mechanismen abgebildet • Es gibt dokumentierte Vorgaben oder Regeln für das Variantenmanagement in der Dokumentation | H19: Bitte auswählen | J19: • Effizienzsteigerungen bei Pflege und Erstellung • bessere Planbarkeit von Übersetzungen und Produktdokumentationen • reduzierte Fehlerquote durch klare Regeln | S19: =IF(H19="Nicht anwendbar","n.a.",0) -> 0 | T19: =IF(H19="Vollständig",1,0) -> 0 | U19: =IF(H19="In den meisten Fällen",0.75,0) -> 0 | V19: =IF(H19="In ein Paar Fällen",0.5,0) -> 0 | W19: =IF(H19="Gar nicht",0,0) -> 0 | X19: =IFERROR(SUM(T19:W21)/COUNTIF(H19:H21,"<>Nicht anwendbar"),"n.a.") -> 0 | Y19: =IF(Y17=1,X19,0) -> 0
C20: Werden Varianten konsistent über modulare Bausteine oder definierte Mechanismen (z. B. Variablen, Attributsteuerung) abgebildet? | H20: Bitte auswählen | S20: =IF(H20="Nicht anwendbar","n.a.",0) -> 0 | T20: =IF(H20="Vollständig",1,0) -> 0 | U20: =IF(H20="In den meisten Fällen",0.75,0) -> 0 | V20: =IF(H20="In ein Paar Fällen",0.5,0) -> 0 | W20: =IF(H20="Gar nicht",0,0) -> 0
C21: Gibt es dokumentierte Vorgaben oder Regeln für das Variantenmanagement in der Dokumentation? | H21: Bitte auswählen | S21: =IF(H21="Nicht anwendbar","n.a.",0) -> 0 | T21: =IF(H21="Vollständig",1,0) -> 0 | U21: =IF(H21="In den meisten Fällen",0.75,0) -> 0 | V21: =IF(H21="In ein Paar Fällen",0.5,0) -> 0 | W21: =IF(H21="Gar nicht",0,0) -> 0
B22: 4 | C22: Wird die Abbildung von Varianten aktiv überwacht und hinsichtlich Konsistenz und Effizienz bewertet? | F22: • Die Abbildung von Varianten wird aktiv überwacht und hinsichtlich Konsistenz und Effizienz bewertet • Metadaten oder Regelwerke werden systematisch eingesetzt, um Varianten zu steuern • Die Ausleitung verschiedener Variantendimensionen erfolgt automatisiert • Es erfolgt eine Abstimmung zwischen Fachbereichen, um Variantenanforderungen konsistent umzusetzen | H22: Bitte auswählen | J22: • hohe Wiederverwendbarkeit von Inhalten • geringerer Zeit- und Kostenaufwand bei Änderungen • schnelle Anpassung an neue Varianten • konsistente Qualität über alle Varianten hinweg | S22: =IF(H22="Nicht anwendbar","n.a.",0) -> 0 | T22: =IF(H22="Vollständig",1,0) -> 0 | U22: =IF(H22="In den meisten Fällen",0.75,0) -> 0 | V22: =IF(H22="In ein Paar Fällen",0.5,0) -> 0 | W22: =IF(H22="Gar nicht",0,0) -> 0 | X22: =IFERROR(SUM(T22:W25)/COUNTIF(H22:H25,"<>Nicht anwendbar"),"n.a.") -> 0 | Y22: =IF(Y19=1,X22,0) -> 0
C23: Werden Metadaten oder Regelwerke systematisch eingesetzt, um Varianten zu steuern? | H23: Bitte auswählen | S23: =IF(H23="Nicht anwendbar","n.a.",0) -> 0 | T23: =IF(H23="Vollständig",1,0) -> 0 | U23: =IF(H23="In den meisten Fällen",0.75,0) -> 0 | V23: =IF(H23="In ein Paar Fällen",0.5,0) -> 0 | W23: =IF(H23="Gar nicht",0,0) -> 0
C24: Erfolgt die Ausleitung verschiedener Variantendimensionen (z. B. Sprache, Marktversion, Produktkonfiguration) automatisiert? | H24: Bitte auswählen | S24: =IF(H24="Nicht anwendbar","n.a.",0) -> 0 | T24: =IF(H24="Vollständig",1,0) -> 0 | U24: =IF(H24="In den meisten Fällen",0.75,0) -> 0 | V24: =IF(H24="In ein Paar Fällen",0.5,0) -> 0 | W24: =IF(H24="Gar nicht",0,0) -> 0
C25: Erfolgt eine Abstimmung zwischen Fachbereichen (z. B. Produktmanagement, Redaktion, Service), um Variantenanforderungen konsistent umzusetzen? | H25: Bitte auswählen | S25: =IF(H25="Nicht anwendbar","n.a.",0) -> 0 | T25: =IF(H25="Vollständig",1,0) -> 0 | U25: =IF(H25="In den meisten Fällen",0.75,0) -> 0 | V25: =IF(H25="In ein Paar Fällen",0.5,0) -> 0 | W25: =IF(H25="Gar nicht",0,0) -> 0
B26: 5 | C26: Wird das Variantenmanagement kontinuierlich anhand von Feedback und Best Practices optimiert? | F26: • Das Variantenmanagement kontinuierlich anhand von Feedback und Best Practices optimiert • Innovative Ansätze (z. B. regelbasierte Publikation, KI-gestützte Variantensteuerung) werden evaluiert und eingesetzt • Varianten werden automatisch bzw. KI-gestützt auf Grundlage der digitalen Zwillinge angelegt und verwaltet • Es erfolgt eine proaktive Anpassung des Variantenmanagements an neue Produkte, Märkte und Zielgruppenanforderungen | H26: Bitte auswählen | J26: • Effizienz durch automatische Ausgabe passender Varianten • flexible und individuelle Bereitstellung für verschiedene Zielgruppen • Wettbewerbsvorteil durch schnelle Reaktionsfähigkeit auf Markt- und Kundenanforderungen | S26: =IF(H26="Nicht anwendbar","n.a.",0) -> 0 | T26: =IF(H26="Vollständig",1,0) -> 0 | U26: =IF(H26="In den meisten Fällen",0.75,0) -> 0 | V26: =IF(H26="In ein Paar Fällen",0.5,0) -> 0 | W26: =IF(H26="Gar nicht",0,0) -> 0 | X26: =IFERROR(SUM(T26:W29)/COUNTIF(H26:H29,"<>Nicht anwendbar"),"n.a.") -> 0 | Y26: =IF(Y22=1,X26,0) -> 0
C27: Werden innovative Ansätze (z. B. regelbasierte Publikation, KI-gestützte Variantensteuerung) evaluiert und eingesetzt? | H27: Bitte auswählen | S27: =IF(H27="Nicht anwendbar","n.a.",0) -> 0 | T27: =IF(H27="Vollständig",1,0) -> 0 | U27: =IF(H27="In den meisten Fällen",0.75,0) -> 0 | V27: =IF(H27="In ein Paar Fällen",0.5,0) -> 0 | W27: =IF(H27="Gar nicht",0,0) -> 0
C28: Werden Varianten automatisch bzw. KI-gestützt auf Grundlage der digitalen Zwillinge angelegt und verwaltet? | H28: Bitte auswählen | S28: =IF(H28="Nicht anwendbar","n.a.",0) -> 0 | T28: =IF(H28="Vollständig",1,0) -> 0 | U28: =IF(H28="In den meisten Fällen",0.75,0) -> 0 | V28: =IF(H28="In ein Paar Fällen",0.5,0) -> 0 | W28: =IF(H28="Gar nicht",0,0) -> 0
C29: Erfolgt eine proaktive Anpassung des Variantenmanagements an neue Produkte, Märkte und Zielgruppenanforderungen? | H29: Bitte auswählen | S29: =IF(H29="Nicht anwendbar","n.a.",0) -> 0 | T29: =IF(H29="Vollständig",1,0) -> 0 | U29: =IF(H29="In den meisten Fällen",0.75,0) -> 0 | V29: =IF(H29="In ein Paar Fällen",0.5,0) -> 0 | W29: =IF(H29="Gar nicht",0,0) -> 0

Sheet TD2.3
B4: Die Reifegrade werden anhand der jeweiligen Antwort ermittelt. Eine Erläuterung des Aufbaus der Reifegrade und der Antwortmöglichkeiten finden Sie in den Ausfüllhinweisen.
B6: TD2.3 | C6: Content Management - Metadatenmanagement | K6: Reifegrad: | L6: =ROUNDDOWN(Z16/0.25,0)*0.25 -> 0 | M6: =IF(L6<1,"Unvollständig",IF(L6<2,"Initial",IF(L6<3,"Gemanagt",IF(L6<4,"Definiert",IF(L6<5,"Quantitativ gemanagt",IF(L6<6,"Optimiert","Ausstehend")))))) -> Unvollständig
B7: Zweck | C7: Inhalte der technischen Dokumentation durch einheitliche und systematisch gepflegte Metadaten auffindbar, wiederverwendbar und für unterschiedliche Kontexte (Publikation, Varianten, Zielgruppen, Prozesse) steuerbar machen. Ziel ist die Strukturierung, Automatisierung und Effizienzsteigerung im Umgang mit Inhalten über den gesamten Dokumentationsprozess hinweg.
B8: Ergebnisse | C8: • Inhalte sind mit relevanten Metadaten versehen. • Einheitliche Regeln für Metadaten sind definiert und umgesetzt. • Metadaten werden konsistent genutzt, um Inhalte zu klassifizieren, zu steuern und zu publizieren. • Metadaten ermöglichen die zielgerichtete Wiederverwendung und Variantenbildung.
B9: Basispraktiken | C9: • Definition relevanter Metadatenkategorien und -felder. • Einheitliche Anwendung von Metadaten bei der Erstellung und Pflege von Inhalten. • Nutzung von Tools oder Systemfunktionen zur automatisierten Vergabe oder Prüfung von Metadaten. • Regelmäßige Überprüfung und Weiterentwicklung des Metadatenmodells.
B10: Arbeitsprodukte | C10: • Metadatenkonzept (Definitionen, Kategorien, Regeln, Taxonomie/Ontologie). • Einheitliche Metadatenfelder und Werte (z. B. Thema, Produkt, Version, Sprache, Zielgruppe). • Dokumentierte Richtlinien für die Vergabe und Pflege von Metadaten. • Inhalte mit angewandten Metadaten, die für Publikation und Wiederverwendung nutzbar sind.
B12: Erhebung der Reifegrade
B14: Zu Reifegrad | C14: Kontrollfrage | F14: Abnahmekriterien | H14: Umsetzung | J14: Nutzen bei Erreichen der Stufe | N14: Kommentar/Hinweis | T14: Listenindex | Y14: Zw. Ergebnis | Z14: Ergebnis
B16: 1 | C16: Können die Mitarbeiter die Dokumentation individuell identifizieren? | F16: • Die Mitarbeiter können die Dokumentation individuell identifizieren | H16: Bitte auswählen | J16: / | S16: =IF(H16="Nicht anwendbar","n.a.",0) -> 0 | T16: =IF(H16="Vollständig",1,0) -> 0 | U16: =IF(H16="In den meisten Fällen",0.75,0) -> 0 | V16: =IF(H16="In ein Paar Fällen",0.5,0) -> 0 | W16: =IF(H16="Gar nicht",0,0) -> 0 | X16: =IF(S16>0,"n.a.",SUM(S16:W16)) -> 0 | Y16: =X16 -> 0 | Z16: =IF(Y16<>"n.a.",SUM(Y16,Y17,Y20,Y23,Y26),NA()) -> 0 | AG16: =IF(X16>0.5,"Umgesetzt","Nicht umgesetzt") -> Nicht umgesetzt
B17: 2 | C17: Können Dokumente mindestens über die Ordnerstruktur und Dateibenennung identifiziert werden? | F17: • Dokumente können über die Ordnerstruktur und Dateibenennung identifiziert werden • Es werden manuell gelegentlich Metadaten auf Dokumenteneben vergeben • Die Metadaten werden für das Versions- und Variantenmanagement verwendet | H17: Bitte auswählen | J17: • erleichterte Auffindbarkeit einzelner Dokumente • reduzierter Suchaufwand im Vergleich zu völlig unstrukturierten Inhalten | S17: =IF(H17="Nicht anwendbar","n.a.",0) -> 0 | T17: =IF(H17="Vollständig",1,0) -> 0 | U17: =IF(H17="In den meisten Fällen",0.75,0) -> 0 | V17: =IF(H17="In ein Paar Fällen",0.5,0) -> 0 | W17: =IF(H17="Gar nicht",0,0) -> 0 | X17: =IFERROR(SUM(T17:W19)/COUNTIF(H17:H19,"<>Nicht anwendbar"),"n.a.") -> 0 | Y17: =IF(X16=1,X17,0) -> 0 | AG17: =IF(X17>0.5,"Umgesetzt","Nicht umgesetzt") -> Nicht umgesetzt
C18: Werden manuell gelegentlich Metadaten auf Dokumenteneben vergeben? | H18: Bitte auswählen | S18: =IF(H18="Nicht anwendbar","n.a.",0) -> 0 | T18: =IF(H18="Vollständig",1,0) -> 0 | U18: =IF(H18="In den meisten Fällen",0.75,0) -> 0 | V18: =IF(H18="In ein Paar Fällen",0.5,0) -> 0 | W18: =IF(H18="Gar nicht",0,0) -> 0 | AG18: =IF(X18>0.5,"Umgesetzt","Nicht umgesetzt") -> Nicht umgesetzt
C19: Werden die Metadaten für das Versions- und Variantenmanagement verwendet? | H19: Bitte auswählen | S19: =IF(H19="Nicht anwendbar","n.a.",0) -> 0 | T19: =IF(H19="Vollständig",1,0) -> 0 | U19: =IF(H19="In den meisten Fällen",0.75,0) -> 0 | V19: =IF(H19="In ein Paar Fällen",0.5,0) -> 0 | W19: =IF(H19="Gar nicht",0,0) -> 0 | AG19: =IF(X19>0.5,"Umgesetzt","Nicht umgesetzt") -> Nicht umgesetzt
B20: 3 | C20: Existieren dokumentierte Regeln und Vorgaben zur einheitlichen Vergabe von Metadaten? | F20: • Es existieren dokumentierte Regeln und Vorgaben zur einheitlichen Vergabe von Metadaten • Metadaten werden systematisch zur Klassifikation, Wiederverwendung oder Steuerung von Inhalten genutzt • Metadatenfelder sind konsistent in allen Projekten und Abteilungen implementiert | H20: Bitte auswählen | J20: • deutlich verbesserte Wiederverwendbarkeit von Inhalten • effiziente Such- und Filtermöglichkeiten | S20: =IF(H20="Nicht anwendbar","n.a.",0) -> 0 | T20: =IF(H20="Vollständig",1,0) -> 0 | U20: =IF(H20="In den meisten Fällen",0.75,0) -> 0 | V20: =IF(H20="In ein Paar Fällen",0.5,0) -> 0 | W20: =IF(H20="Gar nicht",0,0) -> 0 | X20: =IFERROR(SUM(T20:W22)/COUNTIF(H20:H22,"<>Nicht anwendbar"),"n.a.") -> 0 | Y20: =IF(Y17=1,X20,0) -> 0
C21: Werden Metadaten systematisch zur Klassifikation, Wiederverwendung oder Steuerung von Inhalten genutzt? | H21: Bitte auswählen | S21: =IF(H21="Nicht anwendbar","n.a.",0) -> 0 | T21: =IF(H21="Vollständig",1,0) -> 0 | U21: =IF(H21="In den meisten Fällen",0.75,0) -> 0 | V21: =IF(H21="In ein Paar Fällen",0.5,0) -> 0 | W21: =IF(H21="Gar nicht",0,0) -> 0
C22: Sind Metadatenfelder konsistent in allen Projekten und Abteilungen implementiert? | H22: Bitte auswählen | S22: =IF(H22="Nicht anwendbar","n.a.",0) -> 0 | T22: =IF(H22="Vollständig",1,0) -> 0 | U22: =IF(H22="In den meisten Fällen",0.75,0) -> 0 | V22: =IF(H22="In ein Paar Fällen",0.5,0) -> 0 | W22: =IF(H22="Gar nicht",0,0) -> 0
B23: 4 | C23: Wird die Vergabe und Nutzung von Metadaten regelmäßig überwacht und bewertet? | F23: • Die Vergabe und Nutzung von Metadaten wird regelmäßig überwacht und bewertet • Werkzeuge oder Systeme unterstützen die konsistente Anwendung von Metadaten • Die Einhaltung des Metadatenkonzepts wird systematisch überprüft | H23: Bitte auswählen | J23: • deutlich geringerer Pflegeaufwand bei großen Datenmengen • höhere Datenqualität durch Validierungen und Vorgaben | S23: =IF(H23="Nicht anwendbar","n.a.",0) -> 0 | T23: =IF(H23="Vollständig",1,0) -> 0 | U23: =IF(H23="In den meisten Fällen",0.75,0) -> 0 | V23: =IF(H23="In ein Paar Fällen",0.5,0) -> 0 | W23: =IF(H23="Gar nicht",0,0) -> 0 | X23: =IFERROR(SUM(T23:W25)/COUNTIF(H23:H25,"<>Nicht anwendbar"),"n.a.") -> 0 | Y23: =IF(Y20=1,X23,0) -> 0
C24: Unterstützen Werkzeuge oder Systeme die konsistente Anwendung von Metadaten (z. B. Pflichtfelder, automatische Checks)? | H24: Bitte auswählen | S24: =IF(H24="Nicht anwendbar","n.a.",0) -> 0 | T24: =IF(H24="Vollständig",1,0) -> 0 | U24: =IF(H24="In den meisten Fällen",0.75,0) -> 0 | V24: =IF(H24="In ein Paar Fällen",0.5,0) -> 0 | W24: =IF(H24="Gar nicht",0,0) -> 0
C25: Wird die Einhaltung des Metadatenkonzepts systematisch überprüft (z. B. durch Reviews, Audits)? | H25: Bitte auswählen | S25: =IF(H25="Nicht anwendbar","n.a.",0) -> 0 | T25: =IF(H25="Vollständig",1,0) -> 0 | U25: =IF(H25="In den meisten Fällen",0.75,0) -> 0 | V25: =IF(H25="In ein Paar Fällen",0.5,0) -> 0 | W25: =IF(H25="Gar nicht",0,0) -> 0
B26: 5 | C26: Wird das Metadatenmodell regelmäßig weiterentwickelt (z. B. neue Kategorien, semantische Modelle, Ontologien)? | F26: • Das Metadatenmodell wird regelmäßig weiterentwickelt • Die Metadatengenerierung bzw. -vergabe erfolgt automatisch oder KI-basiert • Es werden innovative Ansätze wie KI-gestützte Metadatenerkennung oder semantische Anreicherung eingesetzt | H26: Bitte auswählen | J26: • Effizienz durch automatische Klassifizierung und Kontextsteuerung • personalisierte und kontextsensitve Bereitstellung von Inhalten für verschiedene Nutzergruppen • Wettbewerbsvorteil durch smarte, flexible Content-Ausspielung | S26: =IF(H26="Nicht anwendbar","n.a.",0) -> 0 | T26: =IF(H26="Vollständig",1,0) -> 0 | U26: =IF(H26="In den meisten Fällen",0.75,0) -> 0 | V26: =IF(H26="In ein Paar Fällen",0.5,0) -> 0 | W26: =IF(H26="Gar nicht",0,0) -> 0 | X26: =IFERROR(SUM(T26:W28)/COUNTIF(H26:H28,"<>Nicht anwendbar"),"n.a.") -> 0 | Y26: =IF(Y23=1,X26,0) -> 0
C27: Erfolgt die Metadatengenerierung bzw. -vergabe automatisch oder KI-basiert? | H27: Bitte auswählen | S27: =IF(H27="Nicht anwendbar","n.a.",0) -> 0 | T27: =IF(H27="Vollständig",1,0) -> 0 | U27: =IF(H27="In den meisten Fällen",0.75,0) -> 0 | V27: =IF(H27="In ein Paar Fällen",0.5,0) -> 0 | W27: =IF(H27="Gar nicht",0,0) -> 0
C28: Werden innovative Ansätze wie KI-gestützte Metadatenerkennung oder semantische Anreicherung eingesetzt? | H28: Bitte auswählen | S28: =IF(H28="Nicht anwendbar","n.a.",0) -> 0 | T28: =IF(H28="Vollständig",1,0) -> 0 | U28: =IF(H28="In den meisten Fällen",0.75,0) -> 0 | V28: =IF(H28="In ein Paar Fällen",0.5,0) -> 0 | W28: =IF(H28="Gar nicht",0,0) -> 0

Sheet TD2.4
B4: Die Reifegrade werden anhand der jeweiligen Antwort ermittelt. Eine Erläuterung des Aufbaus der Reifegrade und der Antwortmöglichkeiten finden Sie in den Ausfüllhinweisen.
B6: TD2.4 | C6: Content Management - Terminologiemanagement | K6: Reifegrad: | L6: =ROUNDDOWN(Z16/0.25,0)*0.25 -> 0 | M6: =IF(L6<1,"Unvollständig",IF(L6<2,"Initial",IF(L6<3,"Gemanagt",IF(L6<4,"Definiert",IF(L6<5,"Quantitativ gemanagt",IF(L6<6,"Optimiert","Ausstehend")))))) -> Unvollständig
B7: Zweck | C7: Fachbegriffe, Benennungen und Sprachregelungen konsistent und zielgruppenorientiert in der technischen Dokumentation verwenden. Ziel ist die Eindeutigkeit, Verständlichkeit, Übersetzbarkeit und Rechtskonformität von Inhalten.
B8: Ergebnisse | C8: • Einheitliche Fachterminologie ist definiert und dokumentiert. • Begriffe werden konsistent in allen Dokumenten und Abteilungen verwendet. • Übersetzungen basieren auf festgelegter Terminologie und sind dadurch konsistent. • Terminologische Regeln sind verbindlich und im Redaktionsprozess integriert.
B9: Basispraktiken | C9: • Systematische Erfassung und Pflege relevanter Fachbegriffe. • Abstimmung und Freigabe von Terminologie mit Fachabteilungen und ggf. externen Stakeholdern. • Integration von Terminologieprüfungen in den Redaktionsprozess. • Nutzung von Tools (z. B. Terminologieverwaltungssysteme, Terminologieprüfer). • Regelmäßige Aktualisierung und Erweiterung der Terminologiebasis.
B10: Arbeitsprodukte | C10: • Terminologiedatenbank oder -liste (mit Definitionen, zulässigen Benennungen, Synonymen, Übersetzungen). • Terminologierichtlinien. • Dokumentierte Freigaben für neue oder geänderte Begriffe. • Konsistente Terminologie in den ausgelieferten Dokumentationen.
B12: Erhebung der Reifegrade
B14: Zu Reifegrad | C14: Kontrollfrage | F14: Abnahmekriterien | H14: Umsetzung | J14: Nutzen bei Erreichen der Stufe | N14: Kommentar/Hinweis | T14: Listenindex | Y14: Zw. Ergebnis | Z14: Ergebnis
B16: 1 | C16: Nutzen Mitarbeitende mindestens ihre individuelle Terminologie projektbezogen konsistent? | F16: • Mitarbeitende nutzen ihre individuelle Terminologie projektbezogen konsistent | H16: Bitte auswählen | J16: / | S16: =IF(H16="Nicht anwendbar","n.a.",0) -> 0 | T16: =IF(H16="Vollständig",1,0) -> 0 | U16: =IF(H16="In den meisten Fällen",0.75,0) -> 0 | V16: =IF(H16="In ein Paar Fällen",0.5,0) -> 0 | W16: =IF(H16="Gar nicht",0,0) -> 0 | X16: =IF(S16>0,"n.a.",SUM(S16:W16)) -> 0 | Y16: =X16 -> 0 | Z16: =IF(Y16<>"n.a.",SUM(Y16,Y17,Y19,Y22,Y25),NA()) -> 0 | AG16: =IF(X16>0.5,"Umgesetzt","Nicht umgesetzt") -> Nicht umgesetzt
B17: 2 | C17: Werden gelegentlich Begriffe in einer Terminologieliste dokumentiert? | F17: • Es werden gelegentlich Begriffe in einer Terminologieliste dokumentiert • Die Terminologieliste zugänglich für alle Mitarbeitenden der Redaktion | H17: Bitte auswählen | J17: • leichte Qualitätsverbesserung in einzelnen Projekten | S17: =IF(H17="Nicht anwendbar","n.a.",0) -> 0 | T17: =IF(H17="Vollständig",1,0) -> 0 | U17: =IF(H17="In den meisten Fällen",0.75,0) -> 0 | V17: =IF(H17="In ein Paar Fällen",0.5,0) -> 0 | W17: =IF(H17="Gar nicht",0,0) -> 0 | X17: =IFERROR(SUM(T17:W18)/COUNTIF(H17:H18,"<>Nicht anwendbar"),"n.a.") -> 0 | Y17: =IF(X16=1,X17,0) -> 0 | AG17: =IF(X17>0.5,"Umgesetzt","Nicht umgesetzt") -> Nicht umgesetzt
C18: Ist die Terminologieliste zugänglich für alle Mitarbeitenden der Redaktion? | H18: Bitte auswählen | S18: =IF(H18="Nicht anwendbar","n.a.",0) -> 0 | T18: =IF(H18="Vollständig",1,0) -> 0 | U18: =IF(H18="In den meisten Fällen",0.75,0) -> 0 | V18: =IF(H18="In ein Paar Fällen",0.5,0) -> 0 | W18: =IF(H18="Gar nicht",0,0) -> 0 | AG18: =IF(X18>0.5,"Umgesetzt","Nicht umgesetzt") -> Nicht umgesetzt
B19: 3 | C19: Gibt es eine zentrale, dokumentierte Terminologieliste oder Datenbank? | F19: • Es gibt eine zentrale, dokumentierte Terminologieliste oder Datenbank • Es existieren definierte Terminologierichtlinien • Prozesse für die Freigabe und Pflege von Terminologie sind definiert | H19: Bitte auswählen | J19: • höhere Verständlichkeit für Nutzende durch konsistente Begriffsnutzung • höhere Effizienz bei Übersetzungen durch weniger Varianten • weniger Abstimmungsaufwand zwischen Redkateur:innen • verbesserte Marken- und Unternehmenssprache | S19: =IF(H19="Nicht anwendbar","n.a.",0) -> 0 | T19: =IF(H19="Vollständig",1,0) -> 0 | U19: =IF(H19="In den meisten Fällen",0.75,0) -> 0 | V19: =IF(H19="In ein Paar Fällen",0.5,0) -> 0 | W19: =IF(H19="Gar nicht",0,0) -> 0 | X19: =IFERROR(SUM(T19:W21)/COUNTIF(H19:H21,"<>Nicht anwendbar"),"n.a.") -> 0 | Y19: =IF(Y17=1,X19,0) -> 0
C20: Existieren definierte Terminologierichtlinien? | H20: Bitte auswählen | S20: =IF(H20="Nicht anwendbar","n.a.",0) -> 0 | T20: =IF(H20="Vollständig",1,0) -> 0 | U20: =IF(H20="In den meisten Fällen",0.75,0) -> 0 | V20: =IF(H20="In ein Paar Fällen",0.5,0) -> 0 | W20: =IF(H20="Gar nicht",0,0) -> 0
C21: Sind Prozesse für die Freigabe und Pflege von Terminologie definiert? | H21: Bitte auswählen | S21: =IF(H21="Nicht anwendbar","n.a.",0) -> 0 | T21: =IF(H21="Vollständig",1,0) -> 0 | U21: =IF(H21="In den meisten Fällen",0.75,0) -> 0 | V21: =IF(H21="In ein Paar Fällen",0.5,0) -> 0 | W21: =IF(H21="Gar nicht",0,0) -> 0
B22: 4 | C22: Wird die Einhaltung der Terminologie durch Prüfungen oder Tools systematisch überwacht? | F22: • Die Einhaltung der Terminologie durch Prüfungen oder Tools wird systematisch überwacht • Es erfolgt eine Abstimmung zwischen Abteilungen, um terminologische Konsistenz sicherzustellen • Es wird ein Terminologiemapping zu Zulieferdokumentation durchgeführt | H22: Bitte auswählen | J22: • deutlich geringerer Pflegeaufwand • höhere Prozesssicherheit durch integrierte Prüfungen • konsistente Verwendung über Abteilungen hinweg • erhebliche Kostensenkung in Übersetzungsprojekten | S22: =IF(H22="Nicht anwendbar","n.a.",0) -> 0 | T22: =IF(H22="Vollständig",1,0) -> 0 | U22: =IF(H22="In den meisten Fällen",0.75,0) -> 0 | V22: =IF(H22="In ein Paar Fällen",0.5,0) -> 0 | W22: =IF(H22="Gar nicht",0,0) -> 0 | X22: =IFERROR(SUM(T22:W24)/COUNTIF(H22:H24,"<>Nicht anwendbar"),"n.a.") -> 0 | Y22: =IF(Y19=1,X22,0) -> 0
C23: Erfolgt eine Abstimmung zwischen Abteilungen (z. B. Entwicklung, Service, Marketing), um terminologische Konsistenz sicherzustellen? | H23: Bitte auswählen | S23: =IF(H23="Nicht anwendbar","n.a.",0) -> 0 | T23: =IF(H23="Vollständig",1,0) -> 0 | U23: =IF(H23="In den meisten Fällen",0.75,0) -> 0 | V23: =IF(H23="In ein Paar Fällen",0.5,0) -> 0 | W23: =IF(H23="Gar nicht",0,0) -> 0
C24: Wird ein Terminologiemapping zu Zulieferdokumentation durchgeführt? | H24: Bitte auswählen | S24: =IF(H24="Nicht anwendbar","n.a.",0) -> 0 | T24: =IF(H24="Vollständig",1,0) -> 0 | U24: =IF(H24="In den meisten Fällen",0.75,0) -> 0 | V24: =IF(H24="In ein Paar Fällen",0.5,0) -> 0 | W24: =IF(H24="Gar nicht",0,0) -> 0
B25: 5 | C25: Werden innovative Ansätze wie KI-gestützte Terminologieprüfung oder semantische Netze eingesetzt? | F25: • Es werden innovative Ansätze wie KI-gestützte Terminologieprüfung oder semantische Netze eingesetzt • Es erfolgt eine aktive Mitgestaltung oder Orientierung an branchenweiten Terminologiestandards • Es existiert ein mehrsprachiges, wertstrom- bzw. unternehmensübergreifendes Terminologiemanagement | H25: Bitte auswählen | J25: • Effizienz durch automatisierte Terminologieprüfung und -vorschläge • kontinuierliche Anpassung an neue Märkte, Produkte und Zielgruppen • strategischer Vorteil durch klar differenzierte, konsistente Unternehmenssprache • stärkere Nutzerorientierung durch vereinheitliche, verständliche Begriffe | S25: =IF(H25="Nicht anwendbar","n.a.",0) -> 0 | T25: =IF(H25="Vollständig",1,0) -> 0 | U25: =IF(H25="In den meisten Fällen",0.75,0) -> 0 | V25: =IF(H25="In ein Paar Fällen",0.5,0) -> 0 | W25: =IF(H25="Gar nicht",0,0) -> 0 | X25: =IFERROR(SUM(T25:W27)/COUNTIF(H25:H27,"<>Nicht anwendbar"),"n.a.") -> 0 | Y25: =IF(Y22=1,X25,0) -> 0
C26: Erfolgt eine aktive Mitgestaltung oder Orientierung an branchenweiten Terminologiestandards? | H26: Bitte auswählen | S26: =IF(H26="Nicht anwendbar","n.a.",0) -> 0 | T26: =IF(H26="Vollständig",1,0) -> 0 | U26: =IF(H26="In den meisten Fällen",0.75,0) -> 0 | V26: =IF(H26="In ein Paar Fällen",0.5,0) -> 0 | W26: =IF(H26="Gar nicht",0,0) -> 0
C27: Existiert ein mehrsprachiges, wertstrom- bzw. unternehmensübergreifendes Terminologiemanagement? | H27: Bitte auswählen | S27: =IF(H27="Nicht anwendbar","n.a.",0) -> 0 | T27: =IF(H27="Vollständig",1,0) -> 0 | U27: =IF(H27="In den meisten Fällen",0.75,0) -> 0 | V27: =IF(H27="In ein Paar Fällen",0.5,0) -> 0 | W27: =IF(H27="Gar nicht",0,0) -> 0

Sheet TD2.5
B4: Die Reifegrade werden anhand der jeweiligen Antwort ermittelt. Eine Erläuterung des Aufbaus der Reifegrade und der Antwortmöglichkeiten finden Sie in den Ausfüllhinweisen.
B6: TD2.5 | C6: Content Management - Übersetzungsmanagement | K6: Reifegrad: | L6: =ROUNDDOWN(Z16/0.25,0)*0.25 -> 0 | M6: =IF(L6<1,"Unvollständig",IF(L6<2,"Initial",IF(L6<3,"Gemanagt",IF(L6<4,"Definiert",IF(L6<5,"Quantitativ gemanagt",IF(L6<6,"Optimiert","Ausstehend")))))) -> Unvollständig
B7: Zweck | C7: Das Übersetzungsmanagement stellt sicher, dass technische Dokumentationen zielgruppengerecht, konsistent, rechtssicher und effizient in andere Sprachen übertragen werden. Ziel ist die qualitativ hochwertige und kosteneffiziente Übersetzung, die die internationale Vermarktung von Produkten unterstützt.
B8: Ergebnisse | C8: • Übersetzungen sind konsistent, terminologisch korrekt und erfüllen rechtliche sowie kulturelle Anforderungen. • Prozesse für die Beauftragung, Durchführung und Prüfung von Übersetzungen sind definiert. • Übersetzungsressourcen (z. B. Translation Memory) sind aufgebaut und werden genutzt. • Nachweise zur Qualität und Freigabe der Übersetzungen liegen vor.
B9: Basispraktiken | C9: • Definition von Prozessen für Übersetzungsaufträge, Qualitätsprüfungen und Freigaben. • Nutzung von Translation-Memory-Systemen (TMS). • Auswahl und Steuerung externer Übersetzungsdienstleister oder interner Ressourcen. • Qualitätskontrolle durch linguistische und fachliche Prüfungen. • Kontinuierliche Optimierung von Übersetzungsprozessen und -ressourcen.
B10: Arbeitsprodukte | C10: • Übersetzungsaufträge, Briefings und Anforderungsdokumente. • Translation Memory (TM) und Terminologiedatenbanken. • Styleguides oder Leitfäden für Übersetzungen. • Qualitätsnachweise (z. B. Prüfdokumente, Freigabeprotokolle).
B12: Erhebung der Reifegrade
B14: Zu Reifegrad | C14: Kontrollfrage | F14: Abnahmekriterien | H14: Umsetzung | J14: Nutzen bei Erreichen der Stufe | N14: Kommentar/Hinweis | T14: Listenindex | Y14: Zw. Ergebnis | Z14: Ergebnis
B16: 1 | C16: Wird bei Bedarf zumindest Ad-Hoc nach individuellen Maßstäben übersetzt? | F16: • Bei Bedarf wird Ad-Hoc nach individuellen Maßstäben übersetzt | H16: Bitte auswählen | J16: / | N16: Wenn Übersetzungen nicht relevant sind, bitte "nicht anwendbar" auswählen | S16: =IF(H16="Nicht anwendbar","n.a.",0) -> 0 | T16: =IF(H16="Vollständig",1,0) -> 0 | U16: =IF(H16="In den meisten Fällen",0.75,0) -> 0 | V16: =IF(H16="In ein Paar Fällen",0.5,0) -> 0 | W16: =IF(H16="Gar nicht",0,0) -> 0 | X16: =IF(S16>0,"n.a.",SUM(S16:W16)) -> 0 | Y16: =X16 -> 0 | Z16: =IF(Y16<>"n.a.",SUM(Y16,Y17,Y19,Y22,Y24),NA()) -> 0 | AG16: =IF(X16>0.5,"Umgesetzt","Nicht umgesetzt") -> Nicht umgesetzt
B17: 2 | C17: Werden Übersetzungsarbeiten an einen externen Dienstleister ausgelagert? | F17: • Übersetzungsarbeiten werden an einen externen Dienstleister ausgelagert • Gelegentlich werden informelle Hilfsmittel wie Glossare oder Übersetzungslisten verwendet | H17: Bitte auswählen | J17: • Reduzierung potenzieller Fehlerquellen • Entlastung interne Ressourcen durch Auslagerung | N17: Wenn keine externen Dienstleister beauftragt sind, bitte "nicht anwendbar" auswählen | S17: =IF(H17="Nicht anwendbar","n.a.",0) -> 0 | T17: =IF(H17="Vollständig",1,0) -> 0 | U17: =IF(H17="In den meisten Fällen",0.75,0) -> 0 | V17: =IF(H17="In ein Paar Fällen",0.5,0) -> 0 | W17: =IF(H17="Gar nicht",0,0) -> 0 | X17: =IFERROR(SUM(T17:W18)/COUNTIF(H17:H18,"<>Nicht anwendbar"),"n.a.") -> 0 | Y17: =IF(X16=1,X17,0) -> 0 | AG17: =IF(X17>0.5,"Umgesetzt","Nicht umgesetzt") -> Nicht umgesetzt
C18: Werden gelegentlich zumindest informelle Hilfsmittel wie Glossare oder Übersetzungslisten verwendet? | H18: Bitte auswählen | S18: =IF(H18="Nicht anwendbar","n.a.",0) -> 0 | T18: =IF(H18="Vollständig",1,0) -> 0 | U18: =IF(H18="In den meisten Fällen",0.75,0) -> 0 | V18: =IF(H18="In ein Paar Fällen",0.5,0) -> 0 | W18: =IF(H18="Gar nicht",0,0) -> 0 | AG18: =IF(X18>0.5,"Umgesetzt","Nicht umgesetzt") -> Nicht umgesetzt
B19: 3 | C19: Sind Prozesse für Übersetzungen dokumentiert und definiert (z. B. Briefing, Beauftragung, Freigabe)? | F19: • Prozesse für Übersetzungen sind dokumentiert und definiert • Die Übersetzung erfolgt konsistent nach festgelegten Styleguides und Qualitätsstandards • Übersetzungen werden durch Übersetzungsressourcen unterstützt | H19: Bitte auswählen | J19: • Höhere Qualität und Effizienz bei Übersetzungen durch Softwareunterstützung • Konsistente Übersetzung, unabhängig von Einzelpersonen • verbesserte Nachvollziehbarkeit und Auditierbarkeit | S19: =IF(H19="Nicht anwendbar","n.a.",0) -> 0 | T19: =IF(H19="Vollständig",1,0) -> 0 | U19: =IF(H19="In den meisten Fällen",0.75,0) -> 0 | V19: =IF(H19="In ein Paar Fällen",0.5,0) -> 0 | W19: =IF(H19="Gar nicht",0,0) -> 0 | X19: =IFERROR(SUM(T19:W21)/COUNTIF(H19:H21,"<>Nicht anwendbar"),"n.a.") -> 0 | Y19: =IF(Y17=1,X19,0) -> 0
C20: Erfolgt die Übersetzung konsistent nach festgelegten Styleguides und Qualitätsstandards? | H20: Bitte auswählen | S20: =IF(H20="Nicht anwendbar","n.a.",0) -> 0 | T20: =IF(H20="Vollständig",1,0) -> 0 | U20: =IF(H20="In den meisten Fällen",0.75,0) -> 0 | V20: =IF(H20="In ein Paar Fällen",0.5,0) -> 0 | W20: =IF(H20="Gar nicht",0,0) -> 0
A21: • | C21: Werden Übersetzungen durch Übersetzungsressourcen (z.B. Translation Memory) unterstützt? | H21: Bitte auswählen | S21: =IF(H21="Nicht anwendbar","n.a.",0) -> 0 | T21: =IF(H21="Vollständig",1,0) -> 0 | U21: =IF(H21="In den meisten Fällen",0.75,0) -> 0 | V21: =IF(H21="In ein Paar Fällen",0.5,0) -> 0 | W21: =IF(H21="Gar nicht",0,0) -> 0
B22: 4 | C22: Wird die Qualität der Übersetzungen regelmäßig evaluiert? | F22: • Die Qualität der Übersetzungen wird regelmäßig evaluiert • Es erfolgt eine Rückkopplung aus den Märkten oder Zielgruppen zur Verbesserung der Übersetzungen | H22: Bitte auswählen | J22: • kontinuierliche Verbesserung fremdsprachlicher technischer Dokumentation • deutliche Kostensenkung durch Wiederverwendung von Übersetzungen • schnellere Markteinführung durch kürzerre Übersetzungszyklen | S22: =IF(H22="Nicht anwendbar","n.a.",0) -> 0 | T22: =IF(H22="Vollständig",1,0) -> 0 | U22: =IF(H22="In den meisten Fällen",0.75,0) -> 0 | V22: =IF(H22="In ein Paar Fällen",0.5,0) -> 0 | W22: =IF(H22="Gar nicht",0,0) -> 0 | X22: =IFERROR(SUM(T22:W23)/COUNTIF(H22:H23,"<>Nicht anwendbar"),"n.a.") -> 0 | Y22: =IF(Y19=1,X22,0) -> 0
C23: Erfolgt eine Rückkopplung aus den Märkten oder Zielgruppen zur Verbesserung der Übersetzungen? | H23: Bitte auswählen | S23: =IF(H23="Nicht anwendbar","n.a.",0) -> 0 | T23: =IF(H23="Vollständig",1,0) -> 0 | U23: =IF(H23="In den meisten Fällen",0.75,0) -> 0 | V23: =IF(H23="In ein Paar Fällen",0.5,0) -> 0 | W23: =IF(H23="Gar nicht",0,0) -> 0
B24: 5 | C24: Kommen innovative Ansätze wie maschinelle Übersetzung mit Post-Editing oder KI-gestützte Terminologieprüfung zum Einsatz? | F24: • Innovative Ansätze wie maschinelle Übersetzung mit Post-Editing oder KI-gestützte Terminologieprüfung kommen zum Einsatz • Das Übersetzungsmanagement wird proaktiv an neue Märkte, Zielgruppen, Kulturen und regulatorische Anforderungen angepasst • Übersetzungsprozesse werden kontinuierlich anhand von Best Practices und neuen Technologien optimiert | H24: Bitte auswählen | J24: • Effizienz durch Echtzeit-Übersetzung • Kosteneinsparungen in der Übersetzung durch KI • strategische Vorteile bei der Erschließung neuer Märkte • Wettbewerbsvorteil durch kontextsensitive, nutzerfreundliche Mehrsprachigkeit | S24: =IF(H24="Nicht anwendbar","n.a.",0) -> 0 | T24: =IF(H24="Vollständig",1,0) -> 0 | U24: =IF(H24="In den meisten Fällen",0.75,0) -> 0 | V24: =IF(H24="In ein Paar Fällen",0.5,0) -> 0 | W24: =IF(H24="Gar nicht",0,0) -> 0 | X24: =IFERROR(SUM(T24:W26)/COUNTIF(H24:H26,"<>Nicht anwendbar"),"n.a.") -> 0 | Y24: =IF(Y22=1,X24,0) -> 0
C25: Wird das Übersetzungsmanagement proaktiv an neue Märkte, Zielgruppen, Kulturen und regulatorische Anforderungen angepasst? | H25: Bitte auswählen | S25: =IF(H25="Nicht anwendbar","n.a.",0) -> 0 | T25: =IF(H25="Vollständig",1,0) -> 0 | U25: =IF(H25="In den meisten Fällen",0.75,0) -> 0 | V25: =IF(H25="In ein Paar Fällen",0.5,0) -> 0 | W25: =IF(H25="Gar nicht",0,0) -> 0
C26: Werden Übersetzungsprozesse kontinuierlich anhand von Best Practices und neuen Technologien optimiert? | H26: Bitte auswählen | S26: =IF(H26="Nicht anwendbar","n.a.",0) -> 0 | T26: =IF(H26="Vollständig",1,0) -> 0 | U26: =IF(H26="In den meisten Fällen",0.75,0) -> 0 | V26: =IF(H26="In ein Paar Fällen",0.5,0) -> 0 | W26: =IF(H26="Gar nicht",0,0) -> 0

Sheet TD2.6
B4: Die Reifegrade werden anhand der jeweiligen Antwort ermittelt. Eine Erläuterung des Aufbaus der Reifegrade und der Antwortmöglichkeiten finden Sie in den Ausfüllhinweisen.
B6: TD2.6 | C6: Content Management - Aktualität | K6: Reifegrad: | L6: =ROUNDDOWN(Z16/0.25,0)*0.25 -> 0 | M6: =IF(L6<1,"Unvollständig",IF(L6<2,"Initial",IF(L6<3,"Gemanagt",IF(L6<4,"Definiert",IF(L6<5,"Quantitativ gemanagt",IF(L6<6,"Optimiert","Ausstehend")))))) -> Unvollständig
B7: Zweck | C7: Die technische Dokumentation soll stets dem aktuellen Stand des Produkts, der Prozesse und der gesetzlichen Anforderungen entsprechen. Ziel ist es, veraltete, fehlerhafte oder widersprüchliche Informationen zu vermeiden und die Zuverlässigkeit, Sicherheit und Rechtskonformität der Dokumentation zu gewährleisten.
B8: Ergebnisse | C8: • Dokumentationsinhalte entsprechen dem aktuellen Produkt- und Prozessstand. • Aktualisierungen werden zeitnah in die Dokumentation übernommen. • Die Nachverfolgbarkeit von Änderungen ist gewährleistet. • Nutzer erhalten nur gültige und freigegebene Dokumentationsversionen.
B9: Basispraktiken | C9: • Regelmäßige Überprüfung und Abgleich der Dokumentation mit Produktänderungen. • Integration der Dokumentationspflege in Änderungs- und Freigabeprozesse. • Nutzung von Tools zur Versionierung und Änderungsverfolgung. • Festlegung von Verantwortlichkeiten und Intervallen für Aktualisierungen. • Kontinuierliche Optimierung des Änderungs- und Aktualisierungsprozesses.
B10: Arbeitsprodukte | C10: • Änderungsprotokolle oder Versionshistorien. • Dokumentierte Aktualisierungsprozesse (z. B. Freigaben, Änderungsmanagement). • Aktualisierte Dokumentationen (gedruckt oder digital). • Nachweise über Gültigkeitszeiträume und Rückverfolgbarkeit.
B12: Erhebung der Reifegrade
B14: Zu Reifegrad | C14: Kontrollfrage | F14: Abnahmekriterien | H14: Umsetzung | J14: Nutzen bei Erreichen der Stufe | N14: Kommentar/Hinweis | T14: Listenindex | Y14: Zw. Ergebnis | Z14: Ergebnis
B16: 1 | C16: Erfolgen Aktualisierungen zumindest reaktiv und unsystematisch nach individuellem Ermessen, z. B. nach Kundenrückmeldungen oder Problemen? | F16: • Aktualisierungen erfolgen nur reaktiv und unsystematisch nach individuellem Ermessen, z. B. nach Kundenrückmeldungen oder Problemen | H16: Bitte auswählen | J16: / | S16: =IF(H16="Nicht anwendbar","n.a.",0) -> 0 | T16: =IF(H16="Vollständig",1,0) -> 0 | U16: =IF(H16="In den meisten Fällen",0.75,0) -> 0 | V16: =IF(H16="In ein Paar Fällen",0.5,0) -> 0 | W16: =IF(H16="Gar nicht",0,0) -> 0 | X16: =IF(S16>0,"n.a.",SUM(S16:W16)) -> 0 | Y16: =X16 -> 0 | Z16: =IF(Y16<>"n.a.",SUM(Y16,Y17,Y21,Y24,Y28),NA()) -> 0 | AG16: =IF(X16>0.5,"Umgesetzt","Nicht umgesetzt") -> Nicht umgesetzt
B17: 2 | C17: Gibt es erste Routinen oder informelle Absprachen zur Pflege der Dokumentation? | F17: • Es gibt erste Routinen oder informelle Absprachen zur Pflege der Dokumentation • Dokumente werden gelegentlich aktualisiert • Es sind Verantwortliche für die Dokumente identifiziert worden, die Aktualisierungen vornehmen • Es gibt einen ersten definierten Dokumenten-Lebenszyklus | H17: Bitte auswählen | J17: • weniger veraltete Informationen | S17: =IF(H17="Nicht anwendbar","n.a.",0) -> 0 | T17: =IF(H17="Vollständig",1,0) -> 0 | U17: =IF(H17="In den meisten Fällen",0.75,0) -> 0 | V17: =IF(H17="In ein Paar Fällen",0.5,0) -> 0 | W17: =IF(H17="Gar nicht",0,0) -> 0 | X17: =IFERROR(SUM(T17:W20)/COUNTIF(H17:H20,"<>Nicht anwendbar"),"n.a.") -> 0 | Y17: =IF(Y16=1,X17,0) -> 0 | AG17: =IF(X17>0.5,"Umgesetzt","Nicht umgesetzt") -> Nicht umgesetzt
C18: Werden Dokumente gelegentlich aktualisiert (z.B. anlassbezogen)? | H18: Bitte auswählen | S18: =IF(H18="Nicht anwendbar","n.a.",0) -> 0 | T18: =IF(H18="Vollständig",1,0) -> 0 | U18: =IF(H18="In den meisten Fällen",0.75,0) -> 0 | V18: =IF(H18="In ein Paar Fällen",0.5,0) -> 0 | W18: =IF(H18="Gar nicht",0,0) -> 0 | AG18: =IF(X18>0.5,"Umgesetzt","Nicht umgesetzt") -> Nicht umgesetzt
C19: Sind Verantwortliche für die Dokumente identifiziert worden, die Aktualisierungen vornehmen? | H19: Bitte auswählen | S19: =IF(H19="Nicht anwendbar","n.a.",0) -> 0 | T19: =IF(H19="Vollständig",1,0) -> 0 | U19: =IF(H19="In den meisten Fällen",0.75,0) -> 0 | V19: =IF(H19="In ein Paar Fällen",0.5,0) -> 0 | W19: =IF(H19="Gar nicht",0,0) -> 0 | AG19: =IF(X19>0.5,"Umgesetzt","Nicht umgesetzt") -> Nicht umgesetzt
C20: Gibt es einen ersten definierten Dokumenten-Lebenszyklus? | H20: Bitte auswählen | S20: =IF(H20="Nicht anwendbar","n.a.",0) -> 0 | T20: =IF(H20="Vollständig",1,0) -> 0 | U20: =IF(H20="In den meisten Fällen",0.75,0) -> 0 | V20: =IF(H20="In ein Paar Fällen",0.5,0) -> 0 | W20: =IF(H20="Gar nicht",0,0) -> 0 | AG20: =IF(X20>0.5,"Umgesetzt","Nicht umgesetzt") -> Nicht umgesetzt
B21: 3 | C21: Ist ein definierter Prozess zur Aktualisierung der Dokumentation vorhanden (z. B. Änderungsmanagement, definierte Freigabeschritte)? | F21: • Es ist ein definierter Prozess zur Aktualisierung der Dokumentation vorhanden • Änderungen am Produkt oder Prozess werden systematisch in die Dokumentation übernommen • Die Nachverfolgbarkeit von Änderungen ist sichergestellt | H21: Bitte auswählen | J21: • konsistente Qualität und Zuverlässigkeit der Inhalte • Kenntnis über die aktuelle Konfiguration erleichtert Service-Einsätze und abgestimmte Erstazteilangebote • erhöhte Rechtskonformität durch nachvollziehbare Aktualisierungszyklen | S21: =IF(H21="Nicht anwendbar","n.a.",0) -> 0 | T21: =IF(H21="Vollständig",1,0) -> 0 | U21: =IF(H21="In den meisten Fällen",0.75,0) -> 0 | V21: =IF(H21="In ein Paar Fällen",0.5,0) -> 0 | W21: =IF(H21="Gar nicht",0,0) -> 0 | X21: =IFERROR(SUM(T21:W23)/COUNTIF(H21:H23,"<>Nicht anwendbar"),"n.a.") -> 0 | Y21: =IF(Y17=1,X21,0) -> 0
C22: Werden Änderungen am Produkt oder Prozess systematisch in die Dokumentation übernommen (z.B. bei Wartungseinsätzen)? | H22: Bitte auswählen | S22: =IF(H22="Nicht anwendbar","n.a.",0) -> 0 | T22: =IF(H22="Vollständig",1,0) -> 0 | U22: =IF(H22="In den meisten Fällen",0.75,0) -> 0 | V22: =IF(H22="In ein Paar Fällen",0.5,0) -> 0 | W22: =IF(H22="Gar nicht",0,0) -> 0
C23: Ist die Nachverfolgbarkeit von Änderungen sichergestellt (z. B. durch Versionierung)? | H23: Bitte auswählen | S23: =IF(H23="Nicht anwendbar","n.a.",0) -> 0 | T23: =IF(H23="Vollständig",1,0) -> 0 | U23: =IF(H23="In den meisten Fällen",0.75,0) -> 0 | V23: =IF(H23="In ein Paar Fällen",0.5,0) -> 0 | W23: =IF(H23="Gar nicht",0,0) -> 0
B24: 4 | C24: Wird die Aktualität der Dokumentation regelmäßig überprüft und überwacht (z. B. Audits, Reviews, KPIs)? | F24: • Die Aktualität der Dokumentation wird regelmäßig überprüft und überwacht • Es gibt Verantwortlichkeiten und klare Fristen für die Pflege und Aktualisierung • Bei Änderungen am realen System werden Änderungsbedarfe in der Dokumentation gekennzeichnet • Die Konsistenz zwischen Dokumentationsversionen und Produktständen wird systematisch sichergestellt | H24: Bitte auswählen | J24: • schnellere Verfügbarkeit aktualisierter Inhalte • stärkere Integration mit anderen Abteilungen • Effizienzsteigerung durch Erinnerungen und Workflows | S24: =IF(H24="Nicht anwendbar","n.a.",0) -> 0 | T24: =IF(H24="Vollständig",1,0) -> 0 | U24: =IF(H24="In den meisten Fällen",0.75,0) -> 0 | V24: =IF(H24="In ein Paar Fällen",0.5,0) -> 0 | W24: =IF(H24="Gar nicht",0,0) -> 0 | X24: =IFERROR(SUM(T24:W27)/COUNTIF(H24:H27,"<>Nicht anwendbar"),"n.a.") -> 0 | Y24: =IF(Y21=1,X24,0) -> 0
C25: Gibt es Verantwortlichkeiten und klare Fristen für die Pflege und Aktualisierung? | H25: Bitte auswählen | S25: =IF(H25="Nicht anwendbar","n.a.",0) -> 0 | T25: =IF(H25="Vollständig",1,0) -> 0 | U25: =IF(H25="In den meisten Fällen",0.75,0) -> 0 | V25: =IF(H25="In ein Paar Fällen",0.5,0) -> 0 | W25: =IF(H25="Gar nicht",0,0) -> 0
C26: Werden bei Änderungen am realen System Änderungsbedarfe in der Dokumentation gekennzeichnet? | H26: Bitte auswählen | S26: =IF(H26="Nicht anwendbar","n.a.",0) -> 0 | T26: =IF(H26="Vollständig",1,0) -> 0 | U26: =IF(H26="In den meisten Fällen",0.75,0) -> 0 | V26: =IF(H26="In ein Paar Fällen",0.5,0) -> 0 | W26: =IF(H26="Gar nicht",0,0) -> 0
C27: Wird die Konsistenz zwischen Dokumentationsversionen und Produktständen systematisch sichergestellt? | H27: Bitte auswählen | S27: =IF(H27="Nicht anwendbar","n.a.",0) -> 0 | T27: =IF(H27="Vollständig",1,0) -> 0 | U27: =IF(H27="In den meisten Fällen",0.75,0) -> 0 | V27: =IF(H27="In ein Paar Fällen",0.5,0) -> 0 | W27: =IF(H27="Gar nicht",0,0) -> 0
B28: 5 | C28: Werden die relevanten Dokumentationsinhalte auf Grundlage der durchgeführten Änderungen am realen System über den gesamten Lebenszyklus automatisch aktualisiert? | F28: • Die relevanten Dokumentationsinhalte werden auf Grundlage der durchgeführten Änderungen am realen System über den gesamten Lebenszyklus automatisch aktualisiert • Dabei werden innovative Ansätze (v.a. digitale Zwillinge) genutzt • Der Aktualisierungsprozess wird kontinuierlich verbessert und an neue Anforderungen angepasst | H28: Bitte auswählen | J28: • Verlässlichkeit durch jederzeit aktuelle Dokumentation • Wettbewerbsvorteil durch zeitnahe Reaktion auf Produkt- und Marktänderungen • strategische Unterstützung für digitale Services und Nutzerfreundlichkeit | S28: =IF(H28="Nicht anwendbar","n.a.",0) -> 0 | T28: =IF(H28="Vollständig",1,0) -> 0 | U28: =IF(H28="In den meisten Fällen",0.75,0) -> 0 | V28: =IF(H28="In ein Paar Fällen",0.5,0) -> 0 | W28: =IF(H28="Gar nicht",0,0) -> 0 | X28: =IFERROR(SUM(T28:W30)/COUNTIF(H28:H30,"<>Nicht anwendbar"),"n.a.") -> 0 | Y28: =IF(Y24=1,X28,0) -> 0
C29: Werden dabei innovative Ansätze (v.a. digitale Zwillinge) genutzt? | H29: Bitte auswählen | S29: =IF(H29="Nicht anwendbar","n.a.",0) -> 0 | T29: =IF(H29="Vollständig",1,0) -> 0 | U29: =IF(H29="In den meisten Fällen",0.75,0) -> 0 | V29: =IF(H29="In ein Paar Fällen",0.5,0) -> 0 | W29: =IF(H29="Gar nicht",0,0) -> 0
C30: Wird der Aktualisierungsprozess kontinuierlich verbessert und an neue Anforderungen angepasst? | H30: Bitte auswählen | S30: =IF(H30="Nicht anwendbar","n.a.",0) -> 0 | T30: =IF(H30="Vollständig",1,0) -> 0 | U30: =IF(H30="In den meisten Fällen",0.75,0) -> 0 | V30: =IF(H30="In ein Paar Fällen",0.5,0) -> 0 | W30: =IF(H30="Gar nicht",0,0) -> 0

Sheet TD2.7
B4: Die Reifegrade werden anhand der jeweiligen Antwort ermittelt. Eine Erläuterung des Aufbaus der Reifegrade und der Antwortmöglichkeiten finden Sie in den Ausfüllhinweisen.
B6: TD2.7 | C6: Content Management - Versionierung | K6: Reifegrad: | L6: =ROUNDDOWN(Z16/0.25,0)*0.25 -> 0 | M6: =IF(L6<1,"Unvollständig",IF(L6<2,"Initial",IF(L6<3,"Gemanagt",IF(L6<4,"Definiert",IF(L6<5,"Quantitativ gemanagt",IF(L6<6,"Optimiert","Ausstehend")))))) -> Unvollständig
B7: Zweck | C7: Die Versionierung stellt sicher, dass Dokumentationsinhalte eindeutig identifizierbar, nachvollziehbar und in konsistenter Reihenfolge gepflegt werden. Ziel ist es, jederzeit zu wissen, welche Version eines Inhalts gültig ist, welche Änderungen durchgeführt wurden und wie diese in Bezug auf das Produkt oder System einzuordnen sind.
B8: Ergebnisse | C8: • Jede Dokumentation ist eindeutig einer Version zugeordnet. • Änderungen und Freigaben sind nachvollziehbar dokumentiert. • Veraltete Versionen sind von gültigen Versionen unterscheidbar. • Es besteht Transparenz über die Entwicklungsgeschichte der Inhalte.
B9: Basispraktiken | C9: • Kennzeichnung von Dokumentationsständen durch Versionsnummern oder Datumsangaben. • Dokumentation von Änderungen und Freigaben. • Nutzung von Tools oder Systemfunktionen zur Versionsverwaltung. • Festlegung von Verantwortlichkeiten für die Versionierung. • Regelmäßige Überprüfung und Weiterentwicklung der Versionierungsrichtlinien.
B10: Arbeitsprodukte | C10: • Versionierte Dokumente oder Module mit eindeutiger Kennzeichnung. • Versionshistorien und Änderungsprotokolle. • Freigabedokumente oder Release-Notes zur Dokumentation von Änderungen. • Gültigkeitskennzeichnungen in Publikationen (z. B. Versionsnummern, Datum).
B12: Erhebung der Reifegrade
B14: Zu Reifegrad | C14: Kontrollfrage | F14: Abnahmekriterien | H14: Umsetzung | J14: Nutzen bei Erreichen der Stufe | N14: Kommentar/Hinweis | T14: Listenindex | Y14: Zw. Ergebnis | Z14: Ergebnis
B16: 1 | C16: Haben die Mitarbeiter, die mit der Technischen Dokumentation vertraut sind, zumindest einen individuellen Überblick über die aktuelle Version der Dokumentation, mit der sie arbeiten? | F16: • Die Mitarbeiter, die mit der Technischen Dokumentation vertraut sind, haben einen individuellen Überblick über die aktuelle Version der Dokumentation, mit der sie arbeiten | H16: Bitte auswählen | J16: / | S16: =IF(H16="Nicht anwendbar","n.a.",0) -> 0 | T16: =IF(H16="Vollständig",1,0) -> 0 | U16: =IF(H16="In den meisten Fällen",0.75,0) -> 0 | V16: =IF(H16="In ein Paar Fällen",0.5,0) -> 0 | W16: =IF(H16="Gar nicht",0,0) -> 0 | X16: =IF(S16>0,"n.a.",SUM(S16:W16)) -> 0 | Y16: =X16 -> 0 | Z16: =IF(Y16<>"n.a.",SUM(Y16,Y17,Y19,Y23,Y27),NA()) -> 0 | AG16: =IF(X16>0.5,"Umgesetzt","Nicht umgesetzt") -> Nicht umgesetzt
B17: 2 | C17: Ist die Unterscheidung der Versionen der Dokumentation auch für andere Mitarbeiter interpretierbar (z.B. über die Dateibenennung)? | F17: • Die Unterscheidung der Versionen der Dokumentation ist auch für andere Mitarbeiter interpretierbar • Gelegentlich werden Absprachen über die Kennzeichnung der Version getroffen | H17: Bitte auswählen | J17: • reduzierte Gefahr von Verlust oder Überschneidungen • reduzierte Gefahr der Arbeit mit veralteten Versionen | S17: =IF(H17="Nicht anwendbar","n.a.",0) -> 0 | T17: =IF(H17="Vollständig",1,IF(H17="Nicht anwendbar",1,0)) -> 0 | U17: =IF(H17="In den meisten Fällen",0.75,0) -> 0 | V17: =IF(H17="In ein Paar Fällen",0.5,0) -> 0 | W17: =IF(H17="Gar nicht",0,0) -> 0 | X17: =IFERROR(SUM(T17:W18)/COUNTIF(H17:H18,"<>Nicht anwendbar"),"n.a.") -> 0 | Y17: =IF(X16=1,X17,0) -> 0 | AG17: =IF(X17>0.5,"Umgesetzt","Nicht umgesetzt") -> Nicht umgesetzt
C18: Werden gelegentlich Absprachen über die Kennzeichnung der Version getroffen? | H18: Bitte auswählen | S18: =IF(H18="Nicht anwendbar","n.a.",0) -> 0 | T18: =IF(H18="Vollständig",1,IF(H18="Nicht anwendbar",1,0)) -> 0 | U18: =IF(H18="In den meisten Fällen",0.75,0) -> 0 | V18: =IF(H18="In ein Paar Fällen",0.5,0) -> 0 | W18: =IF(H18="Gar nicht",0,0) -> 0 | AG18: =IF(X18>0.5,"Umgesetzt","Nicht umgesetzt") -> Nicht umgesetzt
B19: 3 | C19: Ist ein definierter Prozess zur Versionierung von Dokumentationen vorhanden (z. B. eindeutige Versionsnummerierung, definierte Freigabeschritte)? | F19: • Es ist ein definierter Prozess zur Versionierung von Dokumentationen vorhanden • Versionsstände werden konsistent geführt und Änderungen systematisch dokumentiert • Es wird regelmäßig systemseitige Unterstützung bei der Versionierung in Anspruch genommen • Es gibt Vorgaben oder Richtlinien zur Versionierung, die verbindlich angewendet werden | H19: Bitte auswählen | J19: • geringeres Risiko von Fehlern und Doppelarbeit • Rechtssicherheit durch lückenlose Änderungsdokumentation | S19: =IF(H19="Nicht anwendbar","n.a.",0) -> 0 | T19: =IF(H19="Vollständig",1,IF(H19="Nicht anwendbar",1,0)) -> 0 | U19: =IF(H19="In den meisten Fällen",0.75,0) -> 0 | V19: =IF(H19="In ein Paar Fällen",0.5,0) -> 0 | W19: =IF(H19="Gar nicht",0,0) -> 0 | X19: =IFERROR(SUM(T19:W22)/COUNTIF(H19:H22,"<>Nicht anwendbar"),"n.a.") -> 0 | Y19: =IF(Y17=1,X19,0) -> 0
C20: Werden Versionsstände konsistent geführt und Änderungen systematisch dokumentiert? | H20: Bitte auswählen | S20: =IF(H20="Nicht anwendbar","n.a.",0) -> 0 | T20: =IF(H20="Vollständig",1,IF(H20="Nicht anwendbar",1,0)) -> 0 | U20: =IF(H20="In den meisten Fällen",0.75,0) -> 0 | V20: =IF(H20="In ein Paar Fällen",0.5,0) -> 0 | W20: =IF(H20="Gar nicht",0,0) -> 0
C21: Wird regelmäßig systemseitige Unterstützung bei der Versionierung in Anspruch genommen? | H21: Bitte auswählen | S21: =IF(H21="Nicht anwendbar","n.a.",0) -> 0 | T21: =IF(H21="Vollständig",1,IF(H21="Nicht anwendbar",1,0)) -> 0 | U21: =IF(H21="In den meisten Fällen",0.75,0) -> 0 | V21: =IF(H21="In ein Paar Fällen",0.5,0) -> 0 | W21: =IF(H21="Gar nicht",0,0) -> 0
C22: Gibt es Vorgaben oder Richtlinien zur Versionierung, die verbindlich angewendet werden? | H22: Bitte auswählen | S22: =IF(H22="Nicht anwendbar","n.a.",0) -> 0 | T22: =IF(H22="Vollständig",1,IF(H22="Nicht anwendbar",1,0)) -> 0 | U22: =IF(H22="In den meisten Fällen",0.75,0) -> 0 | V22: =IF(H22="In ein Paar Fällen",0.5,0) -> 0 | W22: =IF(H22="Gar nicht",0,0) -> 0
B23: 4 | C23: Wird die Einhaltung der Versionierungsregeln regelmäßig überprüft? | F23: • Die Einhaltung der Versionierungsregeln regelmäßig überprüft • Tools oder Systeme unterstützen aktiv die Versionierung • Es besteht Transparenz darüber, welche Version zu welchem Zeitpunkt gültig ist und wer sie freigegeben hat • Es ist eine durchgängige Rückverfolgbarkeit von Versionen gewährleistet | H23: Bitte auswählen | J23: • erhebliche Effizienzsteigerung durch automatische Protokollierung • paralleles Arbeiten mehrerer Personen ohne Konflikte | S23: =IF(H23="Nicht anwendbar","n.a.",0) -> 0 | T23: =IF(H23="Vollständig",1,IF(H23="Nicht anwendbar",1,0)) -> 0 | U23: =IF(H23="In den meisten Fällen",0.75,0) -> 0 | V23: =IF(H23="In ein Paar Fällen",0.5,0) -> 0 | W23: =IF(H23="Gar nicht",0,0) -> 0 | X23: =IFERROR(SUM(T23:W26)/COUNTIF(H23:H26,"<>Nicht anwendbar"),"n.a.") -> 0 | Y23: =IF(Y19=1,X23,0) -> 0
C24: Unterstützen Tools oder Systeme aktiv die Versionierung (z. B. automatisierte Versionsverwaltung, Check-in/Check-out)? | H24: Bitte auswählen | S24: =IF(H24="Nicht anwendbar","n.a.",0) -> 0 | T24: =IF(H24="Vollständig",1,IF(H24="Nicht anwendbar",1,0)) -> 0 | U24: =IF(H24="In den meisten Fällen",0.75,0) -> 0 | V24: =IF(H24="In ein Paar Fällen",0.5,0) -> 0 | W24: =IF(H24="Gar nicht",0,0) -> 0
C25: Besteht Transparenz darüber, welche Version zu welchem Zeitpunkt gültig ist und wer sie freigegeben hat? | H25: Bitte auswählen | S25: =IF(H25="Nicht anwendbar","n.a.",0) -> 0 | T25: =IF(H25="Vollständig",1,IF(H25="Nicht anwendbar",1,0)) -> 0 | U25: =IF(H25="In den meisten Fällen",0.75,0) -> 0 | V25: =IF(H25="In ein Paar Fällen",0.5,0) -> 0 | W25: =IF(H25="Gar nicht",0,0) -> 0
C26: Ist eine durchgängige Rückverfolgbarkeit von Versionen gewährleistet? | H26: Bitte auswählen | S26: =IF(H26="Nicht anwendbar","n.a.",0) -> 0 | T26: =IF(H26="Vollständig",1,IF(H26="Nicht anwendbar",1,0)) -> 0 | U26: =IF(H26="In den meisten Fällen",0.75,0) -> 0 | V26: =IF(H26="In ein Paar Fällen",0.5,0) -> 0 | W26: =IF(H26="Gar nicht",0,0) -> 0
B27: 5 | C27: Wird die Versionierung und die Nachverfolgbarkeit von Änderungen kontinuierlich verbessert? | F27: • Die Versionierung und die Nachverfolgbarkeit von Änderungen wird kontinuierlich verbessert • Es erfolgt eine proaktive Sicherstellung der Konsistenz und Nachvollziehbarkeit aller Versionen über Systeme hinweg • Innovative Ansätze wie automatisierte Änderungsverfolgung oder Integration mit Produktlebenszyklus-Systemen werden genutzt | H27: Bitte auswählen | J27: • vollständige Rückverfolgbarkeit über den gesamten Produktlebenszyklus • strategischer Vorteil durch hohe Prozesssicherheit und Compliance • maximale Transparenz und Effizienz in komplexen Projekten | S27: =IF(H27="Nicht anwendbar","n.a.",0) -> 0 | T27: =IF(H27="Vollständig",1,IF(H27="Nicht anwendbar",1,0)) -> 0 | U27: =IF(H27="In den meisten Fällen",0.75,0) -> 0 | V27: =IF(H27="In ein Paar Fällen",0.5,0) -> 0 | W27: =IF(H27="Gar nicht",0,0) -> 0 | X27: =IFERROR(SUM(T27:W29)/COUNTIF(H27:H29,"<>Nicht anwendbar"),"n.a.") -> 0 | Y27: =IF(Y23=1,X27,0) -> 0
C28: Erfolgt eine proaktive Sicherstellung der Konsistenz und Nachvollziehbarkeit aller Versionen über Systeme hinweg? | H28: Bitte auswählen | S28: =IF(H28="Nicht anwendbar","n.a.",0) -> 0 | T28: =IF(H28="Vollständig",1,IF(H28="Nicht anwendbar",1,0)) -> 0 | U28: =IF(H28="In den meisten Fällen",0.75,0) -> 0 | V28: =IF(H28="In ein Paar Fällen",0.5,0) -> 0 | W28: =IF(H28="Gar nicht",0,0) -> 0
C29: Werden innovative Ansätze wie automatisierte Änderungsverfolgung oder Integration mit Produktlebenszyklus-Systemen genutzt? | H29: Bitte auswählen | S29: =IF(H29="Nicht anwendbar","n.a.",0) -> 0 | T29: =IF(H29="Vollständig",1,IF(H29="Nicht anwendbar",1,0)) -> 0 | U29: =IF(H29="In den meisten Fällen",0.75,0) -> 0 | V29: =IF(H29="In ein Paar Fällen",0.5,0) -> 0 | W29: =IF(H29="Gar nicht",0,0) -> 0

Sheet TD2.8
B4: Die Reifegrade werden anhand der jeweiligen Antwort ermittelt. Eine Erläuterung des Aufbaus der Reifegrade und der Antwortmöglichkeiten finden Sie in den Ausfüllhinweisen.
B6: TD2.8 | C6: Content Management - Ablage und Archivierung | K6: Reifegrad: | L6: =ROUNDDOWN(Z16/0.25,0)*0.25 -> 0 | M6: =IF(L6<1,"Unvollständig",IF(L6<2,"Initial",IF(L6<3,"Gemanagt",IF(L6<4,"Definiert",IF(L6<5,"Quantitativ gemanagt",IF(L6<6,"Optimiert","Ausstehend")))))) -> Unvollständig
B7: Zweck | C7: Die Ablage und Archivierung stellt sicher, dass Dokumentationsinhalte strukturiert, zugänglich und revisionssicher gespeichert werden. Ziel ist die Nachvollziehbarkeit, Rechtskonformität und effiziente Wiederverwendbarkeit von Dokumentationsständen während und nach dem Produktlebenszyklus.
B8: Ergebnisse | C8: • Dokumentationsstände sind eindeutig abgelegt und auffindbar. • Archivierte Versionen sind klar von aktuellen Versionen unterscheidbar. • Aufbewahrungsfristen und rechtliche Anforderungen werden eingehalten. • Zugriff und Nutzung archivierter Inhalte sind nachvollziehbar geregelt.
B9: Basispraktiken | C9: • Systematische Ablage von Dokumentationsständen mit eindeutigen Bezeichnungen. • Nutzung von Archivsystemen oder CMS-Funktionalitäten. • Definition und Umsetzung von Regeln zur Aufbewahrung, Löschung und Sicherung. • Regelmäßige Überprüfung der Zugänglichkeit und Integrität der archivierten Daten. • Kontinuierliche Anpassung an neue rechtliche oder organisatorische Anforderungen.
B10: Arbeitsprodukte | C10: • Strukturierte Ablage (z. B. Ordnerstruktur, Datenbank, CMS). • Archivsystem mit dokumentierten Regeln für Aufbewahrung und Löschung. • Nachweise über Aufbewahrungsfristen und Löschungen. • Zugriffsprotokolle und Dokumentationen der Archivierungsprozesse.
B12: Erhebung der Reifegrade
B14: Zu Reifegrad | C14: Kontrollfrage | F14: Abnahmekriterien | H14: Umsetzung | J14: Nutzen bei Erreichen der Stufe | N14: Kommentar/Hinweis | T14: Listenindex | Y14: Zw. Ergebnis | Z14: Ergebnis
B16: 1 | C16: Werden Dokumente zu Archivierungszwecken zumindest lokal abgelegt? | F16: • Erfahrene Mitarbeiter legen Dokumente zu Archivierungszwecken lokal ab | H16: Bitte auswählen | J16: / | S16: =IF(H16="Nicht anwendbar","n.a.",0) -> 0 | T16: =IF(H16="Vollständig",1,IF(H16="Nicht anwendbar",1,0)) -> 0 | U16: =IF(H16="In den meisten Fällen",0.75,0) -> 0 | V16: =IF(H16="In ein Paar Fällen",0.5,0) -> 0 | W16: =IF(H16="Gar nicht",0,0) -> 0 | X16: =IF(S16>0,"n.a.",SUM(S16:W16)) -> 0 | Y16: =X16 -> 0 | Z16: =IF(Y16<>"n.a.",SUM(Y16,Y17,Y19,Y22,Y25),NA()) -> 0 | AG16: =IF(X16>0.5,"Umgesetzt","Nicht umgesetzt") -> Nicht umgesetzt
B17: 2 | C17: Ist eine zentrale Ablage vorhanden und wird diese gelegentlich von den Mitarbeitenden verwendet? | F17: • Es ist eine zentrale Ablage vorhanden und wird diese gelegentlich von den Mitarbeitenden verwendet • Es werden erste Regeln zur Ablage und Archivierung dokumentiert | H17: Bitte auswählen | J17: • reduzierte Suchzeiten durch feste Ablageorte • geringeres Risiko von Datenverlusten | S17: =IF(H17="Nicht anwendbar","n.a.",0) -> 0 | T17: =IF(H17="Vollständig",1,IF(H17="Nicht anwendbar",1,0)) -> 0 | U17: =IF(H17="In den meisten Fällen",0.75,0) -> 0 | V17: =IF(H17="In ein Paar Fällen",0.5,0) -> 0 | W17: =IF(H17="Gar nicht",0,0) -> 0 | X17: =IFERROR(SUM(T17:W18)/COUNTIF(H17:H18,"<>Nicht anwendbar"),"n.a.") -> 0 | Y17: =IF(X16=1,X17,0) -> 0 | AG17: =IF(X17>0.5,"Umgesetzt","Nicht umgesetzt") -> Nicht umgesetzt
C18: Werden erste Regeln zur Ablage und Archivierung dokumentiert? | H18: Bitte auswählen | S18: =IF(H18="Nicht anwendbar","n.a.",0) -> 0 | T18: =IF(H18="Vollständig",1,IF(H18="Nicht anwendbar",1,0)) -> 0 | U18: =IF(H18="In den meisten Fällen",0.75,0) -> 0 | V18: =IF(H18="In ein Paar Fällen",0.5,0) -> 0 | W18: =IF(H18="Gar nicht",0,0) -> 0 | AG18: =IF(X18>0.5,"Umgesetzt","Nicht umgesetzt") -> Nicht umgesetzt
B19: 3 | C19: Ist ein definierter Prozess für Ablage und Archivierung von Dokumentationen vorhanden? | F19: • Ein definierter Prozess für Ablage und Archivierung von Dokumentationen ist vorhanden • Inhalte werden konsistent in einer zentralen Struktur oder einem System gespeichert • Es bestehen verbindliche Vorgaben für Aufbewahrungsfristen und Zugriffsrechte | H19: Bitte auswählen | J19: • vereinfachte Zusammenarbeit zwischen Abteilungen • höhere Compliance durch nachvollziehbare Archivierung | S19: =IF(H19="Nicht anwendbar","n.a.",0) -> 0 | T19: =IF(H19="Vollständig",1,IF(H19="Nicht anwendbar",1,0)) -> 0 | U19: =IF(H19="In den meisten Fällen",0.75,0) -> 0 | V19: =IF(H19="In ein Paar Fällen",0.5,0) -> 0 | W19: =IF(H19="Gar nicht",0,0) -> 0 | X19: =IFERROR(SUM(T19:W21)/COUNTIF(H19:H21,"<>Nicht anwendbar"),"n.a.") -> 0 | Y19: =IF(Y17=1,X19,0) -> 0
C20: Werden Inhalte konsistent in einer zentralen Struktur oder einem System gespeichert? | H20: Bitte auswählen | S20: =IF(H20="Nicht anwendbar","n.a.",0) -> 0 | T20: =IF(H20="Vollständig",1,IF(H20="Nicht anwendbar",1,0)) -> 0 | U20: =IF(H20="In den meisten Fällen",0.75,0) -> 0 | V20: =IF(H20="In ein Paar Fällen",0.5,0) -> 0 | W20: =IF(H20="Gar nicht",0,0) -> 0
C21: Bestehen verbindliche Vorgaben für Aufbewahrungsfristen und Zugriffsrechte? | H21: Bitte auswählen | S21: =IF(H21="Nicht anwendbar","n.a.",0) -> 0 | T21: =IF(H21="Vollständig",1,IF(H21="Nicht anwendbar",1,0)) -> 0 | U21: =IF(H21="In den meisten Fällen",0.75,0) -> 0 | V21: =IF(H21="In ein Paar Fällen",0.5,0) -> 0 | W21: =IF(H21="Gar nicht",0,0) -> 0
B22: 4 | C22: Wird die Einhaltung der Ablage- und Archivierungsregeln regelmäßig überprüft (z. B. durch Audits oder interne Kontrollen)? | F22: • Die Einhaltung der Ablage- und Archivierungsregeln wird regelmäßig überprüft • Systeme unterstützen die Verwaltung von Zugriffsrechten, Versionen und Fristen • Archivierte Inhalte jederzeit nachvollziehbar und revisionssicher verfügbar | H22: Bitte auswählen | J22: • deutlich geringerer Suchaufwand • sichere Langzeitarchivierung • Zugriffskontrolle und Berechtigungsmanagement erhöhen die Sicherheit | S22: =IF(H22="Nicht anwendbar","n.a.",0) -> 0 | T22: =IF(H22="Vollständig",1,IF(H22="Nicht anwendbar",1,0)) -> 0 | U22: =IF(H22="In den meisten Fällen",0.75,0) -> 0 | V22: =IF(H22="In ein Paar Fällen",0.5,0) -> 0 | W22: =IF(H22="Gar nicht",0,0) -> 0 | X22: =IFERROR(SUM(T22:W24)/COUNTIF(H22:H24,"<>Nicht anwendbar"),"n.a.") -> 0 | Y22: =IF(Y19=1,X22,0) -> 0
C23: Unterstützen Systeme die Verwaltung von Zugriffsrechten, Versionen und Fristen? | H23: Bitte auswählen | S23: =IF(H23="Nicht anwendbar","n.a.",0) -> 0 | T23: =IF(H23="Vollständig",1,IF(H23="Nicht anwendbar",1,0)) -> 0 | U23: =IF(H23="In den meisten Fällen",0.75,0) -> 0 | V23: =IF(H23="In ein Paar Fällen",0.5,0) -> 0 | W23: =IF(H23="Gar nicht",0,0) -> 0
C24: Sind archivierte Inhalte jederzeit nachvollziehbar und revisionssicher verfügbar? | H24: Bitte auswählen | S24: =IF(H24="Nicht anwendbar","n.a.",0) -> 0 | T24: =IF(H24="Vollständig",1,IF(H24="Nicht anwendbar",1,0)) -> 0 | U24: =IF(H24="In den meisten Fällen",0.75,0) -> 0 | V24: =IF(H24="In ein Paar Fällen",0.5,0) -> 0 | W24: =IF(H24="Gar nicht",0,0) -> 0
B25: 5 | C25: Werden rechtliche und organisatorische Anforderungen proaktiv in die Archivierung integriert und regelmäßig aktualisiert? | F25: • Rechtliche und organisatorische Anforderungen werden proaktiv in die Archivierung integriert und regelmäßig aktualisiert • Es erfolgt eine automatisierte Archivierung auf Basis von Metadaten, Ereignissen oder Fristen • Es erfolgt eine unternehmensweite Harmonisierung mit anderen Systemen zur ganzheitlichen Archivverwaltung | H25: Bitte auswählen | J25: • strategische Nutzung archivierter Daten für Analysen und Wissensmanagement • Rechtskonformität durch Compliance-gerechte Archivierung | S25: =IF(H25="Nicht anwendbar","n.a.",0) -> 0 | T25: =IF(H25="Vollständig",1,IF(H25="Nicht anwendbar",1,0)) -> 0 | U25: =IF(H25="In den meisten Fällen",0.75,0) -> 0 | V25: =IF(H25="In ein Paar Fällen",0.5,0) -> 0 | W25: =IF(H25="Gar nicht",0,0) -> 0 | X25: =IFERROR(SUM(T25:W27)/COUNTIF(H25:H27,"<>Nicht anwendbar"),"n.a.") -> 0 | Y25: =IF(Y22=1,X25,0) -> 0
C26: Erfolgt eine automatisierte Archivierung auf Basis von Metadaten, Ereignissen oder Fristen? | H26: Bitte auswählen | S26: =IF(H26="Nicht anwendbar","n.a.",0) -> 0 | T26: =IF(H26="Vollständig",1,IF(H26="Nicht anwendbar",1,0)) -> 0 | U26: =IF(H26="In den meisten Fällen",0.75,0) -> 0 | V26: =IF(H26="In ein Paar Fällen",0.5,0) -> 0 | W26: =IF(H26="Gar nicht",0,0) -> 0
C27: Erfolgt eine unternehmensweite Harmonisierung mit anderen Systemen (z. B. PLM, ERP, DMS) zur ganzheitlichen Archivverwaltung? | H27: Bitte auswählen | S27: =IF(H27="Nicht anwendbar","n.a.",0) -> 0 | T27: =IF(H27="Vollständig",1,IF(H27="Nicht anwendbar",1,0)) -> 0 | U27: =IF(H27="In den meisten Fällen",0.75,0) -> 0 | V27: =IF(H27="In ein Paar Fällen",0.5,0) -> 0 | W27: =IF(H27="Gar nicht",0,0) -> 0

Sheet TD3.1
B4: Die Reifegrade werden anhand der jeweiligen Antwort ermittelt. Eine Erläuterung des Aufbaus der Reifegrade und der Antwortmöglichkeiten finden Sie in den Ausfüllhinweisen.
B6: TD3.1 | C6: Content Delivery - Publikation und Verwaltung | K6: Reifegrad: | L6: =ROUNDDOWN(Z16/0.25,0)*0.25 -> 0 | M6: =IF(L6<1,"Unvollständig",IF(L6<2,"Initial",IF(L6<3,"Gemanagt",IF(L6<4,"Definiert",IF(L6<5,"Quantitativ gemanagt",IF(L6<6,"Optimiert","Ausstehend")))))) -> Unvollständig
B7: Zweck | C7: Dokumentationsinhalte werden gezielt, konsistent und effizient veröffentlicht, verteilt und verwaltet. Ziel ist es, dass die richtigen Informationen zur richtigen Zeit, in geeigneter Form und für die passende Zielgruppe bereitgestellt werden.
B8: Ergebnisse | C8: • Dokumentationsinhalte werden in den definierten Formaten und Kanälen veröffentlicht. • Veröffentlichungen sind nachvollziehbar geplant, freigegeben und dokumentiert. • Nutzerinnen haben Zugriff auf die aktuellen und freigegebenen Inhalte. • Verwaltungsprozesse sichern Konsistenz, Wiederverwendbarkeit und Transparenz der Publikationen.
B9: Basispraktiken | C9: • Erstellung und Verwaltung von Publikationsworkflows. • Systematische Freigabe vor der Veröffentlichung. • Nutzung geeigneter Systeme oder Plattformen für Verwaltung und Bereitstellung. • Sicherstellung der Konsistenz über verschiedene Ausgabekanäle hinweg. • Regelmäßige Optimierung von Publikations- und Verwaltungsprozessen.
B10: Arbeitsprodukte | C10: • Veröffentlichte Dokumentationen (z. B. Print, PDF, Online-Hilfe, Portale, Apps). • Freigabe- und Veröffentlichungsprotokolle. • Publikationspläne oder -workflows. • Verwaltungssysteme für Content (z. B. CMS, DMS, Portallösungen).
B12: Erhebung der Reifegrade
B14: Zu Reifegrad | C14: Kontrollfrage | F14: Abnahmekriterien | H14: Umsetzung | J14: Nutzen bei Erreichen der Stufe | N14: Kommentar/Hinweis | T14: Listenindex | Y14: Zw. Ergebnis | Z14: Ergebnis
B16: 1 | C16: Wird die Dokumentation mindestens einmalig manuell nach dessen Fertigstellung publiziert? | F16: • Die Dokumentation wird einmalig manuell nach dessen Fertigstellung publiziert | H16: Bitte auswählen | J16: / | S16: =IF(H16="Nicht anwendbar","n.a.",0) -> 0 | T16: =IF(H16="Vollständig",1,0) -> 0 | U16: =IF(H16="In den meisten Fällen",0.75,0) -> 0 | V16: =IF(H16="In ein Paar Fällen",0.5,0) -> 0 | W16: =IF(H16="Gar nicht",0,0) -> 0 | X16: =IF(S16>0,"n.a.",SUM(S16:W16)) -> 0 | Y16: =X16 -> 0 | Z16: =IF(Y16<>"n.a.",SUM(Y16,Y17,Y19,Y23,Y27),NA()) -> 0 | AG16: =IF(X16>0.5,"Umgesetzt","Nicht umgesetzt") -> Nicht umgesetzt
B17: 2 | C17: Werden Publikationen regelmäßig nach individuellen Abläufen oder Projektstandards erstellt? | F17: • Publikationen werden regelmäßig nach individuellen Abläufen oder Projektstandards erstellt • Es gibt bereits erste dokumentierte Zeit- und Projektpläne für den Publikationsprozess | H17: Bitte auswählen | J17: • höhere Reichweite durch mehr Kanäle • leichtere Zugänglichkeit für Nutzende • weniger Fehler durch wiederkehrende Publikationsroutinen | S17: =IF(H17="Nicht anwendbar","n.a.",0) -> 0 | T17: =IF(H17="Vollständig",1,0) -> 0 | U17: =IF(H17="In den meisten Fällen",0.75,0) -> 0 | V17: =IF(H17="In ein Paar Fällen",0.5,0) -> 0 | W17: =IF(H17="Gar nicht",0,0) -> 0 | X17: =IFERROR(SUM(T17:W18)/COUNTIF(H17:H18,"<>Nicht anwendbar"),"n.a.") -> 0 | Y17: =IF(X16=1,X17,0) -> 0 | AG17: =IF(X17>0.5,"Umgesetzt","Nicht umgesetzt") -> Nicht umgesetzt
C18: Gibt es bereits erste dokumentierte Zeit- und Projektpläne für den Publikationsprozess? | H18: Bitte auswählen | S18: =IF(H18="Nicht anwendbar","n.a.",0) -> 0 | T18: =IF(H18="Vollständig",1,0) -> 0 | U18: =IF(H18="In den meisten Fällen",0.75,0) -> 0 | V18: =IF(H18="In ein Paar Fällen",0.5,0) -> 0 | W18: =IF(H18="Gar nicht",0,0) -> 0 | AG18: =IF(X18>0.5,"Umgesetzt","Nicht umgesetzt") -> Nicht umgesetzt
B19: 3 | C19: Sind Publikationsprozesse definiert und dokumentiert (z. B. mit Freigabe, Ausgabeformaten, Kanälen)? | F19: • Publikationsprozesse sind definiert und dokumentier • Verantwortlichkeiten und Zuständigkeiten für den Publikationsprozess sind definiert und zugewiesen • Veröffentlichungen werden konsistent gesteuert und verwaltet • Es bestehen zentrale Vorgaben für die Verwaltung und Auslieferung der Dokumentation | H19: Bitte auswählen | J19: • bessere Planbarkeit von Veröffentlichungen • reduzierte Fehlerquote durchh klare Verantwortlichkeiten | S19: =IF(H19="Nicht anwendbar","n.a.",0) -> 0 | T19: =IF(H19="Vollständig",1,0) -> 0 | U19: =IF(H19="In den meisten Fällen",0.75,0) -> 0 | V19: =IF(H19="In ein Paar Fällen",0.5,0) -> 0 | W19: =IF(H19="Gar nicht",0,0) -> 0 | X19: =IFERROR(SUM(T19:W22)/COUNTIF(H19:H22,"<>Nicht anwendbar"),"n.a.") -> 0 | Y19: =IF(Y17=1,X19,0) -> 0
C20: Sind Verantwortlichkeiten und Zuständigkeiten für den Publikationsprozess definiert und zugewiesen? | H20: Bitte auswählen | S20: =IF(H20="Nicht anwendbar","n.a.",0) -> 0 | T20: =IF(H20="Vollständig",1,0) -> 0 | U20: =IF(H20="In den meisten Fällen",0.75,0) -> 0 | V20: =IF(H20="In ein Paar Fällen",0.5,0) -> 0 | W20: =IF(H20="Gar nicht",0,0) -> 0
C21: Werden Veröffentlichungen konsistent gesteuert und verwaltet? | H21: Bitte auswählen | S21: =IF(H21="Nicht anwendbar","n.a.",0) -> 0 | T21: =IF(H21="Vollständig",1,0) -> 0 | U21: =IF(H21="In den meisten Fällen",0.75,0) -> 0 | V21: =IF(H21="In ein Paar Fällen",0.5,0) -> 0 | W21: =IF(H21="Gar nicht",0,0) -> 0
C22: Bestehen zentrale Vorgaben für die Verwaltung und Auslieferung der Dokumentation? | H22: Bitte auswählen | S22: =IF(H22="Nicht anwendbar","n.a.",0) -> 0 | T22: =IF(H22="Vollständig",1,0) -> 0 | U22: =IF(H22="In den meisten Fällen",0.75,0) -> 0 | V22: =IF(H22="In ein Paar Fällen",0.5,0) -> 0 | W22: =IF(H22="Gar nicht",0,0) -> 0
B23: 4 | C23: Wird die Einhaltung der Publikations- und Verwaltungsprozesse regelmäßig überprüft? | F23: • Die Einhaltung der Publikations- und Verwaltungsprozesse wird regelmäßig überprüft • Der Publikationsprozess mithilfe von Kennzahlen gesteuert • Systeme unterstützen aktiv die Verwaltung und Auslieferung der Inhalte • Es besteht Transparenz über Veröffentlichungszeitpunkte, Zuständigkeiten und Zielgruppen | H23: Bitte auswählen | J23: • vereinfachtes Management großer Informationsmengen | S23: =IF(H23="Nicht anwendbar","n.a.",0) -> 0 | T23: =IF(H23="Vollständig",1,0) -> 0 | U23: =IF(H23="In den meisten Fällen",0.75,0) -> 0 | V23: =IF(H23="In ein Paar Fällen",0.5,0) -> 0 | W23: =IF(H23="Gar nicht",0,0) -> 0 | X23: =IFERROR(SUM(T23:W26)/COUNTIF(H23:H26,"<>Nicht anwendbar"),"n.a.") -> 0 | Y23: =IF(Y19=1,X23,0) -> 0
C24: Wird der Publikationsprozess mithilfe von Kennzahlen gesteuert? | H24: Bitte auswählen | S24: =IF(H24="Nicht anwendbar","n.a.",0) -> 0 | T24: =IF(H24="Vollständig",1,0) -> 0 | U24: =IF(H24="In den meisten Fällen",0.75,0) -> 0 | V24: =IF(H24="In ein Paar Fällen",0.5,0) -> 0 | W24: =IF(H24="Gar nicht",0,0) -> 0
C25: Unterstützen Systeme (z. B. CMS, Portale) aktiv die Verwaltung und Auslieferung der Inhalte? | H25: Bitte auswählen | S25: =IF(H25="Nicht anwendbar","n.a.",0) -> 0 | T25: =IF(H25="Vollständig",1,0) -> 0 | U25: =IF(H25="In den meisten Fällen",0.75,0) -> 0 | V25: =IF(H25="In ein Paar Fällen",0.5,0) -> 0 | W25: =IF(H25="Gar nicht",0,0) -> 0
C26: Besteht Transparenz über Veröffentlichungszeitpunkte, Zuständigkeiten und Zielgruppen? | H26: Bitte auswählen | S26: =IF(H26="Nicht anwendbar","n.a.",0) -> 0 | T26: =IF(H26="Vollständig",1,0) -> 0 | U26: =IF(H26="In den meisten Fällen",0.75,0) -> 0 | V26: =IF(H26="In ein Paar Fällen",0.5,0) -> 0 | W26: =IF(H26="Gar nicht",0,0) -> 0
B27: 5 | C27: Werden Publikations- und Verwaltungsprozesse kontinuierlich verbessert und an neue Anforderungen (z. B. Omnichannel, Headless Delivery) angepasst? | F27: • Publikations- und Verwaltungsprozesse werden kontinuierlich verbessert und an neue Anforderungen angepasst • Innovative Technologien werden eingesetzt | H27: Bitte auswählen | J27: • Nutzerfreundlichkeit durch passgenaue Inhalte • Wettbewerbsvorteil durch innovative Content Delivery • strategische Rolle der Dokumentation als Teil digitaler Services | S27: =IF(H27="Nicht anwendbar","n.a.",0) -> 0 | T27: =IF(H27="Vollständig",1,0) -> 0 | U27: =IF(H27="In den meisten Fällen",0.75,0) -> 0 | V27: =IF(H27="In ein Paar Fällen",0.5,0) -> 0 | W27: =IF(H27="Gar nicht",0,0) -> 0 | X27: =IFERROR(SUM(T27:W28)/COUNTIF(H27:H28,"<>Nicht anwendbar"),"n.a.") -> 0 | Y27: =IF(Y23=1,X27,0) -> 0
C28: Werden innovative Technologien eingesetzt (z. B. vollautomatisierte Publikation)? | H28: Bitte auswählen | S28: =IF(H28="Nicht anwendbar","n.a.",0) -> 0 | T28: =IF(H28="Vollständig",1,0) -> 0 | U28: =IF(H28="In den meisten Fällen",0.75,0) -> 0 | V28: =IF(H28="In ein Paar Fällen",0.5,0) -> 0 | W28: =IF(H28="Gar nicht",0,0) -> 0

Sheet TD3.2
B4: Die Reifegrade werden anhand der jeweiligen Antwort ermittelt. Eine Erläuterung des Aufbaus der Reifegrade und der Antwortmöglichkeiten finden Sie in den Ausfüllhinweisen.
B6: TD3.2 | C6: Content Delivery - Zugriffsmanagement | K6: Reifegrad: | L6: =ROUNDDOWN(Z16/0.25,0)*0.25 -> 0 | M6: =IF(L6<1,"Unvollständig",IF(L6<2,"Initial",IF(L6<3,"Gemanagt",IF(L6<4,"Definiert",IF(L6<5,"Quantitativ gemanagt",IF(L6<6,"Optimiert","Ausstehend")))))) -> Unvollständig
B7: Zweck | C7: Das Zugriffsmanagement stellt sicher, dass Nutzerinnen nur auf die für sie relevanten und freigegebenen Dokumentationsinhalte zugreifen können. Ziel ist der Schutz vertraulicher Informationen, die Einhaltung rechtlicher Vorgaben und die nutzerorientierte Bereitstellung von Dokumentation.
B8: Ergebnisse | C8: • Zugriffsrechte sind klar definiert und nach Rollen oder Nutzergruppen zugewiesen. • Nur autorisierte Personen können sensible oder interne Inhalte einsehen. • Es ist nachvollziehbar, wer wann auf welche Inhalte zugegriffen hat. • Dokumentationszugriffe sind effizient, sicher und zielgruppenorientiert organisiert.
B9: Basispraktiken | C9: • Definition und Verwaltung von Rollen, Rechten und Zugriffsprofilen. • Technische Umsetzung des Berechtigungsmanagements in Systemen. • Regelmäßige Überprüfung und Aktualisierung der Berechtigungen. • Sicherstellung der Einhaltung rechtlicher Vorgaben (z. B. Datenschutz, Exportkontrolle). • Kontinuierliche Optimierung durch Automatisierung oder Integration mit anderen Systemen (z. B. ERP, PLM).
B10: Arbeitsprodukte | C10: • Rollen- und Berechtigungskonzepte. • Benutzer- und Gruppenrichtlinien. • Protokolle über Zugriffe, Freigaben und Änderungen. • Systemeinstellungen im CMS, DMS oder Portal zum Rechte- und Rollenmanagement.
B12: Erhebung der Reifegrade
B14: Zu Reifegrad | C14: Kontrollfrage | F14: Abnahmekriterien | H14: Umsetzung | J14: Nutzen bei Erreichen der Stufe | N14: Kommentar/Hinweis | T14: Listenindex | Y14: Zw. Ergebnis | Z14: Ergebnis
B16: 1 | C16: Ist die Etablierung eines Zugriffsmanagements zumindest geplant? | F16: • Alle Personen können auf alle Inhalte zugreifen | H16: Bitte auswählen | J16: / | S16: =IF(H16="Nicht anwendbar","n.a.",0) -> 0 | T16: =IF(H16="Vollständig",1,0) -> 0 | U16: =IF(H16="In den meisten Fällen",0.75,0) -> 0 | V16: =IF(H16="In ein Paar Fällen",0.5,0) -> 0 | W16: =IF(H16="Gar nicht",0,0) -> 0 | X16: =IF(S16>0,"n.a.",SUM(S16:W16)) -> 0 | Y16: =X16 -> 0 | Z16: =IF(Y16<>"n.a.",SUM(Y16,Y17,Y19,Y22,Y25),NA()) -> 0 | AG16: =IF(X16>0.5,"Umgesetzt","Nicht umgesetzt") -> Nicht umgesetzt
B17: 2 | C17: Sind mindestens erste Nutzergruppen oder Dateiberechtigungen definiert? Wird darüber das Zugriffsmanagement darüber gelegentlich gesteuert? | F17: • Erste Nutzergruppen oder Dateiberechtigungen sind definiert • Das Zugriffsmanagement wird gelegentlich über diese Gruppen oder Berechtigungen gesteuert • Zugriffe werden fallweise geregelt | H17: Bitte auswählen | J17: • mehr Sicherheit gegenüber offenem Zugang • erste Reduzierung von Missbrauchs- und Fehlerpotenzial | S17: =IF(H17="Nicht anwendbar","n.a.",0) -> 0 | T17: =IF(H17="Vollständig",1,0) -> 0 | U17: =IF(H17="In den meisten Fällen",0.75,0) -> 0 | V17: =IF(H17="In ein Paar Fällen",0.5,0) -> 0 | W17: =IF(H17="Gar nicht",0,0) -> 0 | X17: =IFERROR(SUM(T17:W18)/COUNTIF(H17:H18,"<>Nicht anwendbar"),"n.a.") -> 0 | Y17: =IF(X16=1,X17,0) -> 0 | AG17: =IF(X17>0.5,"Umgesetzt","Nicht umgesetzt") -> Nicht umgesetzt
C18: Werden Zugriffe zumindest fallweise geregelt, z. B. durch individuelle Freigaben oder einfache Passwortschutzmechanismen? | H18: Bitte auswählen | S18: =IF(H18="Nicht anwendbar","n.a.",0) -> 0 | T18: =IF(H18="Vollständig",1,0) -> 0 | U18: =IF(H18="In den meisten Fällen",0.75,0) -> 0 | V18: =IF(H18="In ein Paar Fällen",0.5,0) -> 0 | W18: =IF(H18="Gar nicht",0,0) -> 0 | AG18: =IF(X18>0.5,"Umgesetzt","Nicht umgesetzt") -> Nicht umgesetzt
B19: 3 | C19: Existiert ein definiertes und dokumentiertes Rollen- und Berechtigungskonzept? | F19: • Ein definiertes und dokumentiertes Rollen- und Berechtigungskonzept existiert • Zugriffsrechte sind konsistent im System umgesetzt und werden systematisch vergeben • Es erfolgt eine klare Unterscheidung zwischen internen, externen und öffentlichen Inhalten | H19: Bitte auswählen | J19: • Reduzierung von Haftungs- und Compliance-Risiken • bessere Planbarkeit bei Publikationen für verschiedene Nutzergruppen | S19: =IF(H19="Nicht anwendbar","n.a.",0) -> 0 | T19: =IF(H19="Vollständig",1,0) -> 0 | U19: =IF(H19="In den meisten Fällen",0.75,0) -> 0 | V19: =IF(H19="In ein Paar Fällen",0.5,0) -> 0 | W19: =IF(H19="Gar nicht",0,0) -> 0 | X19: =IFERROR(SUM(T19:W21)/COUNTIF(H19:H21,"<>Nicht anwendbar"),"n.a.") -> 0 | Y19: =IF(Y17=1,X19,0) -> 0
C20: Sind Zugriffsrechte konsistent im System umgesetzt und werden systematisch vergeben? | H20: Bitte auswählen | S20: =IF(H20="Nicht anwendbar","n.a.",0) -> 0 | T20: =IF(H20="Vollständig",1,0) -> 0 | U20: =IF(H20="In den meisten Fällen",0.75,0) -> 0 | V20: =IF(H20="In ein Paar Fällen",0.5,0) -> 0 | W20: =IF(H20="Gar nicht",0,0) -> 0
C21: Erfolgt eine klare Unterscheidung zwischen internen, externen und öffentlichen Inhalten? | H21: Bitte auswählen | S21: =IF(H21="Nicht anwendbar","n.a.",0) -> 0 | T21: =IF(H21="Vollständig",1,0) -> 0 | U21: =IF(H21="In den meisten Fällen",0.75,0) -> 0 | V21: =IF(H21="In ein Paar Fällen",0.5,0) -> 0 | W21: =IF(H21="Gar nicht",0,0) -> 0
B22: 4 | C22: Ist jederzeit nachvollziehbar, wer auf welche Inhalte zugegriffen hat (Logging)? | F22: • Es ist jederzeit nachvollziehbar, wer auf welche Inhalte zugegriffen hat (Logging) • Die Einhaltung des Zugriffsmanagements wird regelmäßig überprüft (z. B. durch Audits oder Protokollauswertungen) • Systeme zur Verwaltung von Berechtigungen werden aktiv genutzt | H22: Bitte auswählen | J22: • höhere Datensicherheit durch Integration in IT-Sicherheitskonzepte | S22: =IF(H22="Nicht anwendbar","n.a.",0) -> 0 | T22: =IF(H22="Vollständig",1,0) -> 0 | U22: =IF(H22="In den meisten Fällen",0.75,0) -> 0 | V22: =IF(H22="In ein Paar Fällen",0.5,0) -> 0 | W22: =IF(H22="Gar nicht",0,0) -> 0 | X22: =IFERROR(SUM(T22:W24)/COUNTIF(H22:H24,"<>Nicht anwendbar"),"n.a.") -> 0 | Y22: =IF(Y19=1,X22,0) -> 0
C23: Wird die Einhaltung des Zugriffsmanagements regelmäßig überprüft (z. B. durch Audits oder Protokollauswertungen)? | H23: Bitte auswählen | S23: =IF(H23="Nicht anwendbar","n.a.",0) -> 0 | T23: =IF(H23="Vollständig",1,0) -> 0 | U23: =IF(H23="In den meisten Fällen",0.75,0) -> 0 | V23: =IF(H23="In ein Paar Fällen",0.5,0) -> 0 | W23: =IF(H23="Gar nicht",0,0) -> 0
C24: Werden Systeme zur Verwaltung von Berechtigungen aktiv genutzt? | H24: Bitte auswählen | S24: =IF(H24="Nicht anwendbar","n.a.",0) -> 0 | T24: =IF(H24="Vollständig",1,0) -> 0 | U24: =IF(H24="In den meisten Fällen",0.75,0) -> 0 | V24: =IF(H24="In ein Paar Fällen",0.5,0) -> 0 | W24: =IF(H24="Gar nicht",0,0) -> 0
B25: 5 | C25: Werden innovative Technologien wie Single-Sign-On, adaptive Zugriffssteuerung oder KI-gestützte Anomalieerkennung genutzt? | F25: • Innovative Technologien wie Single-Sign-On, adaptive Zugriffssteuerung oder KI-gestützte Anomalieerkennung werden eingesetzt • Das Zugriffsmanagement ist unternehmensweit mit anderen Systemen integriert • Das Zugriffsmanagement erfolgt dynamisch mit Personalisierung | H25: Bitte auswählen | J25: • Nutzerfreundlichkeit durch personalisierte Zugriffe • hohe Sicherheit durch kontextsensitive Mechnismen • strategischer Vorteil durch Integration in digitale Geschäftsmodelle • Transparenz durch kontinuierliches Monitoring und Reporting | S25: =IF(H25="Nicht anwendbar","n.a.",0) -> 0 | T25: =IF(H25="Vollständig",1,0) -> 0 | U25: =IF(H25="In den meisten Fällen",0.75,0) -> 0 | V25: =IF(H25="In ein Paar Fällen",0.5,0) -> 0 | W25: =IF(H25="Gar nicht",0,0) -> 0 | X25: =IFERROR(SUM(T25:W27)/COUNTIF(H25:H27,"<>Nicht anwendbar"),"n.a.") -> 0 | Y25: =IF(Y22=1,X25,0) -> 0
C26: Erfolgt eine unternehmensweite Integration des Zugriffsmanagements mit anderen Systemen? | H26: Bitte auswählen | S26: =IF(H26="Nicht anwendbar","n.a.",0) -> 0 | T26: =IF(H26="Vollständig",1,0) -> 0 | U26: =IF(H26="In den meisten Fällen",0.75,0) -> 0 | V26: =IF(H26="In ein Paar Fällen",0.5,0) -> 0 | W26: =IF(H26="Gar nicht",0,0) -> 0
C27: Erfolgt das Zugriffsmanagement dynamisch mit Personalisierung? | H27: Bitte auswählen | S27: =IF(H27="Nicht anwendbar","n.a.",0) -> 0 | T27: =IF(H27="Vollständig",1,0) -> 0 | U27: =IF(H27="In den meisten Fällen",0.75,0) -> 0 | V27: =IF(H27="In ein Paar Fällen",0.5,0) -> 0 | W27: =IF(H27="Gar nicht",0,0) -> 0

Sheet TD3.3
B4: Die Reifegrade werden anhand der jeweiligen Antwort ermittelt. Eine Erläuterung des Aufbaus der Reifegrade und der Antwortmöglichkeiten finden Sie in den Ausfüllhinweisen.
B6: TD3.3 | C6: Content Delivery - Zugänglichkeit der Dokumentation | K6: Reifegrad: | L6: =ROUNDDOWN(Z16/0.25,0)*0.25 -> 0 | M6: =IF(L6<1,"Unvollständig",IF(L6<2,"Initial",IF(L6<3,"Gemanagt",IF(L6<4,"Definiert",IF(L6<5,"Quantitativ gemanagt",IF(L6<6,"Optimiert","Ausstehend")))))) -> Unvollständig
B7: Zweck | C7: Dokumentationsinhalte sind in der für den Anwendungsfall passenden Granularität zugänglich sind. Ziel ist es, dass Nutzerinnen genau die Informationseinheit erhalten, die sie benötigen – sei es als vollständiges Dokument, als Modul, Topic oder einzelnes Datenelement.
B8: Ergebnisse | C8: • Inhalte sind in einer definierten Granularität verfügbar (z. B. Dokument, Kapitel, Modul, Topic, Datenobjekt). • Nutzerinnen erhalten bedarfsgerechten Zugriff auf Informationen (z. B. kontext- oder rollenbasiert). • Granularität und Zugriffsmodell sind konsistent und nachvollziehbar dokumentiert. • Die Informationsarchitektur unterstützt Wiederverwendung und effiziente Auslieferung.
B9: Basispraktiken | C9: • Festlegung der kleinsten Informationseinheit (Dokument, Modul, Topic). • Strukturierung von Inhalten nach wiederverwendbaren Bausteinen. • Nutzung von Metadaten und Taxonomien zur gezielten Bereitstellung. • Implementierung von Systemen zur Verwaltung granularer Inhalte (z. B. CCMS). • Kontinuierliche Anpassung der Granularität an Nutzer- und Systemanforderungen.
B10: Arbeitsprodukte | C10: • Dokumentationsinhalte in der jeweils definierten Granularität (z. B. PDF, XML-Dateien, modulare Topics). • Klassifikationen und Metadaten, die den Zugriff auf verschiedene Granularitätsebenen ermöglichen. • Richtlinien zur Strukturierung und Modularisierung. • Systemeinstellungen oder Plattformen, die den granularen Zugriff steuern (z. B. CMS, Portale, APIs).
B12: Erhebung der Reifegrade
B14: Zu Reifegrad | C14: Kontrollfrage | F14: Abnahmekriterien | H14: Umsetzung | J14: Nutzen bei Erreichen der Stufe | N14: Kommentar/Hinweis | T14: Listenindex | Y14: Zw. Ergebnis | Z14: Ergebnis
B16: 1 | C16: Erfolgt die Bereitstellung technischer Dokumente in einem elektronischen Format, das elektronisch zugänglich ist oder einfach und zuverlässig in ein solches Format umgewandelt werden kann (z.B. PDF)? | F16: • Die Bereitstellung technischer Dokumente erfolgt in einem elektronischen Format, das elektronisch zugänglich ist oder einfach und zuverlässig in ein solches Format umgewandelt werden kann | H16: Bitte auswählen | J16: / | S16: =IF(H16="Nicht anwendbar","n.a.",0) -> 0 | T16: =IF(H16="Vollständig",1,0) -> 0 | U16: =IF(H16="In den meisten Fällen",0.75,0) -> 0 | V16: =IF(H16="In ein Paar Fällen",0.5,0) -> 0 | W16: =IF(H16="Gar nicht",0,0) -> 0 | X16: =IF(S16>0,"n.a.",SUM(S16:W16)) -> 0 | Y16: =X16 -> 0 | Z16: =IF(Y16<>"n.a.",SUM(Y16,Y17,Y19,Y22,Y25),NA()) -> 0 | AG16: =IF(X16>0.5,"Umgesetzt","Nicht umgesetzt") -> Nicht umgesetzt
B17: 2 | C17: Ist die technische Dokumentation in einem strukturierten und nicht-proprietären Format (z.B. XML) zugänglich? | F17: • Die technische Dokumentation ist in einem strukturierten und nicht-proprietären Format (z. B. XML) zugänglich • Es bestehen vereinzelte Möglichkeiten, Inhalte unabhängig vom Gesamtdokument zu verwenden | H17: Bitte auswählen | J17: • gezieltere Bereitstellung für bestimmte Zielgruppen • erste Anpassungsmöglichkeiten für Märkte oder Produkte | S17: =IF(H17="Nicht anwendbar","n.a.",0) -> 0 | T17: =IF(H17="Vollständig",1,0) -> 0 | U17: =IF(H17="In den meisten Fällen",0.75,0) -> 0 | V17: =IF(H17="In ein Paar Fällen",0.5,0) -> 0 | W17: =IF(H17="Gar nicht",0,0) -> 0 | X17: =IFERROR(SUM(T17:W18)/COUNTIF(H17:H18,"<>Nicht anwendbar"),"n.a.") -> 0 | Y17: =IF(X16=1,X17,0) -> 0 | AG17: =IF(X17>0.5,"Umgesetzt","Nicht umgesetzt") -> Nicht umgesetzt
C18: Bestehen vereinzelte Möglichkeiten, Inhalte unabhängig vom Gesamtdokument zu verwenden? | H18: Bitte auswählen | S18: =IF(H18="Nicht anwendbar","n.a.",0) -> 0 | T18: =IF(H18="Vollständig",1,0) -> 0 | U18: =IF(H18="In den meisten Fällen",0.75,0) -> 0 | V18: =IF(H18="In ein Paar Fällen",0.5,0) -> 0 | W18: =IF(H18="Gar nicht",0,0) -> 0 | AG18: =IF(X18>0.5,"Umgesetzt","Nicht umgesetzt") -> Nicht umgesetzt
B19: 3 | C19: Ist die Dokumentation in Modulen verfügbar, die einzeln zugänglich sind? | F19: • Die Dokumentation ist in Modulen verfügbar, die einzeln zugänglich sind • Die Informationsarchitektur unterstützt die Wiederverwendung einzelner Module • Es gibt definierte Standards für die Modularisierung | H19: Bitte auswählen | J19: • bessere Wiederverwendbarkeit von Inhalten • gezielte Informationsbereitstellung für bestimmte Anwendungsfälle | S19: =IF(H19="Nicht anwendbar","n.a.",0) -> 0 | T19: =IF(H19="Vollständig",1,0) -> 0 | U19: =IF(H19="In den meisten Fällen",0.75,0) -> 0 | V19: =IF(H19="In ein Paar Fällen",0.5,0) -> 0 | W19: =IF(H19="Gar nicht",0,0) -> 0 | X19: =IFERROR(SUM(T19:W21)/COUNTIF(H19:H21,"<>Nicht anwendbar"),"n.a.") -> 0 | Y19: =IF(Y17=1,X19,0) -> 0
C20: Unterstützt die Informationsarchitektur die Wiederverwendung einzelner Module? | H20: Bitte auswählen | S20: =IF(H20="Nicht anwendbar","n.a.",0) -> 0 | T20: =IF(H20="Vollständig",1,0) -> 0 | U20: =IF(H20="In den meisten Fällen",0.75,0) -> 0 | V20: =IF(H20="In ein Paar Fällen",0.5,0) -> 0 | W20: =IF(H20="Gar nicht",0,0) -> 0
C21: Gibt es definierte Standards für die Modularisierung? | H21: Bitte auswählen | S21: =IF(H21="Nicht anwendbar","n.a.",0) -> 0 | T21: =IF(H21="Vollständig",1,0) -> 0 | U21: =IF(H21="In den meisten Fällen",0.75,0) -> 0 | V21: =IF(H21="In ein Paar Fällen",0.5,0) -> 0 | W21: =IF(H21="Gar nicht",0,0) -> 0
B22: 4 | C22: Sind die Module über Identifikatoren (z.B. URIs) eindeutig zugänglich? | F22: • Die Module sind über Identifikatoren (z. B. URIs) eindeutig zugänglich • Eine klare Metadatenstruktur erlaubt den gezielten Zugriff auf einzelne Topics • Systeme (z. B. CCMS) unterstützen die Verwaltung und Auslieferung granularer Inhalte | H22: Bitte auswählen | J22: • Nutzer erhalten genau die Informationen, die sie in ihrer Situation benötigen • erhebliche Verbesserung der Nutzerfreundlichkeit • Reduzierung von Fehlbedingungen oder Missverständnissen | S22: =IF(H22="Nicht anwendbar","n.a.",0) -> 0 | T22: =IF(H22="Vollständig",1,0) -> 0 | U22: =IF(H22="In den meisten Fällen",0.75,0) -> 0 | V22: =IF(H22="In ein Paar Fällen",0.5,0) -> 0 | W22: =IF(H22="Gar nicht",0,0) -> 0 | X22: =IFERROR(SUM(T22:W24)/COUNTIF(H22:H24,"<>Nicht anwendbar"),"n.a.") -> 0 | Y22: =IF(Y19=1,X22,0) -> 0
C23: Besteht eine klare Metadatenstruktur, die den gezielten Zugriff auf einzelne Topics erlaubt? | H23: Bitte auswählen | S23: =IF(H23="Nicht anwendbar","n.a.",0) -> 0 | T23: =IF(H23="Vollständig",1,0) -> 0 | U23: =IF(H23="In den meisten Fällen",0.75,0) -> 0 | V23: =IF(H23="In ein Paar Fällen",0.5,0) -> 0 | W23: =IF(H23="Gar nicht",0,0) -> 0
C24: Unterstützen Systeme (z. B. CCMS) die Verwaltung und Auslieferung dieser granularen Inhalte? | H24: Bitte auswählen | S24: =IF(H24="Nicht anwendbar","n.a.",0) -> 0 | T24: =IF(H24="Vollständig",1,0) -> 0 | U24: =IF(H24="In den meisten Fällen",0.75,0) -> 0 | V24: =IF(H24="In ein Paar Fällen",0.5,0) -> 0 | W24: =IF(H24="Gar nicht",0,0) -> 0
B25: 5 | C25: Können Inhalte auf feinster Ebene (z. B. Datenobjekte, Informationselemente) zielgerichtet abgerufen werden? | F25: • Inhalte können auf feinster Ebene (z. B. Datenobjekte, Informationselemente) zielgerichtet abgerufen werden • Die Elemente verfügen über Semantik und beziehen sich auf Konzepte einer Ontologie • Die Granularität wird kontinuierlich an neue Anforderungen (z. B. IoT, Digital Twin, AR/VR) angepasst | H25: Bitte auswählen | J25: • höchstmögliche Relevanz der Informationen durch Aktualität und Kontextbezug • Unterstützung digitaler Geschäftsmodelle • strategischer Wettbewerbsvorteil durch dynamische und integrierte Content-Ökosysteme | S25: =IF(H25="Nicht anwendbar","n.a.",0) -> 0 | T25: =IF(H25="Vollständig",1,0) -> 0 | U25: =IF(H25="In den meisten Fällen",0.75,0) -> 0 | V25: =IF(H25="In ein Paar Fällen",0.5,0) -> 0 | W25: =IF(H25="Gar nicht",0,0) -> 0 | X25: =IFERROR(SUM(T25:W27)/COUNTIF(H25:H27,"<>Nicht anwendbar"),"n.a.") -> 0 | Y25: =IF(Y22=1,X25,0) -> 0
C26: Verfügen die Elemente über Semantik und beziehen sie sich auf Konzepte einer Ontologie? | H26: Bitte auswählen | S26: =IF(H26="Nicht anwendbar","n.a.",0) -> 0 | T26: =IF(H26="Vollständig",1,0) -> 0 | U26: =IF(H26="In den meisten Fällen",0.75,0) -> 0 | V26: =IF(H26="In ein Paar Fällen",0.5,0) -> 0 | W26: =IF(H26="Gar nicht",0,0) -> 0
C27: Wird die Granularität kontinuierlich an neue Anforderungen (z. B. IoT, Digital Twin, AR/VR) angepasst? | H27: Bitte auswählen | S27: =IF(H27="Nicht anwendbar","n.a.",0) -> 0 | T27: =IF(H27="Vollständig",1,0) -> 0 | U27: =IF(H27="In den meisten Fällen",0.75,0) -> 0 | V27: =IF(H27="In ein Paar Fällen",0.5,0) -> 0 | W27: =IF(H27="Gar nicht",0,0) -> 0

Sheet TD3.4
B4: Die Reifegrade werden anhand der jeweiligen Antwort ermittelt. Eine Erläuterung des Aufbaus der Reifegrade und der Antwortmöglichkeiten finden Sie in den Ausfüllhinweisen.
B6: TD3.4 | C6: Content Delivery - Kanäle und Plattformen | K6: Reifegrad: | L6: =ROUNDDOWN(Z16/0.25,0)*0.25 -> 0 | M6: =IF(L6<1,"Unvollständig",IF(L6<2,"Initial",IF(L6<3,"Gemanagt",IF(L6<4,"Definiert",IF(L6<5,"Quantitativ gemanagt",IF(L6<6,"Optimiert","Ausstehend")))))) -> Unvollständig
B7: Zweck | C7: Medien, Systeme und Ausgabekanäle über die die Dokumentationsinhalte bereitgestellt werden. Ziel ist es, dass die Inhalte zielgruppen- und kontextspezifisch auf den jeweils passenden Plattformen verfügbar sind.
B8: Ergebnisse | C8: • Inhalte sind in einem definierten Grad über verschiedene Kanäle verfügbar. • Die Kanäle sind konsistent aufeinander abgestimmt (keine widersprüchlichen Informationsstände). • Plattformen unterstützen eine nutzerorientierte Auslieferung. • Neue Kanäle und Technologien (z. B. AR/VR, IoT, Digital Twin) können flexibel integriert werden.
B9: Basispraktiken | C9: • Publikation in einem einzelnen Kanal ohne Synchronisierung. • Bereitstellung in mehreren Kanälen (z. B. Print + PDF), jedoch ohne Integration. • Systematische Mehrkanalpublikation auf Basis modularer Inhalte. • Einsatz von Portalen oder Headless-Delivery-Ansätzen für kontextsensitive Nutzung. • Omnichannel-Strategie mit dynamischer Ausspielung, Vernetzung und API-First-Ansatz.
B10: Arbeitsprodukte | C10: • Publikationen in einem oder mehreren Kanälen (z. B. Print, PDF, Portal). • Richtlinien zur Nutzung und Pflege von Ausgabekanälen. • Metadatenmodelle oder Steuerungsmechanismen für Mehrkanal- oder kontextsensitive Ausspielung. • Plattformen oder Systeme zur zentralen Verwaltung und Publikation (z. B. CCMS, Headless CMS). • Schnittstellen oder APIs zur Integration von Inhalten in externe Systeme oder neue Plattformen.
B12: Erhebung der Reifegrade
B14: Zu Reifegrad | C14: Kontrollfrage | F14: Abnahmekriterien | H14: Umsetzung | J14: Nutzen bei Erreichen der Stufe | N14: Kommentar/Hinweis | T14: Listenindex | Y14: Zw. Ergebnis | Z14: Ergebnis
B16: 1 | C16: Werden zumindest Ad-Hoc Kanäle für die Veröffentlichung ausgewählt? | F16: • Individuelle Kanäle werden für die Veröffentlichung verwendet | H16: Bitte auswählen | J16: / | S16: =IF(H16="Nicht anwendbar","n.a.",0) -> 0 | T16: =IF(H16="Vollständig",1,0) -> 0 | U16: =IF(H16="In den meisten Fällen",0.75,0) -> 0 | V16: =IF(H16="In ein Paar Fällen",0.5,0) -> 0 | W16: =IF(H16="Gar nicht",0,0) -> 0 | X16: =IF(S16>0,"n.a.",SUM(S16:W16)) -> 0 | Y16: =X16 -> 0 | Z16: =IF(Y16<>"n.a.",SUM(Y16,Y17,Y19,Y21,Y23),NA()) -> 0 | AG16: =IF(X16>0.5,"Umgesetzt","Nicht umgesetzt") -> Nicht umgesetzt
B17: 2 | C17: Bestehen gelegentlich Absprachen über zu verwendende Kanäle zur Publikation? | F17: • Erste Absprachen über die zu verwendenden Kanäle zur Publikation bestehen • Inhalte werden in mehreren Kanälen bereitgestellt (z. B. Print, PDF, Website), wobei die Pflege in den unterschiedlichen Kanälen unabhängig voneinander erfolgt | H17: Bitte auswählen | J17: • höhere Reichweite • erste Flexibilität in der Bereitstellung | S17: =IF(H17="Nicht anwendbar","n.a.",0) -> 0 | T17: =IF(H17="Vollständig",1,0) -> 0 | U17: =IF(H17="In den meisten Fällen",0.75,0) -> 0 | V17: =IF(H17="In ein Paar Fällen",0.5,0) -> 0 | W17: =IF(H17="Gar nicht",0,0) -> 0 | X17: =IFERROR(SUM(T17:W18)/COUNTIF(H17:H18,"<>Nicht anwendbar"),"n.a.") -> 0 | Y17: =IF(X16=1,X17,0) -> 0 | AG17: =IF(X17>0.5,"Umgesetzt","Nicht umgesetzt") -> Nicht umgesetzt
C18: Werden Inhalte in mehreren Kanälen bereitgestellt (z. B. Print, PDF, Website), wobei die Pflege in den unterschiedlichen Kanälen noch unabhängig voneinander erfolgt? | H18: Bitte auswählen | S18: =IF(H18="Nicht anwendbar","n.a.",0) -> 0 | T18: =IF(H18="Vollständig",1,0) -> 0 | U18: =IF(H18="In den meisten Fällen",0.75,0) -> 0 | V18: =IF(H18="In ein Paar Fällen",0.5,0) -> 0 | W18: =IF(H18="Gar nicht",0,0) -> 0 | AG18: =IF(X18>0.5,"Umgesetzt","Nicht umgesetzt") -> Nicht umgesetzt
B19: 3 | C19: Ist die Pflege der Inhalte zentralisiert, sodass Konsistenz über alle Kanäle hinweg gewährleistet ist? | F19: • Die Pflege der Inhalte ist zentralisiert, sodass Konsistenz über alle Kanäle hinweg gewährleistet ist • Die Nutzung der Kanäle wird regelmäßig erfasst und dokumentiert | H19: Bitte auswählen | J19: • Konsistenz der Inhalte über Kanäle hinweg • bessere Planbarkeit von Publikationen | S19: =IF(H19="Nicht anwendbar","n.a.",0) -> 0 | T19: =IF(H19="Vollständig",1,0) -> 0 | U19: =IF(H19="In den meisten Fällen",0.75,0) -> 0 | V19: =IF(H19="In ein Paar Fällen",0.5,0) -> 0 | W19: =IF(H19="Gar nicht",0,0) -> 0 | X19: =IFERROR(SUM(T19:W20)/COUNTIF(H19:H20,"<>Nicht anwendbar"),"n.a.") -> 0 | Y19: =IF(Y17=1,X19,0) -> 0
C20: Wird die Nutzung der Kanäle regelmäßig erfasst und dokumentiert? | H20: Bitte auswählen | S20: =IF(H20="Nicht anwendbar","n.a.",0) -> 0 | T20: =IF(H20="Vollständig",1,0) -> 0 | U20: =IF(H20="In den meisten Fällen",0.75,0) -> 0 | V20: =IF(H20="In ein Paar Fällen",0.5,0) -> 0 | W20: =IF(H20="Gar nicht",0,0) -> 0
B21: 4 | C21: Erfolgt die Ausspielung der Inhalte kontextspezifisch über Plattformen (z. B. Portal, App)? | F21: • Die Ausspielung der Inhalte erfolgt kontextspezifisch über Plattformen (z. B. Portal, App) • Nutzungsdaten werden systematisch ausgewertet, um Kanäle und Plattformen gezielt weiterzuentwickeln | H21: Bitte auswählen | J21: • Effizienzsteigerung durch einmalige Inhaltspflege • hohe Konsistenz und Aktualität über alle Kanäle • schnelle Publikation in vielen Formaten gleichzeitig | S21: =IF(H21="Nicht anwendbar","n.a.",0) -> 0 | T21: =IF(H21="Vollständig",1,0) -> 0 | U21: =IF(H21="In den meisten Fällen",0.75,0) -> 0 | V21: =IF(H21="In ein Paar Fällen",0.5,0) -> 0 | W21: =IF(H21="Gar nicht",0,0) -> 0 | X21: =IFERROR(SUM(T21:W22)/COUNTIF(H21:H22,"<>Nicht anwendbar"),"n.a.") -> 0 | Y21: =IF(Y19=1,X21,0) -> 0
C22: Werden die Nutzungsdaten systematisch ausgewertet, um Kanäle und Plattformen gezielt weiterzuentwickeln? | H22: Bitte auswählen | S22: =IF(H22="Nicht anwendbar","n.a.",0) -> 0 | T22: =IF(H22="Vollständig",1,0) -> 0 | U22: =IF(H22="In den meisten Fällen",0.75,0) -> 0 | V22: =IF(H22="In ein Paar Fällen",0.5,0) -> 0 | W22: =IF(H22="Gar nicht",0,0) -> 0
B23: 5 | C23: Gibt es eine Omnichannel-Strategie, die Inhalte konsistent und dynamisch über alle relevanten Kanäle hinweg ausliefert? | F23: • Es existiert eine Omnichannel-Strategie, die Inhalte konsistent und dynamisch über alle relevanten Kanäle hinweg ausliefert • Nutzungsdaten werden automatisiert in den Redaktionsprozess zurückgeführt und für kontinuierliche Optimierung (z. B. KI-gestützt) genutzt • Inhalte werden über APIs oder Schnittstellen in externe Systeme integriert und sind flexibel auf neuen Plattformen nutzbar | H23: Bitte auswählen | J23: • Nutzerfreundlichkeit durch personalisierte Bereitstellung • Wettbewerbsvorteil durch innovative Content Delivery • strategische Rolle der Dokumentation als Teil digitaler Services und Ökosysteme | S23: =IF(H23="Nicht anwendbar","n.a.",0) -> 0 | T23: =IF(H23="Vollständig",1,0) -> 0 | U23: =IF(H23="In den meisten Fällen",0.75,0) -> 0 | V23: =IF(H23="In ein Paar Fällen",0.5,0) -> 0 | W23: =IF(H23="Gar nicht",0,0) -> 0 | X23: =IFERROR(SUM(T23:W25)/COUNTIF(H23:H25,"<>Nicht anwendbar"),"n.a.") -> 0 | Y23: =IF(Y21=1,X23,0) -> 0
C24: Werden Nutzungsdaten automatisiert in den Redaktionsprozess zurückgeführt und für kontinuierliche Optimierung (z. B. KI-gestützt) genutzt? | H24: Bitte auswählen | S24: =IF(H24="Nicht anwendbar","n.a.",0) -> 0 | T24: =IF(H24="Vollständig",1,0) -> 0 | U24: =IF(H24="In den meisten Fällen",0.75,0) -> 0 | V24: =IF(H24="In ein Paar Fällen",0.5,0) -> 0 | W24: =IF(H24="Gar nicht",0,0) -> 0
C25: Werden Inhalte über APIs oder Schnittstellen in externe Systeme integriert und flexibel auf neuen Plattformen nutzbar gemacht? | H25: Bitte auswählen | S25: =IF(H25="Nicht anwendbar","n.a.",0) -> 0 | T25: =IF(H25="Vollständig",1,0) -> 0 | U25: =IF(H25="In den meisten Fällen",0.75,0) -> 0 | V25: =IF(H25="In ein Paar Fällen",0.5,0) -> 0 | W25: =IF(H25="Gar nicht",0,0) -> 0

Sheet TD4.1
B4: Die Reifegrade werden anhand der jeweiligen Antwort ermittelt. Eine Erläuterung des Aufbaus der Reifegrade und der Antwortmöglichkeiten finden Sie in den Ausfüllhinweisen.
B6: TD4.1 | C6: Zielgruppenorientierung - Zielgruppenkenntnis | K6: Reifegrad: | L6: =ROUNDDOWN(Z16/0.25,0)*0.25 -> 0 | M6: =IF(L6<1,"Unvollständig",IF(L6<2,"Initial",IF(L6<3,"Gemanagt",IF(L6<4,"Definiert",IF(L6<5,"Quantitativ gemanagt",IF(L6<6,"Optimiert","Ausstehend")))))) -> Unvollständig
B7: Zweck | C7: Die Zielgruppenkenntnis beschreibt, in welchem Maß Unternehmen ihre Nutzerinnen, deren Anforderungen und Nutzungssituationen kennen und berücksichtigen. Ziel ist es, die Dokumentation systematisch an den Informationsbedürfnissen und Nutzungskontexten der Zielgruppen auszurichten.
B8: Ergebnisse | C8: • Die Zielgruppen sind klar identifiziert und beschrieben. • Informationsbedürfnisse und Nutzungskontexte der Zielgruppen sind dokumentiert. • Dokumentationsinhalte sind an den Bedürfnissen der Zielgruppen ausgerichtet. • Erkenntnisse aus Zielgruppenanalysen werden regelmäßig aktualisiert und in die Dokumentation zurückgeführt.
B9: Basispraktiken | C9: • Identifikation der relevanten Zielgruppen. • Erhebung von Anforderungen und Nutzungssituationen. • Systematische Analyse und Dokumentation der Zielgruppenbedürfnisse. • Integration der Ergebnisse in den Redaktionsprozess. • Kontinuierliche Evaluation und Anpassung durch Feedback- und Trackingdaten
B10: Arbeitsprodukte | C10: • Zielgruppenprofile oder Personas. • Bedarfs- und Nutzungsszenarien. • Anforderungen der Zielgruppen an Inhalte und Medien. • Auswertungen von Nutzerfeedback oder Nutzungstracking. • Richtlinien zur zielgruppengerechten Dokumentation.
B12: Erhebung der Reifegrade
B14: Zu Reifegrad | C14: Kontrollfrage | F14: Abnahmekriterien | H14: Umsetzung | J14: Nutzen bei Erreichen der Stufe | N14: Kommentar/Hinweis | T14: Listenindex | Y14: Zw. Ergebnis | Z14: Ergebnis
B16: 1 | C16: Basieren die Inhalte mindestens auf Annahmen und individuellem Erfahrungswissen der einzelnen Mitarbeiter bezüglich der Zielgruppe der Dokumentation? | F16: • Die Inhalte basieren auf Annahmen und individuellem Erfahrungswissen der einzelnen Mitarbeiter bezüglich der Zielgruppe der Dokumentation | H16: Bitte auswählen | J16: / | S16: =IF(H16="Nicht anwendbar","n.a.",0) -> 0 | T16: =IF(H16="Vollständig",1,0) -> 0 | U16: =IF(H16="In den meisten Fällen",0.75,0) -> 0 | V16: =IF(H16="In ein Paar Fällen",0.5,0) -> 0 | W16: =IF(H16="Gar nicht",0,0) -> 0 | X16: =IF(S16>0,"n.a.",SUM(S16:W16)) -> 0 | Y16: =X16 -> 0 | Z16: =IF(Y16<>"n.a.",SUM(Y16,Y17,Y19,Y22,Y26),NA()) -> 0 | AG16: =IF(X16>0.5,"Umgesetzt","Nicht umgesetzt") -> Nicht umgesetzt
B17: 2 | C17: Sind die Zielgruppen grundsätzlich bekannt? | F17: • Die Zielgruppen sind grundsätzlich bekannt • Eine grobe Zielgruppeneinteilung (z. B. „Wartungspersonal“) und eine erste Einschätzung zu deren Informationsbedürfnissen wird vorgenommen | H17: Bitte auswählen | J17: • bessere Fokussierung • erste Anpassung von Inhalten an unterschiedliche Nutzergruppen | S17: =IF(H17="Nicht anwendbar","n.a.",0) -> 0 | T17: =IF(H17="Vollständig",1,0) -> 0 | U17: =IF(H17="In den meisten Fällen",0.75,0) -> 0 | V17: =IF(H17="In ein Paar Fällen",0.5,0) -> 0 | W17: =IF(H17="Gar nicht",0,0) -> 0 | X17: =IFERROR(SUM(T17:W18)/COUNTIF(H17:H18,"<>Nicht anwendbar"),"n.a.") -> 0 | Y17: =IF(X16=1,X17,0) -> 0 | AG17: =IF(X17>0.5,"Umgesetzt","Nicht umgesetzt") -> Nicht umgesetzt
C18: Wird eine grobe Zielgruppeneinteilung (z.B. "Wartungspersonal") und eine erste Einschätzung zu deren Informationsbedürfnissen vorgenommen? | H18: Bitte auswählen | S18: =IF(H18="Nicht anwendbar","n.a.",0) -> 0 | T18: =IF(H18="Vollständig",1,0) -> 0 | U18: =IF(H18="In den meisten Fällen",0.75,0) -> 0 | V18: =IF(H18="In ein Paar Fällen",0.5,0) -> 0 | W18: =IF(H18="Gar nicht",0,0) -> 0 | AG18: =IF(X18>0.5,"Umgesetzt","Nicht umgesetzt") -> Nicht umgesetzt
B19: 3 | C19: Werden Zielgruppen systematisch analysiert (z. B. durch Interviews, Workshops)? | F19: • Zielgruppen werden systematisch analysiert (z. B. durch Interviews, Workshops) • Dokumentierte Zielgruppenprofile oder Personas liegen vor • Die typischen Nutzungsszenarien der Zielgruppen sind bekannt und beschrieben | H19: Bitte auswählen | J19: • höhere Passgenauigkeit der Inhalte • Reduzierung von Missverständnissen und Fehlbedingungen | S19: =IF(H19="Nicht anwendbar","n.a.",0) -> 0 | T19: =IF(H19="Vollständig",1,0) -> 0 | U19: =IF(H19="In den meisten Fällen",0.75,0) -> 0 | V19: =IF(H19="In ein Paar Fällen",0.5,0) -> 0 | W19: =IF(H19="Gar nicht",0,0) -> 0 | X19: =IFERROR(SUM(T19:W21)/COUNTIF(H19:H21,"<>Nicht anwendbar"),"n.a.") -> 0 | Y19: =IF(Y17=1,X19,0) -> 0
C20: Liegen dokumentierte Zielgruppenprofile oder Personas vor? | H20: Bitte auswählen | S20: =IF(H20="Nicht anwendbar","n.a.",0) -> 0 | T20: =IF(H20="Vollständig",1,0) -> 0 | U20: =IF(H20="In den meisten Fällen",0.75,0) -> 0 | V20: =IF(H20="In ein Paar Fällen",0.5,0) -> 0 | W20: =IF(H20="Gar nicht",0,0) -> 0
C21: Sind die typischen Nutzungsszenarien der Zielgruppen bekannt und beschrieben? | H21: Bitte auswählen | S21: =IF(H21="Nicht anwendbar","n.a.",0) -> 0 | T21: =IF(H21="Vollständig",1,0) -> 0 | U21: =IF(H21="In den meisten Fällen",0.75,0) -> 0 | V21: =IF(H21="In ein Paar Fällen",0.5,0) -> 0 | W21: =IF(H21="Gar nicht",0,0) -> 0
B22: 4 | C22: Werden die Erkenntnisse über Zielgruppen aktiv genutzt, um Inhalte und Medienauswahl zu steuern? | F22: • Die Erkenntnisse über Zielgruppen werden aktiv genutzt, um Inhalte und Medienauswahl zu steuern • Verbindliche Richtlinien oder Leitfäden stellen die zielgruppengerechte Aufbereitung der Dokumentation sicher • Kulturelle Nuancen auf internationalen Märkten sind bekannt und fließen in die Dokumentation ein • Zielgruppenwissen wird regelmäßig aktualisiert | H22: Bitte auswählen | J22: • kontinuierliche Verbesserung der Dokumentation • messbare Steigerung der Nutzerfreundlichkeit und Akzeptanz | S22: =IF(H22="Nicht anwendbar","n.a.",0) -> 0 | T22: =IF(H22="Vollständig",1,0) -> 0 | U22: =IF(H22="In den meisten Fällen",0.75,0) -> 0 | V22: =IF(H22="In ein Paar Fällen",0.5,0) -> 0 | W22: =IF(H22="Gar nicht",0,0) -> 0 | X22: =IFERROR(SUM(T22:W25)/COUNTIF(H22:H25,"<>Nicht anwendbar"),"n.a.") -> 0 | Y22: =IF(Y19=1,X22,0) -> 0
C23: Gibt es verbindliche Richtlinien oder Leitfäden, die die zielgruppengerechte Aufbereitung der Dokumentation sicherstellen? | H23: Bitte auswählen | S23: =IF(H23="Nicht anwendbar","n.a.",0) -> 0 | T23: =IF(H23="Vollständig",1,0) -> 0 | U23: =IF(H23="In den meisten Fällen",0.75,0) -> 0 | V23: =IF(H23="In ein Paar Fällen",0.5,0) -> 0 | W23: =IF(H23="Gar nicht",0,0) -> 0
